Workbook

Sheet README
B2: AI Munim, with Intent Guard: 8-quarter GMV and contribution projection (v2, clubhouse pricing)
B3: Paytm Build for India AI Hackathon, Mumbai | Track 1: Merchant Growth AI | Kamalika Poddar
B5: What this model does
B6: 1. Baseline: Paytm merchant GMV and device merchants, projected with FORECAST (linear) on 8 reported quarters, Q2 FY25 to Q1 FY27. GROWTH (exponential) is shown alongside as a cross-check.
B7: 2. AI Munim: an AI munim in the Paytm for Business app. Built for owners of 2-5 outlets, open to every merchant from one shop to a chain. It reads Paytm collections per outlet, bank statements and GST returns through the Account Aggregator (PPSL as FIU) and cash expenses logged by voice. It gives profit per outlet, a 90-day cash plan and shift checks, and acts only inside the owner's mandate (Intent Guard).
B8: 3. Pricing, the clubhouse: a monthly membership per business that includes the first 5 outlets; per-outlet add-ons in slabs above that (outlets 6-10, 11-20, 21+); and utility fees: a shift-check pass per outlet and a CA pack per business. Billed on its own in the Business app, with a notice before every charge. Not bundled with the Soundbox.
B9: 4. Capital tab: pre-approved lines from lending partners, open to every merchant, member or not. Lenders pay Paytm; merchants pay Paytm nothing for credit. Only drawdowns prompted by a member's cash plan are counted here; the rest is Paytm's existing lending.
B10: 5. Businesses are modelled in four size bands (1 outlet, 2-5, 6-20, 21+), each with its own share of device merchants, outlets and adoption.
B11: 6. Outputs: incremental GMV and contribution for 8 quarters from Q4 FY27 (Jan-Mar 2027 Mumbai pilot) to Q3 FY29, in three scenarios (Bear, Base, Bull).
B13: How to use it
B14: Change blue cells on Assumptions (and reported actuals on Baseline). Every other number is a formula and recalculates.
B15: Colour code: blue text = input | black text = formula | green text = link to another sheet | yellow fill = key assumption.
... B38: Caveat: reported figures come from Paytm's disclosures, regulators and press coverage (see Sources). Everything else on Assumptions is a team estimate for a hackathon pitch, not Paytm data. Paytm's own data (PANs by number of outlet IDs, device churn, lending take rates, enterprise book) would replace several estimates directly.

Sheet Assumptions
A1: Assumptions: AI Munim, with Intent Guard (v2, clubhouse pricing)
A2: Blue cells are inputs. Bear / Base / Bull columns feed the three scenario blocks on the Model sheet. Team estimates unless a source is named (Sources sheet). Prices are per month, excluding GST.
A4: ID | B4: Assumption | C4: Unit | D4: Bear | E4: Base | F4: Bull | L4: Why this number / source
A5: Common
A6: K1 | B6: Payment processing margin on incremental GMV | C6: % of GMV | D6: 0.0004 | E6: 0.0004 | F6: 0.0004 | L6: Paytm Q1 FY27: payment processing margin 'comfortably above 4 bps' (S1, S10). Held at 4 bps in all scenarios.
A7: K2 | B7: Paytm-processed GMV per outlet, multi-outlet members, before the Munim | C7: Rs / month | D7: 60000 | E7: 90000 | F7: 130000 | L7: Team estimate: outlets of multi-outlet businesses run busier counters than the average device merchant. Ceiling check on Baseline: ~Rs 1.5 lakh a month if all GMV came from device merchants.
A8: K3 | B8: Paytm-processed GMV of a single-outlet member, before the Munim | C8: Rs / month | D8: 30000 | E8: 45000 | F8: 60000 | L8: Team estimate: below the multi-outlet figure and well under the ~Rs 1.5 lakh ceiling.
A9: K4 | B9: Device subscription revenue per outlet | C9: Rs / month | D9: 80 | E9: 90 | F9: 100 | L9: ~Rs 90 per device a month in Q4 FY24 (S8); the Q1 FY27 release notes a modest YoY decline per device (S1).
A10: Who could join: businesses by size, as a share of device merchants
A11: S1 | B11: Single-outlet businesses | C11: % of device merchants | D11: 0.65 | E11: 0.7 | F11: 0.75 | L11: Team estimate. The rest of the count is multi-outlet businesses and second devices at the same counter (check on Summary).
A12: S2 | B12: Businesses running 2-5 outlets | C12: % of device merchants | D12: 0.02 | E12: 0.04 | F12: 0.06 | L12: Team estimate. At base, 4 businesses per 100 device merchants x 2.5 outlets = about 10 of every 100 devices. Paytm can replace this with its count of PANs with 2-5 outlet IDs.
A13: S3 | B13: Businesses running 6-20 outlets | C13: % of device merchants | D13: 0.001 | E13: 0.002 | F13: 0.003 | L13: Team estimate: small chains.
A14: S4 | B14: Businesses running 21 or more outlets (enterprise) | C14: % of device merchants | D14: 5e-05 | E14: 0.0001 | F14: 0.00015 | L14: Team estimate: about 2,200 chains at base by Q3 FY29. Paytm's enterprise book would replace this.
A15: S5 | B15: Average outlets, 2-5 band | C15: outlets | D15: 2.3 | E15: 2.5 | F15: 2.8 | L15: Team estimate.
A16: S6 | B16: Average outlets, 6-20 band | C16: outlets | D16: 8 | E16: 10 | F16: 12 | L16: Team estimate.
A17: S7 | B17: Average outlets, 21+ band | C17: outlets | D17: 60 | E17: 100 | F17: 150 | L17: Team estimate.
A18: Who pays: paying members as a share of businesses reached
A19: A1 | B19: Single-outlet businesses | C19: % of reached | D19: 0.005 | E19: 0.01 | F19: 0.02 | L19: Team estimate. A single shop gets less from the Munim (most owners run their own counter), so few pay. Reached in the app at little cost.
A20: A2 | B20: 2-5 outlet businesses | C20: % of reached | D20: 0.05 | E20: 0.1 | F20: 0.15 | L20: Team estimate, unchanged from the flat-price version even though this band now pays less (an upside we don't count). Paid from day one; no free tier.
A21: A3 | B21: 6-20 outlet businesses | C21: % of reached | D21: 0.04 | E21: 0.08 | F21: 0.12 | L21: Team estimate.
A22: A4 | B22: 21+ outlet businesses (enterprise) | C22: % of reached | D22: 0.01 | E22: 0.03 | F22: 0.06 | L22: Team estimate. Enterprise deals are sales-led and slow; many chains already run an ERP.
A23: A5 | B23: Extra outlets opened per 100 paying businesses per year (cash plan and credit) | C23: per 100 / year | D23: 1 | E23: 2 | F23: 4 | L23: Team estimate. New outlets come onto a Paytm device and the Munim.
A24: Pricing: the clubhouse (per month, excluding GST)
A25: P1 | B25: Membership per business, includes the first 5 outlets | C25: Rs / month | D25: 149 | E25: 199 | F25: 299 | L25: The membership: outlet view, staff roles, profit per outlet, 90-day cash plan, Intent Guard, evidence log. Anchors: the earlier flat price of Rs 199 per outlet; Soundbox rental runs Rs 125-150 (S7).
A26: P2 | B26: Add-on per outlet, outlets 6-10 | C26: Rs / outlet / month | D26: 29 | E26: 49 | F26: 79 | L26: Kept small so the step after 5 included outlets is gentle.
A27: P3 | B27: Add-on per outlet, outlets 11-20 | C27: Rs / outlet / month | D27: 49 | E27: 79 | F27: 99 | L27: Team estimate.
A28: P4 | B28: Add-on per outlet, outlets 21 and above | C28: Rs / outlet / month | D28: 69 | E28: 99 | F28: 149 | L28: List price. Chains this size will negotiate.
A29: P5 | B29: Shift-check pass, per outlet | C29: Rs / outlet / month | D29: 79 | E29: 99 | F29: 149 | L29: Utility fee, unlimited checks. Priced above its own AI and photo-check cost.
A30: P6 | B30: Pass uptake, single-outlet members | C30: % of outlets | D30: 0.05 | E30: 0.1 | F30: 0.2 | L30: Team estimate: most single shops are run by the owner.
A31: P7 | B31: Pass uptake, multi-outlet members | C31: % of outlets | D31: 0.3 | E31: 0.5 | F31: 0.7 | L31: Team estimate: staffed counters are where shift checks matter.
A32: P8 | B32: CA pack, per business | C32: Rs / month | D32: 79 | E32: 99 | F32: 149 | L32: Utility fee: a books-ready monthly pack (charges by payment type, GST for input credit) for the business's CA.
A33: P9 | B33: CA pack uptake | C33: % of members | D33: 0.1 | E33: 0.2 | F33: 0.3 | L33: Team estimate.
A34: Capital tab: open to every merchant; only drawdowns prompted by a member's cash plan are counted
A35: C1 | B35: Members with a pre-approved line (1-20 outlets; chains of 21+ use their bank limits) | C35: % of members | D35: 0.3 | E35: 0.45 | F35: 0.6 | L35: The lender takes its own AA consent and runs its rules engine upfront. Benchmark: public-sector banks' digital MSME model approved ~47% of applications in Apr-Oct FY26 (S12).
A36: C2 | B36: Drawdowns per year per member with a line | C36: per year | D36: 1.5 | E36: 2 | F36: 3 | L36: Team estimate: festive stock-ups, wedding season, a new outlet.
A37: C3 | B37: Average drawdown, per outlet of the business | C37: Rs per outlet | D37: 40000 | E37: 80000 | F37: 120000 | L37: Team estimate: Rs 2 lakh for a 2.5-outlet business at base, as in v1. Paytm business loans run up to Rs 10 lakh over 3-36 months (S29).
A38: C4 | B38: Paytm revenue per drawdown (distribution and collection support), paid by the lender | C38: % of drawdown | D38: 0.015 | E38: 0.02 | F38: 0.025 | L38: Team estimate. Paytm doesn't publish take rates. Under RBI's digital lending rules the lender pays this, never the borrower (S30).
A39: C5 | B39: Collection and servicing per drawdown (reminders, repayment follow-up) | C39: % of drawdown | D39: 0.005 | E39: 0.003 | F39: 0.002 | L39: Team estimate. The support Paytm is paid for (C4) has its own cost.
A40: C6 | B40: Paytm credit-loss sharing | C40: % of drawdown | D40: 0.0075 | E40: 0.004 | F40: 0 | L40: Team estimate. RBI caps default-loss guarantees at 5% of a loan portfolio (S26); whether Paytm offers one isn't public.
A41: Growth levers (applied to the Paytm GMV of member outlets)
A42: G1 | B42: Sales increase from the cash plan (stock ready before peaks) | C42: % of sales | D42: 0.01 | E42: 0.02 | F42: 0.03 | L42: Team estimate, tested against matched outlets without the Munim.
A43: G2 | B43: Collections moved to Paytm's outlet QRs (multi-outlet members) | C43: % of Paytm GMV | D43: 0.01 | E43: 0.03 | F43: 0.05 | L43: Owners route more sales to Paytm's outlet-tagged QRs because that makes outlet profit exact; other QRs only appear business-wide in bank data.
A44: G3 | B44: Leakage recovered that lands on Paytm (outlets with the pass) | C44: % of Paytm GMV | D44: 0.005 | E44: 0.01 | F44: 0.02 | L44: Team estimate: shift checks make unrecorded sales visible.
A45: G4 | B45: Drop in annual device churn for member outlets | C45: percentage points / year | D45: 0.01 | E45: 0.02 | F45: 0.03 | L45: Team estimate. Paytm does not disclose device churn.
A46: Costs
A47: V1 | B47: AI per member outlet (cash plan, voice, bank narrations, shift forecasts) | C47: Rs / outlet / month | D47: 40 | E47: 25 | F47: 15 | L47: Team estimate.
A48: V2 | B48: Shift handovers per outlet per day | C48: per day | D48: 2 | E48: 2 | F48: 2 | L48: Two shifts a day.
A49: V3 | B49: Photo check per handover (2-3 high-value shelves) | C49: Rs per handover | D49: 1 | E49: 0.6 | F49: 0.3 | L49: Team estimate.
A50: V4 | B50: Account Aggregator data per business (bank daily, GST monthly) | C50: Rs / month | D50: 25 | E50: 15 | F50: 10 | L50: Team estimate. AAs charge FIUs per fetch.
A51: V5 | B51: Support per member outlet | C51: Rs / outlet / month | D51: 20 | E51: 12 | F51: 8 | L51: Team estimate: Rs 30 for a 2.5-outlet business at base, as in v1; scales with outlets for chains.
A52: V6 | B52: Onboarding per new member business (consents, rules, roles) | C52: Rs per business | D52: 250 | E52: 150 | F52: 100 | L52: Team estimate.
A53: V7 | B53: Onboarding per outlet of a new member (mapping QRs and devices) | C53: Rs per outlet | D53: 200 | E53: 140 | F53: 100 | L53: Team estimate: Rs 500 for a 2.5-outlet business at base, as in v1.
A54: V8 | B54: Sales and integration per new enterprise member (21+ outlets) | C54: Rs per business | D54: 100000 | E54: 50000 | F54: 25000 | L54: Team estimate.
A55: Merchant view
A56: MV1 | B56: Sales per outlet, 2-5 outlet member (all channels, including cash) | C56: Rs / month | D56: 250000 | E56: 350000 | F56: 500000 | L56: Team estimate.
A57: MV2 | B57: Sales of a single-outlet member (all channels) | C57: Rs / month | D57: 150000 | E57: 200000 | F57: 300000 | L57: Team estimate.
A58: MV3 | B58: Gross margin | C58: % of sales | D58: 0.09 | E58: 0.1 | F58: 0.12 | L58: Kirana margins run ~5-10% on national brands and 10-18% on regional brands (S14); multi-category shops sit higher.
A59: MV4 | B59: Leakage recovered with the shift-check pass | C59: % of sales | D59: 0.003 | E59: 0.005 | F59: 0.01 | L59: Team estimate. Shown in the product as a range, never as an accusation; tested in the pilot.
A61: Rollout ramp (Paytm controls the pace, so the same in all scenarios and all bands)
B62: Quarter | D62: Q4 FY27 | E62: Q1 FY28 | F62: Q2 FY28 | G62: Q3 FY28 | H62: Q4 FY28 | I62: Q1 FY29 | J62: Q2 FY29 | K62: Q3 FY29
A63: MR | B63: Share of businesses the Munim reaches | C63: % of businesses | D63: 0.05 | E63: 0.15 | F63: 0.3 | G63: 0.45 | H63: 0.6 | I63: 0.7 | J63: 0.8 | K63: 0.85 | L63: Q4 FY27 Mumbai pilot; then national: in-app for single shops, Paytm's field force for multi-outlet owners, sales for chains.
A65: Structural rules built into the formulas
A66: Rule 1 | B66: Paying members = businesses in the band x share reached x adoption. Outlets = members x average outlets in the band (1 for single shops), plus extra outlets opened.
A67: Rule 2 | B67: Each member pays the membership (first 5 outlets included) plus outlet add-ons by slab: outlets 6-10 at P2, 11-20 at P3, 21+ at P4, worked out on the band's average outlet count.
A68: Rule 3 | B68: Utility fees are optional: the shift-check pass per outlet (P5, taken by P6/P7 of outlets) and the CA pack per business (P8, taken by P9 of members).
A69: Rule 4 | B69: The Capital tab is open to every merchant and never needs a membership. Only drawdowns by members with a line, prompted by their cash plan, are counted. Chains of 21+ outlets use their bank limits. Paytm's share is paid by the lender (C4).
A70: Rule 5 | B70: GMV levers apply to the Paytm GMV of member outlets. Collections moved to outlet QRs apply to multi-outlet members only; leakage recovered applies to outlets with the pass only. Supplier payments made from drawdowns are not GMV.
A71: Rule 6 | B71: Outlets kept by lower device churn and extra outlets opened are cumulative; they carry device subscription revenue (K4).
A72: Rule 7 | B72: Baseline GMV and device merchants use FORECAST (linear) on 8 reported quarters; GROWTH (exponential) is a cross-check.
A73: Rule 8 | B73: Contribution = revenue - variable costs. Fixed engineering, platform and field-force salary costs are excluded.

Sheet Baseline
A1: Baseline: Paytm merchant GMV and device merchants
A2: Rows 5-12 are reported actuals (blue). Rows 13-22 are FORECAST (linear) on those 8 quarters. Column G is GROWTH (exponential) as a cross-check. The model uses the linear forecast.
A4: x (period) | B4: Quarter | C4: Months | D4: Type | E4: Merchant GMV (Rs lakh crore) | F4: GMV YoY | G4: Cross-check: GROWTH (Rs lakh crore) | H4: Device merchants (crore) | I4: Source / method
A5: 1 | B5: Q2 FY25 | C5: Jul-Sep 2024 | D5: Actual | E5: 4.5 | H5: 1.12 | I5: GMV: S5 (Q3 FY25 GMV up 13% QoQ from Rs 4.5 lakh crore). Device merchants: derived, 1.17 crore at Dec-24 minus 5 lakh added that quarter (S5).
A6: 2 | B6: Q3 FY25 | C6: Oct-Dec 2024 | D6: Actual | E6: 5 | H6: 1.17 | I6: S5
A7: 3 | B7: Q4 FY25 | C7: Jan-Mar 2025 | D7: Actual | E7: 5.1 | H7: 1.24 | I7: S4
A8: 4 | B8: Q1 FY26 | C8: Apr-Jun 2025 | D8: Actual | E8: 5.4 | H8: 1.3 | I8: S1 (Jun-25 column of the Q1 FY27 release)
A9: 5 | B9: Q2 FY26 | C9: Jul-Sep 2025 | D9: Actual | E9: 5.67 | F9: =E9/E5-1 -> 0.26 | H9: 1.37 | I9: S2
A10: 6 | B10: Q3 FY26 | C10: Oct-Dec 2025 | D10: Actual | E10: 6.2 | F10: =E10/E6-1 -> 0.24 | H10: 1.44 | I10: GMV: S3. Device merchants: S6
A11: 7 | B11: Q4 FY26 | C11: Jan-Mar 2026 | D11: Actual | E11: 6.5 | F11: =E11/E7-1 -> 0.2745098 | H11: 1.51 | I11: S1 (Mar-26 column)
A12: 8 | B12: Q1 FY27 | C12: Apr-Jun 2026 | D12: Actual | E12: 7.1 | F12: =E12/E8-1 -> 0.31481481 | H12: 1.57 | I12: S1, S10
A13: 9 | B13: Q2 FY27 | C13: Jul-Sep 2026 | D13: Forecast | E13: =FORECAST(A13,$E$5:$E$12,$A$5:$A$12) -> 7.2517857 | F13: =E13/E9-1 -> 0.27897455 | G13: =GROWTH($E$5:$E$12,$A$5:$A$12,A13) -> 7.4103976 | H13: =FORECAST(A13,$H$5:$H$12,$A$5:$A$12) -> 1.6357143 | I13: FORECAST (linear) on rows 5-12. Not yet reported; bridges to the projection window.
A14: 10 | B14: Q3 FY27 | C14: Oct-Dec 2026 | D14: Forecast | E14: =FORECAST(A14,$E$5:$E$12,$A$5:$A$12) -> 7.6002381 | F14: =E14/E10-1 -> 0.22584485 | G14: =GROWTH($E$5:$E$12,$A$5:$A$12,A14) -> 7.8778783 | H14: =FORECAST(A14,$H$5:$H$12,$A$5:$A$12) -> 1.7014286 | I14: FORECAST (linear) on rows 5-12. Not yet reported; bridges to the projection window.
A15: 11 | B15: Q4 FY27 | C15: Jan-Mar 2027 | D15: Forecast | E15: =FORECAST(A15,$E$5:$E$12,$A$5:$A$12) -> 7.9486905 | F15: =E15/E11-1 -> 0.22287546 | G15: =GROWTH($E$5:$E$12,$A$5:$A$12,A15) -> 8.3748497 | H15: =FORECAST(A15,$H$5:$H$12,$A$5:$A$12) -> 1.7671429 | I15: FORECAST (linear) on rows 5-12
A16: 12 | B16: Q1 FY28 | C16: Apr-Jun 2027 | D16: Forecast | E16: =FORECAST(A16,$E$5:$E$12,$A$5:$A$12) -> 8.2971429 | F16: =E16/E12-1 -> 0.16861167 | G16: =GROWTH($E$5:$E$12,$A$5:$A$12,A16) -> 8.9031723 | H16: =FORECAST(A16,$H$5:$H$12,$A$5:$A$12) -> 1.8328571 | I16: FORECAST (linear) on rows 5-12
A17: 13 | B17: Q2 FY28 | C17: Jul-Sep 2027 | D17: Forecast | E17: =FORECAST(A17,$E$5:$E$12,$A$5:$A$12) -> 8.6455952 | F17: =E17/E13-1 -> 0.19220225 | G17: =GROWTH($E$5:$E$12,$A$5:$A$12,A17) -> 9.4648238 | H17: =FORECAST(A17,$H$5:$H$12,$A$5:$A$12) -> 1.8985714 | I17: FORECAST (linear) on rows 5-12
A18: 14 | B18: Q3 FY28 | C18: Oct-Dec 2027 | D18: Forecast | E18: =FORECAST(A18,$E$5:$E$12,$A$5:$A$12) -> 8.9940476 | F18: =E18/E14-1 -> 0.18339024 | G18: =GROWTH($E$5:$E$12,$A$5:$A$12,A18) -> 10.061907 | H18: =FORECAST(A18,$H$5:$H$12,$A$5:$A$12) -> 1.9642857 | I18: FORECAST (linear) on rows 5-12
A19: 15 | B19: Q4 FY28 | C19: Jan-Mar 2028 | D19: Forecast | E19: =FORECAST(A19,$E$5:$E$12,$A$5:$A$12) -> 9.3425 | F19: =E19/E15-1 -> 0.17535084 | G19: =GROWTH($E$5:$E$12,$A$5:$A$12,A19) -> 10.696656 | H19: =FORECAST(A19,$H$5:$H$12,$A$5:$A$12) -> 2.03 | I19: FORECAST (linear) on rows 5-12
A20: 16 | B20: Q1 FY29 | C20: Apr-Jun 2028 | D20: Forecast | E20: =FORECAST(A20,$E$5:$E$12,$A$5:$A$12) -> 9.6909524 | F20: =E20/E16-1 -> 0.16798669 | G20: =GROWTH($E$5:$E$12,$A$5:$A$12,A20) -> 11.371449 | H20: =FORECAST(A20,$H$5:$H$12,$A$5:$A$12) -> 2.0957143 | I20: FORECAST (linear) on rows 5-12
A21: 17 | B21: Q2 FY29 | C21: Jul-Sep 2028 | D21: Forecast | E21: =FORECAST(A21,$E$5:$E$12,$A$5:$A$12) -> 10.039405 | F21: =E21/E17-1 -> 0.16121614 | G21: =GROWTH($E$5:$E$12,$A$5:$A$12,A21) -> 12.08881 | H21: =FORECAST(A21,$H$5:$H$12,$A$5:$A$12) -> 2.1614286 | I21: FORECAST (linear) on rows 5-12
A22: 18 | B22: Q3 FY29 | C22: Oct-Dec 2028 | D22: Forecast | E22: =FORECAST(A22,$E$5:$E$12,$A$5:$A$12) -> 10.387857 | F22: =E22/E18-1 -> 0.15497022 | G22: =GROWTH($E$5:$E$12,$A$5:$A$12,A22) -> 12.851426 | H22: =FORECAST(A22,$H$5:$H$12,$A$5:$A$12) -> 2.2271429 | I22: FORECAST (linear) on rows 5-12
A25: Reported reference points (Q1 FY27, quarter ended 30 June 2026), checks, earlier versions and options
B26: Revenue from operations | D26: Rs crore | F26: 2448 | I26: S10 (up 28% YoY)
B27: Contribution profit | D27: Rs crore | F27: 1350 | I27: S10 (up 17% YoY)
B28: Contribution margin | D28: % of revenue | F28: 0.55 | I28: S10
B29: EBITDA | D29: Rs crore | F29: 203 | I29: S10 (8% margin)
B30: Profit after tax | D30: Rs crore | F30: 220 | I30: S10 (up 79% YoY)
B31: Financial services revenue (merchant loans, personal loans, insurance distribution) | D31: Rs crore | F31: 814 | I31: S10 (up 45% YoY)
B32: Net payment revenue, excluding PIDF | D32: Rs crore | F32: 601 | I32: S1, S10
B33: Net payment revenue per Rs of GMV | D33: bps | F33: =F32/(E12*100000)*10000 -> 8.4647887 | I33: Formula. Paytm reports 8.4 bps (S1).
B34: Ceiling: GMV per device merchant per month if all GMV came from device merchants | D34: Rs / month | F34: =E12*1000000000000/(H12*10000000)/3 -> 150743.1 | I34: Formula. Upper bound used to sanity-check K2 and K3.
B35: Q3 FY29 baseline: GROWTH cross-check vs FORECAST | D35: % above linear | F35: =G22/E22-1 -> 0.2371585 | I35: Formula. How conservative the linear baseline is.
B36: Previous version of this model (flat Rs 199 per outlet, 2-5 outlet businesses only): base contribution over the same 8 quarters | D36: Rs crore | F36: 45.87 | I36: AI_Munim_Projection.xlsx v1, Summary, base case.
B37: Previous version of this model: base incremental GMV over the same 8 quarters | D37: Rs crore | F37: 1792.07 | I37: AI_Munim_Projection.xlsx v1, Summary, base case.
B38: Earlier option, dropped: Mohalla Network, base contribution over the same 8 quarters | D38: Rs crore | F38: 29.52 | I38: Mohalla_GMV_Projection.xlsx, Summary, base case.
B39: Earlier option, parked: Restock Agent, base contribution over the same 8 quarters | D39: Rs crore | F39: 26.22 | I39: Restock_Care_Projection.xlsx, Summary, base case.
B40: Earlier option, parked: Restock Agent, supplier payments new to Paytm over the same 8 quarters | D40: Rs crore | F40: 20419.56 | I40: Restock_Care_Projection.xlsx, Summary, base case (5.35 lakh active grocery shops).
B41: Earlier option, folded in: Soundbox Care, base contribution over the same 8 quarters | D41: Rs crore | F41: 70.01 | I41: Restock_Care_Projection.xlsx, Summary, base case (mostly Paytm's own device-service savings).

Sheet Model
A1: Model: AI Munim, with Intent Guard, quarter by quarter, by business size
A2: Every cell is a formula. Assumption references: Bear = Assumptions column D, Base = E, Bull = F. Column L sums flows over the 8 quarters; stock rows show Q3 FY29; ratio rows divide the 8-quarter totals.
A4: # | B4: Quarter | C4: Unit | D4: Q4 FY27 | E4: Q1 FY28 | F4: Q2 FY28 | G4: Q3 FY28 | H4: Q4 FY28 | I4: Q1 FY29 | J4: Q2 FY29 | K4: Q3 FY29 | L4: 8-qtr total
B5: Months | D5: Jan-Mar 2027 | E5: Apr-Jun 2027 | F5: Jul-Sep 2027 | G5: Oct-Dec 2027 | H5: Jan-Mar 2028 | I5: Apr-Jun 2028 | J5: Jul-Sep 2028 | K5: Oct-Dec 2028
B6: Baseline period index (x) | D6: =Baseline!A15 -> 11 | E6: =Baseline!A16 -> 12 | F6: =Baseline!A17 -> 13 | G6: =Baseline!A18 -> 14 | H6: =Baseline!A19 -> 15 | I6: =Baseline!A20 -> 16 | J6: =Baseline!A21 -> 17 | K6: =Baseline!A22 -> 18
A8: BEAR scenario (Assumptions column D)
B9: Device merchants and rollout
A10: 1 | B10: Device merchants, baseline | C10: lakh | D10: =Baseline!H15*100 -> 176.71429 | E10: =Baseline!H16*100 -> 183.28571 | F10: =Baseline!H17*100 -> 189.85714 | G10: =Baseline!H18*100 -> 196.42857 | H10: =Baseline!H19*100 -> 203 | I10: =Baseline!H20*100 -> 209.57143 | J10: =Baseline!H21*100 -> 216.14286 | K10: =Baseline!H22*100 -> 222.71429 | L10: =K10 -> 222.71429
A11: 2 | B11: Share of businesses reached (rollout) | C11: % of businesses | D11: =Assumptions!D$63 -> 0.05 | E11: =Assumptions!E$63 -> 0.15 | F11: =Assumptions!F$63 -> 0.3 | G11: =Assumptions!G$63 -> 0.45 | H11: =Assumptions!H$63 -> 0.6 | I11: =Assumptions!I$63 -> 0.7 | J11: =Assumptions!J$63 -> 0.8 | K11: =Assumptions!K$63 -> 0.85 | L11: =K11 -> 0.85
B12: Band 1: Single-outlet businesses
A13: 3 | B13: Businesses in this band | C13: lakh | D13: =D10*Assumptions!$D$11 -> 114.86429 | E13: =E10*Assumptions!$D$11 -> 119.13571 | F13: =F10*Assumptions!$D$11 -> 123.40714 | G13: =G10*Assumptions!$D$11 -> 127.67857 | H13: =H10*Assumptions!$D$11 -> 131.95 | I13: =I10*Assumptions!$D$11 -> 136.22143 | J13: =J10*Assumptions!$D$11 -> 140.49286 | K13: =K10*Assumptions!$D$11 -> 144.76429 | L13: =K13 -> 144.76429
A14: 4 | B14: Paying members | C14: lakh | D14: =D13*D11*Assumptions!$D$19 -> 0.028716071 | E14: =E13*E11*Assumptions!$D$19 -> 0.089351786 | F14: =F13*F11*Assumptions!$D$19 -> 0.18511071 | G14: =G13*G11*Assumptions!$D$19 -> 0.28727679 | H14: =H13*H11*Assumptions!$D$19 -> 0.39585 | I14: =I13*I11*Assumptions!$D$19 -> 0.476775 | J14: =J13*J11*Assumptions!$D$19 -> 0.56197143 | K14: =K13*K11*Assumptions!$D$19 -> 0.61524821 | L14: =K14 -> 0.61524821
A15: 5 | B15: New paying members | C15: lakh | D15: =MAX(0,D14-N(C14)) -> 0.028716071 | E15: =MAX(0,E14-N(D14)) -> 0.060635714 | F15: =MAX(0,F14-N(E14)) -> 0.095758929 | G15: =MAX(0,G14-N(F14)) -> 0.10216607 | H15: =MAX(0,H14-N(G14)) -> 0.10857321 | I15: =MAX(0,I14-N(H14)) -> 0.080925 | J15: =MAX(0,J14-N(I14)) -> 0.085196429 | K15: =MAX(0,K14-N(J14)) -> 0.053276786 | L15: =SUM(D15:K15) -> 0.61524821
A16: 6 | B16: Member outlets | C16: lakh | D16: =D14*1 -> 0.028716071 | E16: =E14*1 -> 0.089351786 | F16: =F14*1 -> 0.18511071 | G16: =G14*1 -> 0.28727679 | H16: =H14*1 -> 0.39585 | I16: =I14*1 -> 0.476775 | J16: =J14*1 -> 0.56197143 | K16: =K14*1 -> 0.61524821 | L16: =K16 -> 0.61524821
A17: 7 | B17: Extra outlets opened (cumulative) | C17: lakh | D17: =N(C17)+D14*Assumptions!$D$23/100/4 -> 7.1790179e-05 | E17: =N(D17)+E14*Assumptions!$D$23/100/4 -> 0.00029516964 | F17: =N(E17)+F14*Assumptions!$D$23/100/4 -> 0.00075794643 | G17: =N(F17)+G14*Assumptions!$D$23/100/4 -> 0.0014761384 | H17: =N(G17)+H14*Assumptions!$D$23/100/4 -> 0.0024657634 | I17: =N(H17)+I14*Assumptions!$D$23/100/4 -> 0.0036577009 | J17: =N(I17)+J14*Assumptions!$D$23/100/4 -> 0.0050626295 | K17: =N(J17)+K14*Assumptions!$D$23/100/4 -> 0.00660075 | L17: =K17 -> 0.00660075
A18: 8 | B18: Member outlets, including new ones | C18: lakh | D18: =D16+D17 -> 0.028787862 | E18: =E16+E17 -> 0.089646955 | F18: =F16+F17 -> 0.18586866 | G18: =G16+G17 -> 0.28875292 | H18: =H16+H17 -> 0.39831576 | I18: =I16+I17 -> 0.4804327 | J18: =J16+J17 -> 0.56703406 | K18: =K16+K17 -> 0.62184896 | L18: =K18 -> 0.62184896
A19: 9 | B19: Outlets with the shift-check pass | C19: lakh | D19: =D18*Assumptions!$D$30 -> 0.0014393931 | E19: =E18*Assumptions!$D$30 -> 0.0044823478 | F19: =F18*Assumptions!$D$30 -> 0.009293433 | G19: =G18*Assumptions!$D$30 -> 0.014437646 | H19: =H18*Assumptions!$D$30 -> 0.019915788 | I19: =I18*Assumptions!$D$30 -> 0.024021635 | J19: =J18*Assumptions!$D$30 -> 0.028351703 | K19: =K18*Assumptions!$D$30 -> 0.031092448 | L19: =K19 -> 0.031092448
A20: 10 | B20: Members with a pre-approved line | C20: lakh | D20: =D14*Assumptions!$D$35 -> 0.0086148214 | E20: =E14*Assumptions!$D$35 -> 0.026805536 | F20: =F14*Assumptions!$D$35 -> 0.055533214 | G20: =G14*Assumptions!$D$35 -> 0.086183036 | H20: =H14*Assumptions!$D$35 -> 0.118755 | I20: =I14*Assumptions!$D$35 -> 0.1430325 | J20: =J14*Assumptions!$D$35 -> 0.16859143 | K20: =K14*Assumptions!$D$35 -> 0.18457446 | L20: =K20 -> 0.18457446
A21: 11 | B21: Drawdowns prompted by the cash plan | C21: lakh | D21: =D20*Assumptions!$D$36/4 -> 0.003230558 | E21: =E20*Assumptions!$D$36/4 -> 0.010052076 | F21: =F20*Assumptions!$D$36/4 -> 0.020824955 | G21: =G20*Assumptions!$D$36/4 -> 0.032318638 | H21: =H20*Assumptions!$D$36/4 -> 0.044533125 | I21: =I20*Assumptions!$D$36/4 -> 0.053637188 | J21: =J20*Assumptions!$D$36/4 -> 0.063221786 | K21: =K20*Assumptions!$D$36/4 -> 0.069215424 | L21: =SUM(D21:K21) -> 0.29703375
A22: 12 | B22: Drawdown value | C22: Rs crore | D22: =D21*Assumptions!$D$37*1/100 -> 1.2922232 | E22: =E21*Assumptions!$D$37*1/100 -> 4.0208304 | F22: =F21*Assumptions!$D$37*1/100 -> 8.3299821 | G22: =G21*Assumptions!$D$37*1/100 -> 12.927455 | H22: =H21*Assumptions!$D$37*1/100 -> 17.81325 | I22: =I21*Assumptions!$D$37*1/100 -> 21.454875 | J22: =J21*Assumptions!$D$37*1/100 -> 25.288714 | K22: =K21*Assumptions!$D$37*1/100 -> 27.68617 | L22: =SUM(D22:K22) -> 118.8135
A23: 13 | B23: Paytm GMV of member outlets before the Munim (reference) | C23: Rs crore | D23: =D16*Assumptions!$D$8*3/100 -> 25.844464 | E23: =E16*Assumptions!$D$8*3/100 -> 80.416607 | F23: =F16*Assumptions!$D$8*3/100 -> 166.59964 | G23: =G16*Assumptions!$D$8*3/100 -> 258.54911 | H23: =H16*Assumptions!$D$8*3/100 -> 356.265 | I23: =I16*Assumptions!$D$8*3/100 -> 429.0975 | J23: =J16*Assumptions!$D$8*3/100 -> 505.77429 | K23: =K16*Assumptions!$D$8*3/100 -> 553.72339 | L23: =SUM(D23:K23) -> 2376.27
A24: 14 | B24: GMV: extra sales from the cash plan | C24: Rs crore | D24: =D23*Assumptions!$D$42 -> 0.25844464 | E24: =E23*Assumptions!$D$42 -> 0.80416607 | F24: =F23*Assumptions!$D$42 -> 1.6659964 | G24: =G23*Assumptions!$D$42 -> 2.5854911 | H24: =H23*Assumptions!$D$42 -> 3.56265 | I24: =I23*Assumptions!$D$42 -> 4.290975 | J24: =J23*Assumptions!$D$42 -> 5.0577429 | K24: =K23*Assumptions!$D$42 -> 5.5372339 | L24: =SUM(D24:K24) -> 23.7627
A25: 15 | B25: GMV: leakage recovered (outlets with the pass) | C25: Rs crore | D25: =D19*Assumptions!$D$8*3/100*Assumptions!$D$44 -> 0.0064772689 | E25: =E19*Assumptions!$D$8*3/100*Assumptions!$D$44 -> 0.020170565 | F25: =F19*Assumptions!$D$8*3/100*Assumptions!$D$44 -> 0.041820449 | G25: =G19*Assumptions!$D$8*3/100*Assumptions!$D$44 -> 0.064969408 | H25: =H19*Assumptions!$D$8*3/100*Assumptions!$D$44 -> 0.089621047 | I25: =I19*Assumptions!$D$8*3/100*Assumptions!$D$44 -> 0.10809736 | J25: =J19*Assumptions!$D$8*3/100*Assumptions!$D$44 -> 0.12758266 | K25: =K19*Assumptions!$D$8*3/100*Assumptions!$D$44 -> 0.13991602 | L25: =SUM(D25:K25) -> 0.59865477
A26: 16 | B26: Outlets kept by lower device churn (cumulative) | C26: lakh | D26: =N(C26)+D18*Assumptions!$D$45/4 -> 7.1969654e-05 | E26: =N(D26)+E18*Assumptions!$D$45/4 -> 0.00029608704 | F26: =N(E26)+F18*Assumptions!$D$45/4 -> 0.00076075869 | G26: =N(F26)+G18*Assumptions!$D$45/4 -> 0.001482641 | H26: =N(G26)+H18*Assumptions!$D$45/4 -> 0.0024784304 | I26: =N(H26)+I18*Assumptions!$D$45/4 -> 0.0036795122 | J26: =N(I26)+J18*Assumptions!$D$45/4 -> 0.0050970973 | K26: =N(J26)+K18*Assumptions!$D$45/4 -> 0.0066517197 | L26: =K26 -> 0.0066517197
A27: 17 | B27: GMV: kept by lower device churn | C27: Rs crore | D27: =D26*Assumptions!$D$8*3/100 -> 0.064772689 | E27: =E26*Assumptions!$D$8*3/100 -> 0.26647834 | F27: =F26*Assumptions!$D$8*3/100 -> 0.68468282 | G27: =G26*Assumptions!$D$8*3/100 -> 1.3343769 | H27: =H26*Assumptions!$D$8*3/100 -> 2.2305874 | I27: =I26*Assumptions!$D$8*3/100 -> 3.3115609 | J27: =J26*Assumptions!$D$8*3/100 -> 4.5873876 | K27: =K26*Assumptions!$D$8*3/100 -> 5.9865477 | L27: =SUM(D27:K27) -> 18.466394
A28: 18 | B28: GMV: extra outlets opened | C28: Rs crore | D28: =D17*Assumptions!$D$8*3/100 -> 0.064611161 | E28: =E17*Assumptions!$D$8*3/100 -> 0.26565268 | F28: =F17*Assumptions!$D$8*3/100 -> 0.68215179 | G28: =G17*Assumptions!$D$8*3/100 -> 1.3285246 | H28: =H17*Assumptions!$D$8*3/100 -> 2.2191871 | I28: =I17*Assumptions!$D$8*3/100 -> 3.2919308 | J28: =J17*Assumptions!$D$8*3/100 -> 4.5563665 | K28: =K17*Assumptions!$D$8*3/100 -> 5.940675 | L28: =SUM(D28:K28) -> 18.3491
A29: 19 | B29: Incremental GMV | C29: Rs crore | D29: =D24+D25+D27+D28 -> 0.39430576 | E29: =E24+E25+E27+E28 -> 1.3564677 | F29: =F24+F25+F27+F28 -> 3.0746515 | G29: =G24+G25+G27+G28 -> 5.3133619 | H29: =H24+H25+H27+H28 -> 8.1020455 | I29: =I24+I25+I27+I28 -> 11.002564 | J29: =J24+J25+J27+J28 -> 14.32908 | K29: =K24+K25+K27+K28 -> 17.604373 | L29: =SUM(D29:K29) -> 61.176849
A30: 20 | B30: Revenue: membership | C30: Rs crore | D30: =D14*Assumptions!$D$25*3/100 -> 0.12836084 | E30: =E14*Assumptions!$D$25*3/100 -> 0.39940248 | F30: =F14*Assumptions!$D$25*3/100 -> 0.82744489 | G30: =G14*Assumptions!$D$25*3/100 -> 1.2841272 | H30: =H14*Assumptions!$D$25*3/100 -> 1.7694495 | I30: =I14*Assumptions!$D$25*3/100 -> 2.1311843 | J30: =J14*Assumptions!$D$25*3/100 -> 2.5120123 | K30: =K14*Assumptions!$D$25*3/100 -> 2.7501595 | L30: =SUM(D30:K30) -> 11.802141
A31: 21 | B31: Revenue: shift-check passes | C31: Rs crore | D31: =D19*Assumptions!$D$29*3/100 -> 0.0034113616 | E31: =E19*Assumptions!$D$29*3/100 -> 0.010623164 | F31: =F19*Assumptions!$D$29*3/100 -> 0.022025436 | G31: =G19*Assumptions!$D$29*3/100 -> 0.034217222 | H31: =H19*Assumptions!$D$29*3/100 -> 0.047200418 | I31: =I19*Assumptions!$D$29*3/100 -> 0.056931275 | J31: =J19*Assumptions!$D$29*3/100 -> 0.067193536 | K31: =K19*Assumptions!$D$29*3/100 -> 0.073689102 | L31: =SUM(D31:K31) -> 0.31529151
A32: 22 | B32: Revenue: CA packs | C32: Rs crore | D32: =D14*Assumptions!$D$33*Assumptions!$D$32*3/100 -> 0.0068057089 | E32: =E14*Assumptions!$D$33*Assumptions!$D$32*3/100 -> 0.021176373 | F32: =F14*Assumptions!$D$33*Assumptions!$D$32*3/100 -> 0.043871239 | G32: =G14*Assumptions!$D$33*Assumptions!$D$32*3/100 -> 0.068084598 | H32: =H14*Assumptions!$D$33*Assumptions!$D$32*3/100 -> 0.09381645 | I32: =I14*Assumptions!$D$33*Assumptions!$D$32*3/100 -> 0.11299568 | J32: =J14*Assumptions!$D$33*Assumptions!$D$32*3/100 -> 0.13318723 | K32: =K14*Assumptions!$D$33*Assumptions!$D$32*3/100 -> 0.14581383 | L32: =SUM(D32:K32) -> 0.6257511
A33: 23 | B33: Revenue: credit (lender pays Paytm a share of each drawdown) | C33: Rs crore | D33: =D22*Assumptions!$D$38 -> 0.019383348 | E33: =E22*Assumptions!$D$38 -> 0.060312455 | F33: =F22*Assumptions!$D$38 -> 0.12494973 | G33: =G22*Assumptions!$D$38 -> 0.19391183 | H33: =H22*Assumptions!$D$38 -> 0.26719875 | I33: =I22*Assumptions!$D$38 -> 0.32182312 | J33: =J22*Assumptions!$D$38 -> 0.37933071 | K33: =K22*Assumptions!$D$38 -> 0.41529254 | L33: =SUM(D33:K33) -> 1.7822025
A34: 24 | B34: Revenue: payment margin on incremental GMV | C34: Rs crore | D34: =D29*Assumptions!$D$6 -> 0.0001577223 | E34: =E29*Assumptions!$D$6 -> 0.00054258706 | F34: =F29*Assumptions!$D$6 -> 0.0012298606 | G34: =G29*Assumptions!$D$6 -> 0.0021253448 | H34: =H29*Assumptions!$D$6 -> 0.0032408182 | I34: =I29*Assumptions!$D$6 -> 0.0044010256 | J34: =J29*Assumptions!$D$6 -> 0.0057316318 | K34: =K29*Assumptions!$D$6 -> 0.0070417491 | L34: =SUM(D34:K34) -> 0.024470739
A35: 25 | B35: Revenue: device subscriptions kept and added | C35: Rs crore | D35: =(D26+D17)*Assumptions!$D$9*3/100 -> 0.0003450236 | E35: =(E26+E17)*Assumptions!$D$9*3/100 -> 0.001419016 | F35: =(F26+F17)*Assumptions!$D$9*3/100 -> 0.0036448923 | G35: =(G26+G17)*Assumptions!$D$9*3/100 -> 0.0071010706 | H35: =(H26+H17)*Assumptions!$D$9*3/100 -> 0.011866065 | I35: =(I26+I17)*Assumptions!$D$9*3/100 -> 0.017609311 | J35: =(J26+J17)*Assumptions!$D$9*3/100 -> 0.024383344 | K35: =(K26+K17)*Assumptions!$D$9*3/100 -> 0.031805927 | L35: =SUM(D35:K35) -> 0.098174651
A36: 26 | B36: Revenue | C36: Rs crore | D36: =SUM(D30:D35) -> 0.158464 | E36: =SUM(E30:E35) -> 0.49347608 | F36: =SUM(F30:F35) -> 1.0231661 | G36: =SUM(G30:G35) -> 1.5895673 | H36: =SUM(H30:H35) -> 2.192772 | I36: =SUM(I30:I35) -> 2.6449447 | J36: =SUM(J30:J35) -> 3.1218387 | K36: =SUM(K30:K35) -> 3.4238027 | L36: =SUM(D36:K36) -> 14.648032
A37: 27 | B37: Cost: AI | C37: Rs crore | D37: =D18*Assumptions!$D$47*3/100 -> 0.034545434 | E37: =E18*Assumptions!$D$47*3/100 -> 0.10757635 | F37: =F18*Assumptions!$D$47*3/100 -> 0.22304239 | G37: =G18*Assumptions!$D$47*3/100 -> 0.34650351 | H37: =H18*Assumptions!$D$47*3/100 -> 0.47797892 | I37: =I18*Assumptions!$D$47*3/100 -> 0.57651924 | J37: =J18*Assumptions!$D$47*3/100 -> 0.68044087 | K37: =K18*Assumptions!$D$47*3/100 -> 0.74621876 | L37: =SUM(D37:K37) -> 3.1928255
A38: 28 | B38: Cost: photo checks at handover | C38: Rs crore | D38: =D19*Assumptions!$D$48*90*Assumptions!$D$49/100 -> 0.0025909075 | E38: =E19*Assumptions!$D$48*90*Assumptions!$D$49/100 -> 0.008068226 | F38: =F19*Assumptions!$D$48*90*Assumptions!$D$49/100 -> 0.016728179 | G38: =G19*Assumptions!$D$48*90*Assumptions!$D$49/100 -> 0.025987763 | H38: =H19*Assumptions!$D$48*90*Assumptions!$D$49/100 -> 0.035848419 | I38: =I19*Assumptions!$D$48*90*Assumptions!$D$49/100 -> 0.043238943 | J38: =J19*Assumptions!$D$48*90*Assumptions!$D$49/100 -> 0.051033065 | K38: =K19*Assumptions!$D$48*90*Assumptions!$D$49/100 -> 0.055966407 | L38: =SUM(D38:K38) -> 0.23946191
A39: 29 | B39: Cost: Account Aggregator data | C39: Rs crore | D39: =D14*Assumptions!$D$50*3/100 -> 0.021537054 | E39: =E14*Assumptions!$D$50*3/100 -> 0.067013839 | F39: =F14*Assumptions!$D$50*3/100 -> 0.13883304 | G39: =G14*Assumptions!$D$50*3/100 -> 0.21545759 | H39: =H14*Assumptions!$D$50*3/100 -> 0.2968875 | I39: =I14*Assumptions!$D$50*3/100 -> 0.35758125 | J39: =J14*Assumptions!$D$50*3/100 -> 0.42147857 | K39: =K14*Assumptions!$D$50*3/100 -> 0.46143616 | L39: =SUM(D39:K39) -> 1.980225
A40: 30 | B40: Cost: support | C40: Rs crore | D40: =D18*Assumptions!$D$51*3/100 -> 0.017272717 | E40: =E18*Assumptions!$D$51*3/100 -> 0.053788173 | F40: =F18*Assumptions!$D$51*3/100 -> 0.1115212 | G40: =G18*Assumptions!$D$51*3/100 -> 0.17325175 | H40: =H18*Assumptions!$D$51*3/100 -> 0.23898946 | I40: =I18*Assumptions!$D$51*3/100 -> 0.28825962 | J40: =J18*Assumptions!$D$51*3/100 -> 0.34022043 | K40: =K18*Assumptions!$D$51*3/100 -> 0.37310938 | L40: =SUM(D40:K40) -> 1.5964127
A41: 31 | B41: Cost: onboarding new members | C41: Rs crore | D41: =D15*(Assumptions!$D$52+Assumptions!$D$53*1)/100 -> 0.12922232 | E41: =E15*(Assumptions!$D$52+Assumptions!$D$53*1)/100 -> 0.27286071 | F41: =F15*(Assumptions!$D$52+Assumptions!$D$53*1)/100 -> 0.43091518 | G41: =G15*(Assumptions!$D$52+Assumptions!$D$53*1)/100 -> 0.45974732 | H41: =H15*(Assumptions!$D$52+Assumptions!$D$53*1)/100 -> 0.48857946 | I41: =I15*(Assumptions!$D$52+Assumptions!$D$53*1)/100 -> 0.3641625 | J41: =J15*(Assumptions!$D$52+Assumptions!$D$53*1)/100 -> 0.38338393 | K41: =K15*(Assumptions!$D$52+Assumptions!$D$53*1)/100 -> 0.23974554 | L41: =SUM(D41:K41) -> 2.768617
A42: 32 | B42: Cost: collection and servicing of drawdowns | C42: Rs crore | D42: =D22*Assumptions!$D$39 -> 0.0064611161 | E42: =E22*Assumptions!$D$39 -> 0.020104152 | F42: =F22*Assumptions!$D$39 -> 0.041649911 | G42: =G22*Assumptions!$D$39 -> 0.064637277 | H42: =H22*Assumptions!$D$39 -> 0.08906625 | I42: =I22*Assumptions!$D$39 -> 0.10727438 | J42: =J22*Assumptions!$D$39 -> 0.12644357 | K42: =K22*Assumptions!$D$39 -> 0.13843085 | L42: =SUM(D42:K42) -> 0.5940675
A43: 33 | B43: Cost: credit-loss sharing | C43: Rs crore | D43: =D22*Assumptions!$D$40 -> 0.0096916741 | E43: =E22*Assumptions!$D$40 -> 0.030156228 | F43: =F22*Assumptions!$D$40 -> 0.062474866 | G43: =G22*Assumptions!$D$40 -> 0.096955915 | H43: =H22*Assumptions!$D$40 -> 0.13359937 | I43: =I22*Assumptions!$D$40 -> 0.16091156 | J43: =J22*Assumptions!$D$40 -> 0.18966536 | K43: =K22*Assumptions!$D$40 -> 0.20764627 | L43: =SUM(D43:K43) -> 0.89110125
A44: 34 | B44: Variable cost | C44: Rs crore | D44: =SUM(D37:D43) -> 0.22132122 | E44: =SUM(E37:E43) -> 0.55956768 | F44: =SUM(F37:F43) -> 1.0251648 | G44: =SUM(G37:G43) -> 1.3825411 | H44: =SUM(H37:H43) -> 1.7609494 | I44: =SUM(I37:I43) -> 1.8979475 | J44: =SUM(J37:J43) -> 2.1926658 | K44: =SUM(K37:K43) -> 2.2225534 | L44: =SUM(D44:K44) -> 11.262711
A45: 35 | B45: Contribution | C45: Rs crore | D45: =D36-D44 -> -0.06285722 | E45: =E36-E44 -> -0.066091601 | F45: =F36-F44 -> -0.0019987064 | G45: =G36-G44 -> 0.20702617 | H45: =H36-H44 -> 0.43182262 | I45: =I36-I44 -> 0.74699717 | J45: =J36-J44 -> 0.92917294 | K45: =K36-K44 -> 1.2012493 | L45: =SUM(D45:K45) -> 3.3853207
B46: Band 2: Businesses with 2-5 outlets
A47: 36 | B47: Businesses in this band | C47: lakh | D47: =D10*Assumptions!$D$12 -> 3.5342857 | E47: =E10*Assumptions!$D$12 -> 3.6657143 | F47: =F10*Assumptions!$D$12 -> 3.7971429 | G47: =G10*Assumptions!$D$12 -> 3.9285714 | H47: =H10*Assumptions!$D$12 -> 4.06 | I47: =I10*Assumptions!$D$12 -> 4.1914286 | J47: =J10*Assumptions!$D$12 -> 4.3228571 | K47: =K10*Assumptions!$D$12 -> 4.4542857 | L47: =K47 -> 4.4542857
A48: 37 | B48: Paying members | C48: lakh | D48: =D47*D11*Assumptions!$D$20 -> 0.0088357143 | E48: =E47*E11*Assumptions!$D$20 -> 0.027492857 | F48: =F47*F11*Assumptions!$D$20 -> 0.056957143 | G48: =G47*G11*Assumptions!$D$20 -> 0.088392857 | H48: =H47*H11*Assumptions!$D$20 -> 0.1218 | I48: =I47*I11*Assumptions!$D$20 -> 0.1467 | J48: =J47*J11*Assumptions!$D$20 -> 0.17291429 | K48: =K47*K11*Assumptions!$D$20 -> 0.18930714 | L48: =K48 -> 0.18930714
A49: 38 | B49: New paying members | C49: lakh | D49: =MAX(0,D48-N(C48)) -> 0.0088357143 | E49: =MAX(0,E48-N(D48)) -> 0.018657143 | F49: =MAX(0,F48-N(E48)) -> 0.029464286 | G49: =MAX(0,G48-N(F48)) -> 0.031435714 | H49: =MAX(0,H48-N(G48)) -> 0.033407143 | I49: =MAX(0,I48-N(H48)) -> 0.0249 | J49: =MAX(0,J48-N(I48)) -> 0.026214286 | K49: =MAX(0,K48-N(J48)) -> 0.016392857 | L49: =SUM(D49:K49) -> 0.18930714
A50: 39 | B50: Member outlets | C50: lakh | D50: =D48*Assumptions!$D$15 -> 0.020322143 | E50: =E48*Assumptions!$D$15 -> 0.063233571 | F50: =F48*Assumptions!$D$15 -> 0.13100143 | G50: =G48*Assumptions!$D$15 -> 0.20330357 | H50: =H48*Assumptions!$D$15 -> 0.28014 | I50: =I48*Assumptions!$D$15 -> 0.33741 | J50: =J48*Assumptions!$D$15 -> 0.39770286 | K50: =K48*Assumptions!$D$15 -> 0.43540643 | L50: =K50 -> 0.43540643
A51: 40 | B51: Extra outlets opened (cumulative) | C51: lakh | D51: =N(C51)+D48*Assumptions!$D$23/100/4 -> 2.2089286e-05 | E51: =N(D51)+E48*Assumptions!$D$23/100/4 -> 9.0821429e-05 | F51: =N(E51)+F48*Assumptions!$D$23/100/4 -> 0.00023321429 | G51: =N(F51)+G48*Assumptions!$D$23/100/4 -> 0.00045419643 | H51: =N(G51)+H48*Assumptions!$D$23/100/4 -> 0.00075869643 | I51: =N(H51)+I48*Assumptions!$D$23/100/4 -> 0.0011254464 | J51: =N(I51)+J48*Assumptions!$D$23/100/4 -> 0.0015577321 | K51: =N(J51)+K48*Assumptions!$D$23/100/4 -> 0.002031 | L51: =K51 -> 0.002031
A52: 41 | B52: Member outlets, including new ones | C52: lakh | D52: =D50+D51 -> 0.020344232 | E52: =E50+E51 -> 0.063324393 | F52: =F50+F51 -> 0.13123464 | G52: =G50+G51 -> 0.20375777 | H52: =H50+H51 -> 0.2808987 | I52: =I50+I51 -> 0.33853545 | J52: =J50+J51 -> 0.39926059 | K52: =K50+K51 -> 0.43743743 | L52: =K52 -> 0.43743743
A53: 42 | B53: Outlets with the shift-check pass | C53: lakh | D53: =D52*Assumptions!$D$31 -> 0.0061032696 | E53: =E52*Assumptions!$D$31 -> 0.018997318 | F53: =F52*Assumptions!$D$31 -> 0.039370393 | G53: =G52*Assumptions!$D$31 -> 0.06112733 | H53: =H52*Assumptions!$D$31 -> 0.084269609 | I53: =I52*Assumptions!$D$31 -> 0.10156063 | J53: =J52*Assumptions!$D$31 -> 0.11977818 | K53: =K52*Assumptions!$D$31 -> 0.13123123 | L53: =K53 -> 0.13123123
A54: 43 | B54: Members with a pre-approved line | C54: lakh | D54: =D48*Assumptions!$D$35 -> 0.0026507143 | E54: =E48*Assumptions!$D$35 -> 0.0082478571 | F54: =F48*Assumptions!$D$35 -> 0.017087143 | G54: =G48*Assumptions!$D$35 -> 0.026517857 | H54: =H48*Assumptions!$D$35 -> 0.03654 | I54: =I48*Assumptions!$D$35 -> 0.04401 | J54: =J48*Assumptions!$D$35 -> 0.051874286 | K54: =K48*Assumptions!$D$35 -> 0.056792143 | L54: =K54 -> 0.056792143
A55: 44 | B55: Drawdowns prompted by the cash plan | C55: lakh | D55: =D54*Assumptions!$D$36/4 -> 0.00099401786 | E55: =E54*Assumptions!$D$36/4 -> 0.0030929464 | F55: =F54*Assumptions!$D$36/4 -> 0.0064076786 | G55: =G54*Assumptions!$D$36/4 -> 0.0099441964 | H55: =H54*Assumptions!$D$36/4 -> 0.0137025 | I55: =I54*Assumptions!$D$36/4 -> 0.01650375 | J55: =J54*Assumptions!$D$36/4 -> 0.019452857 | K55: =K54*Assumptions!$D$36/4 -> 0.021297054 | L55: =SUM(D55:K55) -> 0.091395
A56: 45 | B56: Drawdown value | C56: Rs crore | D56: =D55*Assumptions!$D$37*Assumptions!$D$15/100 -> 0.91449643 | E56: =E55*Assumptions!$D$37*Assumptions!$D$15/100 -> 2.8455107 | F56: =F55*Assumptions!$D$37*Assumptions!$D$15/100 -> 5.8950643 | G56: =G55*Assumptions!$D$37*Assumptions!$D$15/100 -> 9.1486607 | H56: =H55*Assumptions!$D$37*Assumptions!$D$15/100 -> 12.6063 | I56: =I55*Assumptions!$D$37*Assumptions!$D$15/100 -> 15.18345 | J56: =J55*Assumptions!$D$37*Assumptions!$D$15/100 -> 17.896629 | K56: =K55*Assumptions!$D$37*Assumptions!$D$15/100 -> 19.593289 | L56: =SUM(D56:K56) -> 84.0834
A57: 46 | B57: Paytm GMV of member outlets before the Munim (reference) | C57: Rs crore | D57: =D50*Assumptions!$D$7*3/100 -> 36.579857 | E57: =E50*Assumptions!$D$7*3/100 -> 113.82043 | F57: =F50*Assumptions!$D$7*3/100 -> 235.80257 | G57: =G50*Assumptions!$D$7*3/100 -> 365.94643 | H57: =H50*Assumptions!$D$7*3/100 -> 504.252 | I57: =I50*Assumptions!$D$7*3/100 -> 607.338 | J57: =J50*Assumptions!$D$7*3/100 -> 715.86514 | K57: =K50*Assumptions!$D$7*3/100 -> 783.73157 | L57: =SUM(D57:K57) -> 3363.336
A58: 47 | B58: GMV: extra sales from the cash plan | C58: Rs crore | D58: =D57*Assumptions!$D$42 -> 0.36579857 | E58: =E57*Assumptions!$D$42 -> 1.1382043 | F58: =F57*Assumptions!$D$42 -> 2.3580257 | G58: =G57*Assumptions!$D$42 -> 3.6594643 | H58: =H57*Assumptions!$D$42 -> 5.04252 | I58: =I57*Assumptions!$D$42 -> 6.07338 | J58: =J57*Assumptions!$D$42 -> 7.1586514 | K58: =K57*Assumptions!$D$42 -> 7.8373157 | L58: =SUM(D58:K58) -> 33.63336
A59: 48 | B59: GMV: collections moved to Paytm's outlet QRs | C59: Rs crore | D59: =D57*Assumptions!$D$43 -> 0.36579857 | E59: =E57*Assumptions!$D$43 -> 1.1382043 | F59: =F57*Assumptions!$D$43 -> 2.3580257 | G59: =G57*Assumptions!$D$43 -> 3.6594643 | H59: =H57*Assumptions!$D$43 -> 5.04252 | I59: =I57*Assumptions!$D$43 -> 6.07338 | J59: =J57*Assumptions!$D$43 -> 7.1586514 | K59: =K57*Assumptions!$D$43 -> 7.8373157 | L59: =SUM(D59:K59) -> 33.63336
A60: 49 | B60: GMV: leakage recovered (outlets with the pass) | C60: Rs crore | D60: =D53*Assumptions!$D$7*3/100*Assumptions!$D$44 -> 0.054929427 | E60: =E53*Assumptions!$D$7*3/100*Assumptions!$D$44 -> 0.17097586 | F60: =F53*Assumptions!$D$7*3/100*Assumptions!$D$44 -> 0.35433354 | G60: =G53*Assumptions!$D$7*3/100*Assumptions!$D$44 -> 0.55014597 | H60: =H53*Assumptions!$D$7*3/100*Assumptions!$D$44 -> 0.75842648 | I60: =I53*Assumptions!$D$7*3/100*Assumptions!$D$44 -> 0.91404571 | J60: =J53*Assumptions!$D$7*3/100*Assumptions!$D$44 -> 1.0780036 | K60: =K53*Assumptions!$D$7*3/100*Assumptions!$D$44 -> 1.1810811 | L60: =SUM(D60:K60) -> 5.0619416
A61: 50 | B61: Outlets kept by lower device churn (cumulative) | C61: lakh | D61: =N(C61)+D52*Assumptions!$D$45/4 -> 5.086058e-05 | E61: =N(D61)+E52*Assumptions!$D$45/4 -> 0.00020917156 | F61: =N(E61)+F52*Assumptions!$D$45/4 -> 0.00053725817 | G61: =N(F61)+G52*Assumptions!$D$45/4 -> 0.0010466526 | H61: =N(G61)+H52*Assumptions!$D$45/4 -> 0.0017488993 | I61: =N(H61)+I52*Assumptions!$D$45/4 -> 0.0025952379 | J61: =N(I61)+J52*Assumptions!$D$45/4 -> 0.0035933894 | K61: =N(J61)+K52*Assumptions!$D$45/4 -> 0.004686983 | L61: =K61 -> 0.004686983
A62: 51 | B62: GMV: kept by lower device churn | C62: Rs crore | D62: =D61*Assumptions!$D$7*3/100 -> 0.091549045 | E62: =E61*Assumptions!$D$7*3/100 -> 0.37650881 | F62: =F61*Assumptions!$D$7*3/100 -> 0.96706471 | G62: =G61*Assumptions!$D$7*3/100 -> 1.8839747 | H62: =H61*Assumptions!$D$7*3/100 -> 3.1480188 | I62: =I61*Assumptions!$D$7*3/100 -> 4.6714283 | J62: =J61*Assumptions!$D$7*3/100 -> 6.468101 | K62: =K61*Assumptions!$D$7*3/100 -> 8.4365694 | L62: =SUM(D62:K62) -> 26.043215
A63: 52 | B63: GMV: extra outlets opened | C63: Rs crore | D63: =D51*Assumptions!$D$7*3/100 -> 0.039760714 | E63: =E51*Assumptions!$D$7*3/100 -> 0.16347857 | F63: =F51*Assumptions!$D$7*3/100 -> 0.41978571 | G63: =G51*Assumptions!$D$7*3/100 -> 0.81755357 | H63: =H51*Assumptions!$D$7*3/100 -> 1.3656536 | I63: =I51*Assumptions!$D$7*3/100 -> 2.0258036 | J63: =J51*Assumptions!$D$7*3/100 -> 2.8039179 | K63: =K51*Assumptions!$D$7*3/100 -> 3.6558 | L63: =SUM(D63:K63) -> 11.291754
A64: 53 | B64: Incremental GMV | C64: Rs crore | D64: =D58+D60+D62+D63+D59 -> 0.91783633 | E64: =E58+E60+E62+E63+E59 -> 2.9873718 | F64: =F58+F60+F62+F63+F59 -> 6.4572354 | G64: =G58+G60+G62+G63+G59 -> 10.570603 | H64: =H58+H60+H62+H63+H59 -> 15.357139 | I64: =I58+I60+I62+I63+I59 -> 19.758038 | J64: =J58+J60+J62+J63+J59 -> 24.667325 | K64: =K58+K60+K62+K63+K59 -> 28.948082 | L64: =SUM(D64:K64) -> 109.66363
A65: 54 | B65: Revenue: membership | C65: Rs crore | D65: =D48*Assumptions!$D$25*3/100 -> 0.039495643 | E65: =E48*Assumptions!$D$25*3/100 -> 0.12289307 | F65: =F48*Assumptions!$D$25*3/100 -> 0.25459843 | G65: =G48*Assumptions!$D$25*3/100 -> 0.39511607 | H65: =H48*Assumptions!$D$25*3/100 -> 0.544446 | I65: =I48*Assumptions!$D$25*3/100 -> 0.655749 | J65: =J48*Assumptions!$D$25*3/100 -> 0.77292686 | K65: =K48*Assumptions!$D$25*3/100 -> 0.84620293 | L65: =SUM(D65:K65) -> 3.631428
A66: 55 | B66: Revenue: shift-check passes | C66: Rs crore | D66: =D53*Assumptions!$D$29*3/100 -> 0.014464749 | E66: =E53*Assumptions!$D$29*3/100 -> 0.045023643 | F66: =F53*Assumptions!$D$29*3/100 -> 0.093307831 | G66: =G53*Assumptions!$D$29*3/100 -> 0.14487177 | H66: =H53*Assumptions!$D$29*3/100 -> 0.19971897 | I66: =I53*Assumptions!$D$29*3/100 -> 0.2406987 | J66: =J53*Assumptions!$D$29*3/100 -> 0.28387428 | K66: =K53*Assumptions!$D$29*3/100 -> 0.31101801 | L66: =SUM(D66:K66) -> 1.332978
A67: 56 | B67: Revenue: CA packs | C67: Rs crore | D67: =D48*Assumptions!$D$33*Assumptions!$D$32*3/100 -> 0.0020940643 | E67: =E48*Assumptions!$D$33*Assumptions!$D$32*3/100 -> 0.0065158071 | F67: =F48*Assumptions!$D$33*Assumptions!$D$32*3/100 -> 0.013498843 | G67: =G48*Assumptions!$D$33*Assumptions!$D$32*3/100 -> 0.020949107 | H67: =H48*Assumptions!$D$33*Assumptions!$D$32*3/100 -> 0.0288666 | I67: =I48*Assumptions!$D$33*Assumptions!$D$32*3/100 -> 0.0347679 | J67: =J48*Assumptions!$D$33*Assumptions!$D$32*3/100 -> 0.040980686 | K67: =K48*Assumptions!$D$33*Assumptions!$D$32*3/100 -> 0.044865793 | L67: =SUM(D67:K67) -> 0.1925388
A68: 57 | B68: Revenue: credit (lender pays Paytm a share of each drawdown) | C68: Rs crore | D68: =D56*Assumptions!$D$38 -> 0.013717446 | E68: =E56*Assumptions!$D$38 -> 0.042682661 | F68: =F56*Assumptions!$D$38 -> 0.088425964 | G68: =G56*Assumptions!$D$38 -> 0.13722991 | H68: =H56*Assumptions!$D$38 -> 0.1890945 | I68: =I56*Assumptions!$D$38 -> 0.22775175 | J68: =J56*Assumptions!$D$38 -> 0.26844943 | K68: =K56*Assumptions!$D$38 -> 0.29389934 | L68: =SUM(D68:K68) -> 1.261251
A69: 58 | B69: Revenue: payment margin on incremental GMV | C69: Rs crore | D69: =D64*Assumptions!$D$6 -> 0.00036713453 | E69: =E64*Assumptions!$D$6 -> 0.0011949487 | F69: =F64*Assumptions!$D$6 -> 0.0025828942 | G69: =G64*Assumptions!$D$6 -> 0.0042282411 | H69: =H64*Assumptions!$D$6 -> 0.0061428555 | I69: =I64*Assumptions!$D$6 -> 0.007903215 | J69: =J64*Assumptions!$D$6 -> 0.0098669301 | K69: =K64*Assumptions!$D$6 -> 0.011579233 | L69: =SUM(D69:K69) -> 0.043865452
A70: 59 | B70: Revenue: device subscriptions kept and added | C70: Rs crore | D70: =(D61+D51)*Assumptions!$D$9*3/100 -> 0.00017507968 | E70: =(E61+E51)*Assumptions!$D$9*3/100 -> 0.00071998318 | F70: =(F61+F51)*Assumptions!$D$9*3/100 -> 0.0018491339 | G70: =(G61+G51)*Assumptions!$D$9*3/100 -> 0.0036020376 | H70: =(H61+H51)*Assumptions!$D$9*3/100 -> 0.0060182298 | I70: =(I61+I51)*Assumptions!$D$9*3/100 -> 0.0089296425 | J70: =(J61+J51)*Assumptions!$D$9*3/100 -> 0.012362692 | K70: =(K61+K51)*Assumptions!$D$9*3/100 -> 0.016123159 | L70: =SUM(D70:K70) -> 0.049779958
A71: 60 | B71: Revenue | C71: Rs crore | D71: =SUM(D65:D70) -> 0.070314117 | E71: =SUM(E65:E70) -> 0.21903011 | F71: =SUM(F65:F70) -> 0.45426309 | G71: =SUM(G65:G70) -> 0.70599714 | H71: =SUM(H65:H70) -> 0.97428716 | I71: =SUM(I65:I70) -> 1.1758002 | J71: =SUM(J65:J70) -> 1.3884609 | K71: =SUM(K65:K70) -> 1.5236885 | L71: =SUM(D71:K71) -> 6.5118412
A72: 61 | B72: Cost: AI | C72: Rs crore | D72: =D52*Assumptions!$D$47*3/100 -> 0.024413079 | E72: =E52*Assumptions!$D$47*3/100 -> 0.075989271 | F72: =F52*Assumptions!$D$47*3/100 -> 0.15748157 | G72: =G52*Assumptions!$D$47*3/100 -> 0.24450932 | H72: =H52*Assumptions!$D$47*3/100 -> 0.33707844 | I72: =I52*Assumptions!$D$47*3/100 -> 0.40624254 | J72: =J52*Assumptions!$D$47*3/100 -> 0.47911271 | K72: =K52*Assumptions!$D$47*3/100 -> 0.52492491 | L72: =SUM(D72:K72) -> 2.2497518
A73: 62 | B73: Cost: photo checks at handover | C73: Rs crore | D73: =D53*Assumptions!$D$48*90*Assumptions!$D$49/100 -> 0.010985885 | E73: =E53*Assumptions!$D$48*90*Assumptions!$D$49/100 -> 0.034195172 | F73: =F53*Assumptions!$D$48*90*Assumptions!$D$49/100 -> 0.070866707 | G73: =G53*Assumptions!$D$48*90*Assumptions!$D$49/100 -> 0.11002919 | H73: =H53*Assumptions!$D$48*90*Assumptions!$D$49/100 -> 0.1516853 | I73: =I53*Assumptions!$D$48*90*Assumptions!$D$49/100 -> 0.18280914 | J73: =J53*Assumptions!$D$48*90*Assumptions!$D$49/100 -> 0.21560072 | K73: =K53*Assumptions!$D$48*90*Assumptions!$D$49/100 -> 0.23621621 | L73: =SUM(D73:K73) -> 1.0123883
A74: 63 | B74: Cost: Account Aggregator data | C74: Rs crore | D74: =D48*Assumptions!$D$50*3/100 -> 0.0066267857 | E74: =E48*Assumptions!$D$50*3/100 -> 0.020619643 | F74: =F48*Assumptions!$D$50*3/100 -> 0.042717857 | G74: =G48*Assumptions!$D$50*3/100 -> 0.066294643 | H74: =H48*Assumptions!$D$50*3/100 -> 0.09135 | I74: =I48*Assumptions!$D$50*3/100 -> 0.110025 | J74: =J48*Assumptions!$D$50*3/100 -> 0.12968571 | K74: =K48*Assumptions!$D$50*3/100 -> 0.14198036 | L74: =SUM(D74:K74) -> 0.6093
A75: 64 | B75: Cost: support | C75: Rs crore | D75: =D52*Assumptions!$D$51*3/100 -> 0.012206539 | E75: =E52*Assumptions!$D$51*3/100 -> 0.037994636 | F75: =F52*Assumptions!$D$51*3/100 -> 0.078740786 | G75: =G52*Assumptions!$D$51*3/100 -> 0.12225466 | H75: =H52*Assumptions!$D$51*3/100 -> 0.16853922 | I75: =I52*Assumptions!$D$51*3/100 -> 0.20312127 | J75: =J52*Assumptions!$D$51*3/100 -> 0.23955635 | K75: =K52*Assumptions!$D$51*3/100 -> 0.26246246 | L75: =SUM(D75:K75) -> 1.1248759
A76: 65 | B76: Cost: onboarding new members | C76: Rs crore | D76: =D49*(Assumptions!$D$52+Assumptions!$D$53*Assumptions!$D$15)/100 -> 0.062733571 | E76: =E49*(Assumptions!$D$52+Assumptions!$D$53*Assumptions!$D$15)/100 -> 0.13246571 | F76: =F49*(Assumptions!$D$52+Assumptions!$D$53*Assumptions!$D$15)/100 -> 0.20919643 | G76: =G49*(Assumptions!$D$52+Assumptions!$D$53*Assumptions!$D$15)/100 -> 0.22319357 | H76: =H49*(Assumptions!$D$52+Assumptions!$D$53*Assumptions!$D$15)/100 -> 0.23719071 | I76: =I49*(Assumptions!$D$52+Assumptions!$D$53*Assumptions!$D$15)/100 -> 0.17679 | J76: =J49*(Assumptions!$D$52+Assumptions!$D$53*Assumptions!$D$15)/100 -> 0.18612143 | K76: =K49*(Assumptions!$D$52+Assumptions!$D$53*Assumptions!$D$15)/100 -> 0.11638929 | L76: =SUM(D76:K76) -> 1.3440807
A77: 66 | B77: Cost: collection and servicing of drawdowns | C77: Rs crore | D77: =D56*Assumptions!$D$39 -> 0.0045724821 | E77: =E56*Assumptions!$D$39 -> 0.014227554 | F77: =F56*Assumptions!$D$39 -> 0.029475321 | G77: =G56*Assumptions!$D$39 -> 0.045743304 | H77: =H56*Assumptions!$D$39 -> 0.0630315 | I77: =I56*Assumptions!$D$39 -> 0.07591725 | J77: =J56*Assumptions!$D$39 -> 0.089483143 | K77: =K56*Assumptions!$D$39 -> 0.097966446 | L77: =SUM(D77:K77) -> 0.420417
A78: 67 | B78: Cost: credit-loss sharing | C78: Rs crore | D78: =D56*Assumptions!$D$40 -> 0.0068587232 | E78: =E56*Assumptions!$D$40 -> 0.02134133 | F78: =F56*Assumptions!$D$40 -> 0.044212982 | G78: =G56*Assumptions!$D$40 -> 0.068614955 | H78: =H56*Assumptions!$D$40 -> 0.09454725 | I78: =I56*Assumptions!$D$40 -> 0.11387588 | J78: =J56*Assumptions!$D$40 -> 0.13422471 | K78: =K56*Assumptions!$D$40 -> 0.14694967 | L78: =SUM(D78:K78) -> 0.6306255
A79: 68 | B79: Variable cost | C79: Rs crore | D79: =SUM(D72:D78) -> 0.12839707 | E79: =SUM(E72:E78) -> 0.33683332 | F79: =SUM(F72:F78) -> 0.63269165 | G79: =SUM(G72:G78) -> 0.88063965 | H79: =SUM(H72:H78) -> 1.1434224 | I79: =SUM(I72:I78) -> 1.2687811 | J79: =SUM(J72:J78) -> 1.4737848 | K79: =SUM(K72:K78) -> 1.5268893 | L79: =SUM(D79:K79) -> 7.3914393
A80: 69 | B80: Contribution | C80: Rs crore | D80: =D71-D79 -> -0.058082949 | E80: =E71-E79 -> -0.11780321 | F80: =F71-F79 -> -0.17842856 | G80: =G71-G79 -> -0.17464251 | H80: =H71-H79 -> -0.16913526 | I80: =I71-I79 -> -0.09298086 | J80: =J71-J79 -> -0.085323907 | K80: =K71-K79 -> -0.0032008774 | L80: =SUM(D80:K80) -> -0.87959812
B81: Band 3: Businesses with 6-20 outlets
A82: 70 | B82: Businesses in this band | C82: lakh | D82: =D10*Assumptions!$D$13 -> 0.17671429 | E82: =E10*Assumptions!$D$13 -> 0.18328571 | F82: =F10*Assumptions!$D$13 -> 0.18985714 | G82: =G10*Assumptions!$D$13 -> 0.19642857 | H82: =H10*Assumptions!$D$13 -> 0.203 | I82: =I10*Assumptions!$D$13 -> 0.20957143 | J82: =J10*Assumptions!$D$13 -> 0.21614286 | K82: =K10*Assumptions!$D$13 -> 0.22271429 | L82: =K82 -> 0.22271429
A83: 71 | B83: Paying members | C83: lakh | D83: =D82*D11*Assumptions!$D$21 -> 0.00035342857 | E83: =E82*E11*Assumptions!$D$21 -> 0.0010997143 | F83: =F82*F11*Assumptions!$D$21 -> 0.0022782857 | G83: =G82*G11*Assumptions!$D$21 -> 0.0035357143 | H83: =H82*H11*Assumptions!$D$21 -> 0.004872 | I83: =I82*I11*Assumptions!$D$21 -> 0.005868 | J83: =J82*J11*Assumptions!$D$21 -> 0.0069165714 | K83: =K82*K11*Assumptions!$D$21 -> 0.0075722857 | L83: =K83 -> 0.0075722857
A84: 72 | B84: New paying members | C84: lakh | D84: =MAX(0,D83-N(C83)) -> 0.00035342857 | E84: =MAX(0,E83-N(D83)) -> 0.00074628571 | F84: =MAX(0,F83-N(E83)) -> 0.0011785714 | G84: =MAX(0,G83-N(F83)) -> 0.0012574286 | H84: =MAX(0,H83-N(G83)) -> 0.0013362857 | I84: =MAX(0,I83-N(H83)) -> 0.000996 | J84: =MAX(0,J83-N(I83)) -> 0.0010485714 | K84: =MAX(0,K83-N(J83)) -> 0.00065571429 | L84: =SUM(D84:K84) -> 0.0075722857
A85: 73 | B85: Member outlets | C85: lakh | D85: =D83*Assumptions!$D$16 -> 0.0028274286 | E85: =E83*Assumptions!$D$16 -> 0.0087977143 | F85: =F83*Assumptions!$D$16 -> 0.018226286 | G85: =G83*Assumptions!$D$16 -> 0.028285714 | H85: =H83*Assumptions!$D$16 -> 0.038976 | I85: =I83*Assumptions!$D$16 -> 0.046944 | J85: =J83*Assumptions!$D$16 -> 0.055332571 | K85: =K83*Assumptions!$D$16 -> 0.060578286 | L85: =K85 -> 0.060578286
A86: 74 | B86: Extra outlets opened (cumulative) | C86: lakh | D86: =N(C86)+D83*Assumptions!$D$23/100/4 -> 8.8357143e-07 | E86: =N(D86)+E83*Assumptions!$D$23/100/4 -> 3.6328571e-06 | F86: =N(E86)+F83*Assumptions!$D$23/100/4 -> 9.3285714e-06 | G86: =N(F86)+G83*Assumptions!$D$23/100/4 -> 1.8167857e-05 | H86: =N(G86)+H83*Assumptions!$D$23/100/4 -> 3.0347857e-05 | I86: =N(H86)+I83*Assumptions!$D$23/100/4 -> 4.5017857e-05 | J86: =N(I86)+J83*Assumptions!$D$23/100/4 -> 6.2309286e-05 | K86: =N(J86)+K83*Assumptions!$D$23/100/4 -> 8.124e-05 | L86: =K86 -> 8.124e-05
A87: 75 | B87: Member outlets, including new ones | C87: lakh | D87: =D85+D86 -> 0.0028283121 | E87: =E85+E86 -> 0.0088013471 | F87: =F85+F86 -> 0.018235614 | G87: =G85+G86 -> 0.028303882 | H87: =H85+H86 -> 0.039006348 | I87: =I85+I86 -> 0.046989018 | J87: =J85+J86 -> 0.055394881 | K87: =K85+K86 -> 0.060659526 | L87: =K87 -> 0.060659526
A88: 76 | B88: Outlets with the shift-check pass | C88: lakh | D88: =D87*Assumptions!$D$31 -> 0.00084849364 | E88: =E87*Assumptions!$D$31 -> 0.0026404041 | F88: =F87*Assumptions!$D$31 -> 0.0054706843 | G88: =G87*Assumptions!$D$31 -> 0.0084911646 | H88: =H87*Assumptions!$D$31 -> 0.011701904 | I88: =I87*Assumptions!$D$31 -> 0.014096705 | J88: =J87*Assumptions!$D$31 -> 0.016618464 | K88: =K87*Assumptions!$D$31 -> 0.018197858 | L88: =K88 -> 0.018197858
A89: 77 | B89: Outlet add-ons per member business (slabs on the band's average outlets) | C89: Rs / month | D89: =MAX(0,MIN(Assumptions!$D$16,10)-5)*Assumptions!$D$26+MAX(0,MIN(Assumptions!$D$16,20)-10)*Assumptions!$D$27+MAX(0,Assumptions!$D$16-20)*Assumptions!$D$28 -> 87 | E89: =MAX(0,MIN(Assumptions!$D$16,10)-5)*Assumptions!$D$26+MAX(0,MIN(Assumptions!$D$16,20)-10)*Assumptions!$D$27+MAX(0,Assumptions!$D$16-20)*Assumptions!$D$28 -> 87 | F89: =MAX(0,MIN(Assumptions!$D$16,10)-5)*Assumptions!$D$26+MAX(0,MIN(Assumptions!$D$16,20)-10)*Assumptions!$D$27+MAX(0,Assumptions!$D$16-20)*Assumptions!$D$28 -> 87 | G89: =MAX(0,MIN(Assumptions!$D$16,10)-5)*Assumptions!$D$26+MAX(0,MIN(Assumptions!$D$16,20)-10)*Assumptions!$D$27+MAX(0,Assumptions!$D$16-20)*Assumptions!$D$28 -> 87 | H89: =MAX(0,MIN(Assumptions!$D$16,10)-5)*Assumptions!$D$26+MAX(0,MIN(Assumptions!$D$16,20)-10)*Assumptions!$D$27+MAX(0,Assumptions!$D$16-20)*Assumptions!$D$28 -> 87 | I89: =MAX(0,MIN(Assumptions!$D$16,10)-5)*Assumptions!$D$26+MAX(0,MIN(Assumptions!$D$16,20)-10)*Assumptions!$D$27+MAX(0,Assumptions!$D$16-20)*Assumptions!$D$28 -> 87 | J89: =MAX(0,MIN(Assumptions!$D$16,10)-5)*Assumptions!$D$26+MAX(0,MIN(Assumptions!$D$16,20)-10)*Assumptions!$D$27+MAX(0,Assumptions!$D$16-20)*Assumptions!$D$28 -> 87 | K89: =MAX(0,MIN(Assumptions!$D$16,10)-5)*Assumptions!$D$26+MAX(0,MIN(Assumptions!$D$16,20)-10)*Assumptions!$D$27+MAX(0,Assumptions!$D$16-20)*Assumptions!$D$28 -> 87 | L89: =K89 -> 87
A90: 78 | B90: Members with a pre-approved line | C90: lakh | D90: =D83*Assumptions!$D$35 -> 0.00010602857 | E90: =E83*Assumptions!$D$35 -> 0.00032991429 | F90: =F83*Assumptions!$D$35 -> 0.00068348571 | G90: =G83*Assumptions!$D$35 -> 0.0010607143 | H90: =H83*Assumptions!$D$35 -> 0.0014616 | I90: =I83*Assumptions!$D$35 -> 0.0017604 | J90: =J83*Assumptions!$D$35 -> 0.0020749714 | K90: =K83*Assumptions!$D$35 -> 0.0022716857 | L90: =K90 -> 0.0022716857
A91: 79 | B91: Drawdowns prompted by the cash plan | C91: lakh | D91: =D90*Assumptions!$D$36/4 -> 3.9760714e-05 | E91: =E90*Assumptions!$D$36/4 -> 0.00012371786 | F91: =F90*Assumptions!$D$36/4 -> 0.00025630714 | G91: =G90*Assumptions!$D$36/4 -> 0.00039776786 | H91: =H90*Assumptions!$D$36/4 -> 0.0005481 | I91: =I90*Assumptions!$D$36/4 -> 0.00066015 | J91: =J90*Assumptions!$D$36/4 -> 0.00077811429 | K91: =K90*Assumptions!$D$36/4 -> 0.00085188214 | L91: =SUM(D91:K91) -> 0.0036558
A92: 80 | B92: Drawdown value | C92: Rs crore | D92: =D91*Assumptions!$D$37*Assumptions!$D$16/100 -> 0.12723429 | E92: =E91*Assumptions!$D$37*Assumptions!$D$16/100 -> 0.39589714 | F92: =F91*Assumptions!$D$37*Assumptions!$D$16/100 -> 0.82018286 | G92: =G91*Assumptions!$D$37*Assumptions!$D$16/100 -> 1.2728571 | H92: =H91*Assumptions!$D$37*Assumptions!$D$16/100 -> 1.75392 | I92: =I91*Assumptions!$D$37*Assumptions!$D$16/100 -> 2.11248 | J92: =J91*Assumptions!$D$37*Assumptions!$D$16/100 -> 2.4899657 | K92: =K91*Assumptions!$D$37*Assumptions!$D$16/100 -> 2.7260229 | L92: =SUM(D92:K92) -> 11.69856
A93: 81 | B93: Paytm GMV of member outlets before the Munim (reference) | C93: Rs crore | D93: =D85*Assumptions!$D$7*3/100 -> 5.0893714 | E93: =E85*Assumptions!$D$7*3/100 -> 15.835886 | F93: =F85*Assumptions!$D$7*3/100 -> 32.807314 | G93: =G85*Assumptions!$D$7*3/100 -> 50.914286 | H93: =H85*Assumptions!$D$7*3/100 -> 70.1568 | I93: =I85*Assumptions!$D$7*3/100 -> 84.4992 | J93: =J85*Assumptions!$D$7*3/100 -> 99.598629 | K93: =K85*Assumptions!$D$7*3/100 -> 109.04091 | L93: =SUM(D93:K93) -> 467.9424
A94: 82 | B94: GMV: extra sales from the cash plan | C94: Rs crore | D94: =D93*Assumptions!$D$42 -> 0.050893714 | E94: =E93*Assumptions!$D$42 -> 0.15835886 | F94: =F93*Assumptions!$D$42 -> 0.32807314 | G94: =G93*Assumptions!$D$42 -> 0.50914286 | H94: =H93*Assumptions!$D$42 -> 0.701568 | I94: =I93*Assumptions!$D$42 -> 0.844992 | J94: =J93*Assumptions!$D$42 -> 0.99598629 | K94: =K93*Assumptions!$D$42 -> 1.0904091 | L94: =SUM(D94:K94) -> 4.679424
A95: 83 | B95: GMV: collections moved to Paytm's outlet QRs | C95: Rs crore | D95: =D93*Assumptions!$D$43 -> 0.050893714 | E95: =E93*Assumptions!$D$43 -> 0.15835886 | F95: =F93*Assumptions!$D$43 -> 0.32807314 | G95: =G93*Assumptions!$D$43 -> 0.50914286 | H95: =H93*Assumptions!$D$43 -> 0.701568 | I95: =I93*Assumptions!$D$43 -> 0.844992 | J95: =J93*Assumptions!$D$43 -> 0.99598629 | K95: =K93*Assumptions!$D$43 -> 1.0904091 | L95: =SUM(D95:K95) -> 4.679424
A96: 84 | B96: GMV: leakage recovered (outlets with the pass) | C96: Rs crore | D96: =D88*Assumptions!$D$7*3/100*Assumptions!$D$44 -> 0.0076364428 | E96: =E88*Assumptions!$D$7*3/100*Assumptions!$D$44 -> 0.023763637 | F96: =F88*Assumptions!$D$7*3/100*Assumptions!$D$44 -> 0.049236159 | G96: =G88*Assumptions!$D$7*3/100*Assumptions!$D$44 -> 0.076420482 | H96: =H88*Assumptions!$D$7*3/100*Assumptions!$D$44 -> 0.10531714 | I96: =I88*Assumptions!$D$7*3/100*Assumptions!$D$44 -> 0.12687035 | J96: =J88*Assumptions!$D$7*3/100*Assumptions!$D$44 -> 0.14956618 | K96: =K88*Assumptions!$D$7*3/100*Assumptions!$D$44 -> 0.16378072 | L96: =SUM(D96:K96) -> 0.70259111
A97: 85 | B97: Outlets kept by lower device churn (cumulative) | C97: lakh | D97: =N(C97)+D87*Assumptions!$D$45/4 -> 7.0707804e-06 | E97: =N(D97)+E87*Assumptions!$D$45/4 -> 2.9074148e-05 | F97: =N(E97)+F87*Assumptions!$D$45/4 -> 7.4663184e-05 | G97: =N(F97)+G87*Assumptions!$D$45/4 -> 0.00014542289 | H97: =N(G97)+H87*Assumptions!$D$45/4 -> 0.00024293876 | I97: =N(H97)+I87*Assumptions!$D$45/4 -> 0.0003604113 | J97: =N(I97)+J87*Assumptions!$D$45/4 -> 0.00049889851 | K97: =N(J97)+K87*Assumptions!$D$45/4 -> 0.00065054732 | L97: =K97 -> 0.00065054732
A98: 86 | B98: GMV: kept by lower device churn | C98: Rs crore | D98: =D97*Assumptions!$D$7*3/100 -> 0.012727405 | E98: =E97*Assumptions!$D$7*3/100 -> 0.052333467 | F98: =F97*Assumptions!$D$7*3/100 -> 0.13439373 | G98: =G97*Assumptions!$D$7*3/100 -> 0.2617612 | H98: =H97*Assumptions!$D$7*3/100 -> 0.43728977 | I98: =I97*Assumptions!$D$7*3/100 -> 0.64874035 | J98: =J97*Assumptions!$D$7*3/100 -> 0.89801731 | K98: =K97*Assumptions!$D$7*3/100 -> 1.1709852 | L98: =SUM(D98:K98) -> 3.6162484
A99: 87 | B99: GMV: extra outlets opened | C99: Rs crore | D99: =D86*Assumptions!$D$7*3/100 -> 0.0015904286 | E99: =E86*Assumptions!$D$7*3/100 -> 0.0065391429 | F99: =F86*Assumptions!$D$7*3/100 -> 0.016791429 | G99: =G86*Assumptions!$D$7*3/100 -> 0.032702143 | H99: =H86*Assumptions!$D$7*3/100 -> 0.054626143 | I99: =I86*Assumptions!$D$7*3/100 -> 0.081032143 | J99: =J86*Assumptions!$D$7*3/100 -> 0.11215671 | K99: =K86*Assumptions!$D$7*3/100 -> 0.146232 | L99: =SUM(D99:K99) -> 0.45167014
A100: 88 | B100: Incremental GMV | C100: Rs crore | D100: =D94+D96+D98+D99+D95 -> 0.1237417 | E100: =E94+E96+E98+E99+E95 -> 0.39935396 | F100: =F94+F96+F98+F99+F95 -> 0.8565676 | G100: =G94+G96+G98+G99+G95 -> 1.3891695 | H100: =H94+H96+H98+H99+H95 -> 2.000369 | I100: =I94+I96+I98+I99+I95 -> 2.5466268 | J100: =J94+J96+J98+J99+J95 -> 3.1517128 | K100: =K94+K96+K98+K99+K95 -> 3.6618162 | L100: =SUM(D100:K100) -> 14.129358
A101: 89 | B101: Revenue: membership | C101: Rs crore | D101: =D83*Assumptions!$D$25*3/100 -> 0.0015798257 | E101: =E83*Assumptions!$D$25*3/100 -> 0.0049157229 | F101: =F83*Assumptions!$D$25*3/100 -> 0.010183937 | G101: =G83*Assumptions!$D$25*3/100 -> 0.015804643 | H101: =H83*Assumptions!$D$25*3/100 -> 0.02177784 | I101: =I83*Assumptions!$D$25*3/100 -> 0.02622996 | J101: =J83*Assumptions!$D$25*3/100 -> 0.030917074 | K101: =K83*Assumptions!$D$25*3/100 -> 0.033848117 | L101: =SUM(D101:K101) -> 0.14525712
A102: 90 | B102: Revenue: outlet add-ons | C102: Rs crore | D102: =D83*D89*3/100 -> 0.00092244857 | E102: =E83*E89*3/100 -> 0.0028702543 | F102: =F83*F89*3/100 -> 0.0059463257 | G102: =G83*G89*3/100 -> 0.0092282143 | H102: =H83*H89*3/100 -> 0.01271592 | I102: =I83*I89*3/100 -> 0.01531548 | J102: =J83*J89*3/100 -> 0.018052251 | K102: =K83*K89*3/100 -> 0.019763666 | L102: =SUM(D102:K102) -> 0.08481456
...

Sheet Summary
B1: Summary: numbers for the projection and business-model slides
B2: All cells link to the Model, Assumptions and Baseline sheets.
B4: A. Base case, quarter by quarter
B5: Metric | C5: Unit | D5: Q4 FY27 | E5: Q1 FY28 | F5: Q2 FY28 | G5: Q3 FY28 | H5: Q4 FY28 | I5: Q1 FY29 | J5: Q2 FY29 | K5: Q3 FY29 | L5: 8-qtr total
B6: Baseline Paytm merchant GMV (FORECAST) | C6: Rs lakh crore | D6: =Model!D358 -> 7.9486905 | E6: =Model!E358 -> 8.2971429 | F6: =Model!F358 -> 8.6455952 | G6: =Model!G358 -> 8.9940476 | H6: =Model!H358 -> 9.3425 | I6: =Model!I358 -> 9.6909524 | J6: =Model!J358 -> 10.039405 | K6: =Model!K358 -> 10.387857 | L6: =Model!L358 -> 73.34619
B7: Paying members, all sizes | C7: lakh | D7: =Model!D346 -> 0.098633079 | E7: =Model!E346 -> 0.30690276 | F7: =Model!F346 -> 0.63581259 | G7: =Model!G346 -> 0.98672946 | H7: =Model!H346 -> 1.3596534 | I7: =Model!I346 -> 1.6376121 | J7: =Model!J346 -> 1.9302422 | K7: =Model!K346 -> 2.1132356 | L7: =Model!L346 -> 2.1132356
B8: of which single-outlet | C8: lakh | D8: =Model!D210 -> 0.06185 | E8: =Model!E210 -> 0.19245 | F8: =Model!F210 -> 0.3987 | G8: =Model!G210 -> 0.61875 | H8: =Model!H210 -> 0.8526 | I8: =Model!I210 -> 1.0269 | J8: =Model!J210 -> 1.2104 | K8: =Model!K210 -> 1.32515 | L8: =Model!L210 -> 1.32515
B9: of which 2-5 outlets | C9: lakh | D9: =Model!D244 -> 0.035342857 | E9: =Model!E244 -> 0.10997143 | F9: =Model!F244 -> 0.22782857 | G9: =Model!G244 -> 0.35357143 | H9: =Model!H244 -> 0.4872 | I9: =Model!I244 -> 0.5868 | J9: =Model!J244 -> 0.69165714 | K9: =Model!K244 -> 0.75722857 | L9: =Model!L244 -> 0.75722857
B10: of which 6-20 outlets | C10: lakh | D10: =Model!D279 -> 0.0014137143 | E10: =Model!E279 -> 0.0043988571 | F10: =Model!F279 -> 0.0091131429 | G10: =Model!G279 -> 0.014142857 | H10: =Model!H279 -> 0.019488 | I10: =Model!I279 -> 0.023472 | J10: =Model!J279 -> 0.027666286 | K10: =Model!K279 -> 0.030289143 | L10: =Model!L279 -> 0.030289143
B11: of which 21+ outlets | C11: lakh | D11: =Model!D316 -> 2.6507143e-05 | E11: =Model!E316 -> 8.2478571e-05 | F11: =Model!F316 -> 0.00017087143 | G11: =Model!G316 -> 0.00026517857 | H11: =Model!H316 -> 0.0003654 | I11: =Model!I316 -> 0.0004401 | J11: =Model!J316 -> 0.00051874286 | K11: =Model!K316 -> 0.00056792143 | L11: =Model!L316 -> 0.00056792143
B12: Member outlets | C12: lakh | D12: =Model!D348 -> 0.16748817 | E12: =Model!E348 -> 0.52164268 | F12: =Model!F348 -> 1.0816967 | G12: =Model!G348 -> 1.6807654 | H12: =Model!H348 -> 2.3189587 | I12: =Model!I348 -> 2.7977567 | J12: =Model!J348 -> 3.3028579 | K12: =Model!K348 -> 3.6232491 | L12: =Model!L348 -> 3.6232491
B13: Incremental GMV | C13: Rs crore | D13: =Model!D356 -> 20.125955 | E13: =Model!E356 -> 65.386165 | F13: =Model!F356 -> 141.10175 | G13: =Model!G356 -> 230.53594 | H13: =Model!H356 -> 334.32046 | I13: =Model!I356 -> 429.22003 | J13: =Model!J356 -> 534.96284 | K13: =Model!K356 -> 626.60787 | L13: =Model!L356 -> 2382.261
B14: of which extra sales from the cash plan | C14: Rs crore | D14: =Model!D351 -> 7.34778 | E14: =Model!E351 -> 22.86306 | F14: =Model!F351 -> 47.36556 | G14: =Model!G351 -> 73.5075 | H14: =Model!H351 -> 101.28888 | I14: =Model!I351 -> 121.99572 | J14: =Model!J351 -> 143.79552 | K14: =Model!K351 -> 157.42782 | L14: =Model!L351 -> 675.59184
B15: of which collections moved to Paytm's outlet QRs | C15: Rs crore | D15: =Model!D352 -> 8.516745 | E15: =Model!E352 -> 26.500365 | F15: =Model!F352 -> 54.90099 | G15: =Model!G352 -> 85.201875 | H15: =Model!H352 -> 117.40302 | I15: =Model!I352 -> 141.40413 | J15: =Model!J352 -> 166.67208 | K15: =Model!K352 -> 182.47315 | L15: =Model!L352 -> 783.07236
B16: of which leakage recovered | C16: Rs crore | D16: =Model!D353 -> 1.5058553 | E16: =Model!E353 -> 4.6884599 | F16: =Model!F353 -> 9.7190313 | G16: =Model!G353 -> 15.095261 | H16: =Model!H353 -> 20.817798 | I16: =Model!I353 -> 25.101442 | J16: =Model!J353 -> 29.617252 | K16: =Model!K353 -> 32.467817 | L16: =Model!L353 -> 139.01292
B17: of which kept by lower device churn | C17: Rs crore | D17: =Model!D354 -> 1.8415153 | E17: =Model!E354 -> 7.5760713 | F17: =Model!F354 -> 19.465714 | G17: =Model!G354 -> 37.936562 | H17: =Model!H354 -> 63.415757 | I17: =Model!I354 -> 94.147543 | J17: =Model!J354 -> 130.41872 | K17: =Model!K354 -> 170.19589 | L17: =Model!L354 -> 524.99777
B18: of which extra outlets opened | C18: Rs crore | D18: =Model!D355 -> 0.91405906 | E18: =Model!E355 -> 3.7582089 | F18: =Model!F355 -> 9.6504538 | G18: =Model!G355 -> 18.794739 | H18: =Model!H355 -> 31.39501 | I18: =Model!I355 -> 46.571198 | J18: =Model!J355 -> 64.459268 | K18: =Model!K355 -> 84.043186 | L18: =Model!L355 -> 259.58612
B19: Uplift vs baseline GMV | C19: % | D19: =Model!D359 -> 2.5319837e-05 | E19: =Model!E359 -> 7.880564e-05 | F19: =Model!F359 -> 0.00016320652 | G19: =Model!G359 -> 0.00025632057 | H19: =Model!H359 -> 0.00035784904 | I19: =Model!I359 -> 0.000442908 | J19: =Model!J359 -> 0.0005328631 | K19: =Model!K359 -> 0.00060321187 | L19: =Model!L359 -> 0.00032479683
B20: Drawdowns prompted by members' cash plans | C20: Rs crore | D20: =Model!D350 -> 29.581971 | E20: =Model!E350 -> 92.046086 | F20: =Model!F350 -> 190.69251 | G20: =Model!G350 -> 295.93929 | H20: =Model!H350 -> 407.7864 | I20: =Model!I350 -> 491.1516 | J20: =Model!J350 -> 578.91703 | K20: =Model!K350 -> 633.80031 | L20: =Model!L350 -> 2719.9152
B21: Revenue | C21: Rs crore | D21: =Model!D367 -> 1.4430967 | E21: =Model!E367 -> 4.4953516 | F21: =Model!F367 -> 9.3234006 | G21: =Model!G367 -> 14.490365 | H21: =Model!H367 -> 19.997406 | I21: =Model!I367 -> 24.134265 | J21: =Model!J367 -> 28.500185 | K21: =Model!K367 -> 31.277196 | L21: =Model!L367 -> 133.66127
B22: of which membership | C22: Rs crore | D22: =Model!D360 -> 0.58883948 | E22: =Model!E360 -> 1.8322095 | F22: =Model!F360 -> 3.7958011 | G22: =Model!G360 -> 5.8907749 | H22: =Model!H360 -> 8.1171308 | I22: =Model!I360 -> 9.7765442 | J22: =Model!J360 -> 11.523546 | K22: =Model!K360 -> 12.616017 | L22: =Model!L360 -> 54.140863
B23: of which outlet add-ons | C23: Rs crore | D23: =Model!D361 -> 0.017511944 | E23: =Model!E361 -> 0.054489468 | F23: =Model!F361 -> 0.11288621 | G23: =Model!G361 -> 0.17519022 | H23: =Model!H361 -> 0.24140151 | I23: =Model!I361 -> 0.29075207 | J23: =Model!J361 -> 0.34270747 | K23: =Model!K361 -> 0.37519729 | L23: =Model!L361 -> 1.6101362
B24: of which shift-check passes | C24: Rs crore | D24: =Model!D362 -> 0.17487474 | E24: =Model!E362 -> 0.54449824 | F24: =Model!F362 -> 1.1287852 | G24: =Model!G362 -> 1.7533074 | H24: =Model!H362 -> 2.4181462 | I24: =Model!I362 -> 2.9159931 | J24: =Model!J362 -> 3.4408806 | K24: =Model!K362 -> 3.7724671 | L24: =Model!L362 -> 16.148953
B25: of which CA packs | C25: Rs crore | D25: =Model!D363 -> 0.058588049 | E25: =Model!E363 -> 0.18230024 | F25: =Model!F363 -> 0.37767268 | G25: =Model!G363 -> 0.5861173 | H25: =Model!H363 -> 0.80763412 | I25: =Model!I363 -> 0.97274159 | J25: =Model!J363 -> 1.1465638 | K25: =Model!K363 -> 1.255262 | L25: =Model!L363 -> 5.3868798
B26: of which credit (paid by lenders) | C26: Rs crore | D26: =Model!D364 -> 0.59163943 | E26: =Model!E364 -> 1.8409217 | F26: =Model!F364 -> 3.8138503 | G26: =Model!G364 -> 5.9187857 | H26: =Model!H364 -> 8.155728 | I26: =Model!I364 -> 9.823032 | J26: =Model!J364 -> 11.578341 | K26: =Model!K364 -> 12.676006 | L26: =Model!L364 -> 54.398304
B27: of which payment margin and device subscriptions | C27: Rs crore | D27: =Model!D365+Model!D366 -> 0.011643019 | E27: =Model!E365+Model!E366 -> 0.040932466 | F27: =Model!F365+Model!F366 -> 0.094405076 | G27: =Model!G365+Model!G366 -> 0.16618993 | H27: =Model!H365+Model!H366 -> 0.25736501 | I27: =Model!I365+Model!I366 -> 0.35520231 | J27: =Model!J365+Model!J366 -> 0.46814629 | K27: =Model!K365+Model!K366 -> 0.58224684 | L27: =Model!L365+Model!L366 -> 1.9761309
B28: Variable cost | C28: Rs crore | D28: =Model!D375 -> 0.89595755 | E28: =Model!E375 -> 2.3935098 | F28: =Model!F375 -> 4.5493002 | G28: =Model!G375 -> 6.4241371 | H28: =Model!H375 -> 8.4131684 | I28: =Model!I375 -> 9.4539998 | J28: =Model!J375 -> 11.010326 | K28: =Model!K375 -> 11.514005 | L28: =Model!L375 -> 54.654405
B29: Contribution to Paytm | C29: Rs crore | D29: =Model!D376 -> 0.5471391 | E29: =Model!E376 -> 2.1018418 | F29: =Model!F376 -> 4.7741005 | G29: =Model!G376 -> 8.0662284 | H29: =Model!H376 -> 11.584237 | I29: =Model!I376 -> 14.680266 | J29: =Model!J376 -> 17.489858 | K29: =Model!K376 -> 19.763191 | L29: =Model!L376 -> 79.006862
B30: of which single-outlet members | C30: Rs crore | D30: =Model!D241 -> 0.28897673 | E30: =Model!E241 -> 1.0802628 | F30: =Model!F241 -> 2.4280338 | G30: =Model!G241 -> 4.0654486 | H30: =Model!H241 -> 5.8135449 | I30: =Model!I241 -> 7.3300191 | J30: =Model!J241 -> 8.7217251 | K30: =Model!K241 -> 9.8241099 | L30: =Model!L241 -> 39.552121
B31: of which 2-5 outlet members | C31: Rs crore | D31: =Model!D276 -> 0.23911021 | E31: =Model!E276 -> 0.92303651 | F31: =Model!F276 -> 2.1007465 | G31: =Model!G276 -> 3.5556847 | H31: =Model!H276 -> 5.1116646 | I31: =Model!I276 -> 6.4856462 | J31: =Model!J276 -> 7.7316257 | K31: =Model!K276 -> 8.7450335 | L31: =Model!L276 -> 34.892548
B32: of which 6-20 outlet members | C32: Rs crore | D32: =Model!D313 -> 0.029002626 | E32: =Model!E313 -> 0.11244904 | F32: =Model!F313 -> 0.25634523 | G32: =Model!G313 -> 0.43449186 | H32: =Model!H313 -> 0.62504218 | I32: =Model!I313 -> 0.79366687 | J32: =Model!J313 -> 0.94633559 | K32: =Model!K313 -> 1.0708972 | L32: =Model!L313 -> 4.2682306
B33: of which 21+ outlet members | C33: Rs crore | D33: =Model!D344 -> -0.0099504581 | E33: =Model!E344 -> -0.013906534 | F33: =Model!F344 -> -0.011025068 | G33: =Model!G344 -> 0.010603282 | H33: =Model!H344 -> 0.033985476 | I33: =Model!I344 -> 0.070933395 | J33: =Model!J344 -> 0.0901718 | K33: =Model!K344 -> 0.1231502 | L33: =Model!L344 -> 0.29396209
B34: Contribution margin | C34: % | D34: =Model!D377 -> 0.37914238 | E34: =Model!E377 -> 0.46755893 | F34: =Model!F377 -> 0.5120557 | G34: =Model!G377 -> 0.55666149 | H34: =Model!H377 -> 0.579287 | I34: =Model!I377 -> 0.60827481 | J34: =Model!J377 -> 0.61367526 | K34: =Model!K377 -> 0.6318722 | L34: =Model!L377 -> 0.59109766
B35: Quarterly contribution vs Q1 FY27 EBITDA (Rs 203 crore) | C35: % | D35: =Model!D385 -> 0.0026952665 | E35: =Model!E385 -> 0.010353901 | F35: =Model!F385 -> 0.023517736 | G35: =Model!G385 -> 0.039735115 | H35: =Model!H385 -> 0.057065208 | I35: =Model!I385 -> 0.072316579 | J35: =Model!J385 -> 0.086156937 | K35: =Model!K385 -> 0.09735562
B37: B. Scenarios side by side
B38: Metric | C38: Unit | D38: Bear | E38: Base | F38: Bull
B39: Incremental GMV, 8 quarters | C39: Rs crore | D39: =Model!L160 -> 186.25748 | E39: =Model!L356 -> 2382.261 | F39: =Model!L552 -> 14354.037
B40: Incremental GMV in Q3 FY29 | C40: Rs crore | D40: =Model!K160 -> 50.545575 | E40: =Model!K356 -> 626.60787 | F40: =Model!K552 -> 3747.4101
B41: Uplift vs baseline GMV at Q3 FY29 | C41: % | D41: =Model!K163 -> 4.8658327e-05 | E41: =Model!K359 -> 0.00060321187 | F41: =Model!K555 -> 0.003607491
B42: Contribution to Paytm, 8 quarters | C42: Rs crore | D42: =Model!L180 -> 2.0934593 | E42: =Model!L376 -> 79.006862 | F42: =Model!L572 -> 707.01042
B43: Contribution in Q3 FY29 | C43: Rs crore | D43: =Model!K180 -> 1.1387093 | E43: =Model!K376 -> 19.763191 | F43: =Model!K572 -> 167.37371
B44: Q3 FY29 contribution vs Q1 FY27 EBITDA | C44: % | D44: =Model!K189 -> 0.0056094052 | E44: =Model!K385 -> 0.09735562 | F44: =Model!K581 -> 0.82450104
B45: Contribution margin, 8 quarters | C45: % | D45: =Model!L181 -> 0.09589474 | E45: =Model!L377 -> 0.59109766 | F45: =Model!L573 -> 0.88068742
B46: Revenue, 8 quarters | C46: Rs crore | D46: =Model!L171 -> 21.830804 | E46: =Model!L367 -> 133.66127 | F46: =Model!L563 -> 802.79382
B47: Fees paid by merchants as a share of revenue, 8 quarters | C47: % | D47: =Model!L182 -> 0.84209136 | E47: =Model!L378 -> 0.57822908 | F47: =Model!L574 -> 0.37908134
B48: Credit revenue (paid by lenders), 8 quarters | C48: Rs crore | D48: =Model!L168 -> 3.2189319 | E48: =Model!L364 -> 54.398304 | F48: =Model!L560 -> 488.26865
B49: Credit as a share of revenue, 8 quarters | C49: % | D49: =Model!L183 -> 0.14744908 | E49: =Model!L379 -> 0.4069863 | F49: =Model!L575 -> 0.60821177
B50: Paying members at Q3 FY29 | C50: lakh | D50: =Model!K150 -> 0.8122223 | E50: =Model!K346 -> 2.1132356 | F50: =Model!K542 -> 4.6132258
B51: of which single-outlet | C51: lakh | D51: =Model!K14 -> 0.61524821 | E51: =Model!K210 -> 1.32515 | F51: =Model!K406 -> 2.8396071
B52: of which 2-5 outlets | C52: lakh | D52: =Model!K48 -> 0.18930714 | E52: =Model!K244 -> 0.75722857 | F52: =Model!K440 -> 1.7037643
B53: of which 6-20 outlets | C53: lakh | D53: =Model!K83 -> 0.0075722857 | E53: =Model!K279 -> 0.030289143 | F53: =Model!K475 -> 0.068150571
B54: of which 21+ outlets | C54: lakh | D54: =Model!K120 -> 9.4653571e-05 | E54: =Model!K316 -> 0.00056792143 | F54: =Model!K512 -> 0.0017037643
B55: Member outlets at Q3 FY29 | C55: lakh | D55: =Model!K152 -> 1.1256261 | E55: =Model!K348 -> 3.6232491 | F55: =Model!K544 -> 8.8814924
B56: Drawdowns prompted by members' cash plans, 8 quarters | C56: Rs crore | D56: =Model!L154 -> 214.59546 | E56: =Model!L350 -> 2719.9152 | F56: =Model!L546 -> 19530.746
B57: Contribution per member outlet per month (Q3 FY29) | C57: Rs / month | D57: =Model!K185 -> 44.898723 | E57: =Model!K381 -> 188.56027 | F57: =Model!K577 -> 632.63397
B58: Contribution per member business per month (Q3 FY29) | C58: Rs / month | D58: =Model!K186 -> 62.22333 | E58: =Model!K382 -> 323.2961 | F58: =Model!K578 -> 1217.962
B59: Months to recover onboarding | C59: months | D59: =Model!K188 -> 8.6250587 | E59: =Model!K384 -> 1.2387106 | F59: =Model!K580 -> 0.24423092
B60: Net gain per outlet, 2-5 outlet member with the pass | C60: Rs / month | D60: =Model!K195 -> 831.21739 | E60: =Model!K391 -> 2271.4 | F60: =Model!K587 -> 6544.2143
B61: Return per Rs 1 of fees, 2-5 outlet member with the pass | C61: x | D61: =Model!K196 -> 6.7810705 | E61: =Model!K392 -> 13.717805 | F61: =Model!K588 -> 26.584753
B62: Net gain, single-outlet member without the pass | C62: Rs / month | D62: =Model!K200 -> -14 | E62: =Model!K396 -> 201 | F62: =Model!K592 -> 781
B64: C. By business size, base case
B65: Metric | C65: Unit | D65: 1 outlet | E65: 2-5 | F65: 6-20 | G65: 21+ | H65: All
B66: Paying members at Q3 FY29 | C66: lakh | D66: =Model!K210 -> 1.32515 | E66: =Model!K244 -> 0.75722857 | F66: =Model!K279 -> 0.030289143 | G66: =Model!K316 -> 0.00056792143 | H66: =Model!K346 -> 2.1132356
B67: Member outlets at Q3 FY29 | C67: lakh | D67: =Model!K214 -> 1.353584 | E67: =Model!K248 -> 1.9093194 | F67: =Model!K283 -> 0.30354135 | G67: =Model!K320 -> 0.056804329 | H67: =Model!K348 -> 3.6232491
B68: Incremental GMV, 8 quarters | C68: Rs crore | D68: =Model!L225 -> 399.98198 | E68: =Model!L260 -> 1683.0775 | F68: =Model!L296 -> 252.74309 | G68: =Model!L330 -> 46.458431 | H68: =Model!L356 -> 2382.261
B69: Revenue, 8 quarters | C69: Rs crore | D69: =Model!L232 -> 60.152977 | E69: =Model!L267 -> 63.864657 | F69: =Model!L304 -> 8.5820518 | G69: =Model!L337 -> 1.0615805 | H69: =Model!L367 -> 133.66127
B70: Contribution, 8 quarters | C70: Rs crore | D70: =Model!L241 -> 39.552121 | E70: =Model!L276 -> 34.892548 | F70: =Model!L313 -> 4.2682306 | G70: =Model!L344 -> 0.29396209 | H70: =Model!L376 -> 79.006862
B71: Contribution in Q3 FY29 | C71: Rs crore | D71: =Model!K241 -> 9.8241099 | E71: =Model!K276 -> 8.7450335 | F71: =Model!K313 -> 1.0708972 | G71: =Model!K344 -> 0.1231502 | H71: =Model!K376 -> 19.763191
B72: Share of 8-quarter contribution | C72: % | D72: =IF($H$70<>0,D70/$H$70,0) -> 0.50061628 | E72: =IF($H$70<>0,E70/$H$70,0) -> 0.44163946 | F72: =IF($H$70<>0,F70/$H$70,0) -> 0.054023544 | G72: =IF($H$70<>0,G70/$H$70,0) -> 0.0037207159 | H72: =SUM(D72:G72) -> 1
B73: Contribution per member business per month, Q3 FY29 (after onboarding) | C73: Rs / month | D73: =IF(D66>0,D71*100/D66/3,0) -> 247.11944 | E73: =IF(E66>0,E71*100/E66/3,0) -> 384.9579 | F73: =IF(F66>0,F71*100/F66/3,0) -> 1178.5271 | G73: =IF(G66>0,G71*100/G66/3,0) -> 7228.1241 | H73: =IF(H66>0,H71*100/H66/3,0) -> 311.73666
B75: D. What a business pays a month at base prices (excluding GST)
B76: Outlets in the business (change these to test other sizes) | C76: outlets | D76: 1 | E76: 3 | F76: 5 | G76: 6 | H76: 10 | I76: 20 | J76: 50 | K76: 100 | L76: 1000
B77: Membership (first 5 outlets included) | C77: Rs / month | D77: =Assumptions!$E$25 -> 199 | E77: =Assumptions!$E$25 -> 199 | F77: =Assumptions!$E$25 -> 199 | G77: =Assumptions!$E$25 -> 199 | H77: =Assumptions!$E$25 -> 199 | I77: =Assumptions!$E$25 -> 199 | J77: =Assumptions!$E$25 -> 199 | K77: =Assumptions!$E$25 -> 199 | L77: =Assumptions!$E$25 -> 199
B78: Outlet add-ons (6-10, 11-20, 21+ slabs) | C78: Rs / month | D78: =MAX(0,MIN(D$76,10)-5)*Assumptions!$E$26+MAX(0,MIN(D$76,20)-10)*Assumptions!$E$27+MAX(0,D$76-20)*Assumptions!$E$28 -> 0 | E78: =MAX(0,MIN(E$76,10)-5)*Assumptions!$E$26+MAX(0,MIN(E$76,20)-10)*Assumptions!$E$27+MAX(0,E$76-20)*Assumptions!$E$28 -> 0 | F78: =MAX(0,MIN(F$76,10)-5)*Assumptions!$E$26+MAX(0,MIN(F$76,20)-10)*Assumptions!$E$27+MAX(0,F$76-20)*Assumptions!$E$28 -> 0 | G78: =MAX(0,MIN(G$76,10)-5)*Assumptions!$E$26+MAX(0,MIN(G$76,20)-10)*Assumptions!$E$27+MAX(0,G$76-20)*Assumptions!$E$28 -> 49 | H78: =MAX(0,MIN(H$76,10)-5)*Assumptions!$E$26+MAX(0,MIN(H$76,20)-10)*Assumptions!$E$27+MAX(0,H$76-20)*Assumptions!$E$28 -> 245 | I78: =MAX(0,MIN(I$76,10)-5)*Assumptions!$E$26+MAX(0,MIN(I$76,20)-10)*Assumptions!$E$27+MAX(0,I$76-20)*Assumptions!$E$28 -> 1035 | J78: =MAX(0,MIN(J$76,10)-5)*Assumptions!$E$26+MAX(0,MIN(J$76,20)-10)*Assumptions!$E$27+MAX(0,J$76-20)*Assumptions!$E$28 -> 4005 | K78: =MAX(0,MIN(K$76,10)-5)*Assumptions!$E$26+MAX(0,MIN(K$76,20)-10)*Assumptions!$E$27+MAX(0,K$76-20)*Assumptions!$E$28 -> 8955 | L78: =MAX(0,MIN(L$76,10)-5)*Assumptions!$E$26+MAX(0,MIN(L$76,20)-10)*Assumptions!$E$27+MAX(0,L$76-20)*Assumptions!$E$28 -> 98055
B79: Monthly bill, membership and add-ons | C79: Rs / month | D79: =D77+D78 -> 199 | E79: =E77+E78 -> 199 | F79: =F77+F78 -> 199 | G79: =G77+G78 -> 248 | H79: =H77+H78 -> 444 | I79: =I77+I78 -> 1234 | J79: =J77+J78 -> 4204 | K79: =K77+K78 -> 9154 | L79: =L77+L78 -> 98254
B80: Per outlet | C80: Rs / outlet | D80: =D79/D$76 -> 199 | E80: =E79/E$76 -> 66.333333 | F80: =F79/F$76 -> 39.8 | G80: =G79/G$76 -> 41.333333 | H80: =H79/H$76 -> 44.4 | I80: =I79/I$76 -> 61.7 | J80: =J79/J$76 -> 84.08 | K80: =K79/K$76 -> 91.54 | L80: =L79/L$76 -> 98.254
B81: With the shift-check pass on every outlet | C81: Rs / month | D81: =D79+D$76*Assumptions!$E$29 -> 298 | E81: =E79+E$76*Assumptions!$E$29 -> 496 | F81: =F79+F$76*Assumptions!$E$29 -> 694 | G81: =G79+G$76*Assumptions!$E$29 -> 842 | H81: =H79+H$76*Assumptions!$E$29 -> 1434 | I81: =I79+I$76*Assumptions!$E$29 -> 3214 | J81: =J79+J$76*Assumptions!$E$29 -> 9154 | K81: =K79+K$76*Assumptions!$E$29 -> 19054 | L81: =L79+L$76*Assumptions!$E$29 -> 197254
B82: Per outlet, with passes | C82: Rs / outlet | D82: =D81/D$76 -> 298 | E82: =E81/E$76 -> 165.33333 | F82: =F81/F$76 -> 138.8 | G82: =G81/G$76 -> 140.33333 | H82: =H81/H$76 -> 143.4 | I82: =I81/I$76 -> 160.7 | J82: =J81/J$76 -> 183.08 | K82: =K81/K$76 -> 190.54 | L82: =L81/L$76 -> 197.254
B84: E. Context
B85: Baseline GMV, Q1 FY27 actual | C85: Rs lakh crore | D85: =Baseline!E12 -> 7.1
B86: Baseline GMV, Q3 FY29 FORECAST (linear) | C86: Rs lakh crore | D86: =Baseline!E22 -> 10.387857
B87: Baseline GMV, Q3 FY29 GROWTH cross-check | C87: Rs lakh crore | D87: =Baseline!G22 -> 12.851426
B88: Device merchants, Q3 FY29 FORECAST | C88: crore | D88: =Baseline!H22 -> 2.2271429
B89: Q1 FY27 contribution profit | C89: Rs crore | D89: =Baseline!F27 -> 1350
B90: Q1 FY27 EBITDA | C90: Rs crore | D90: =Baseline!F29 -> 203
B91: Q1 FY27 financial services revenue | C91: Rs crore | D91: =Baseline!F31 -> 814
B92: Previous version (flat Rs 199 per outlet, 2-5 outlets only): base contribution, 8 quarters | C92: Rs crore | D92: =Baseline!F36 -> 45.87
B93: Previous version: base incremental GMV, 8 quarters | C93: Rs crore | D93: =Baseline!F37 -> 1792.07
B94: Earlier option (dropped): Mohalla, base contribution, 8 quarters | C94: Rs crore | D94: =Baseline!F38 -> 29.52
B95: Earlier option (parked): Restock Agent, base contribution, 8 quarters | C95: Rs crore | D95: =Baseline!F39 -> 26.22
B96: Earlier option (parked): Restock Agent, supplier payments new to Paytm, 8 quarters | C96: Rs crore | D96: =Baseline!F40 -> 20419.56
B97: Earlier option (folded in): Soundbox Care, base contribution, 8 quarters | C97: Rs crore | D97: =Baseline!F41 -> 70.01
B98: Munim credit revenue at Q3 FY29 vs Q1 FY27 financial services revenue | C98: % | D98: =Model!K386 -> 0.015572489
B100: F. Checks
B101: Devices accounted for by the four bands stay at or under 100% of device merchants in every scenario | D101: =IF(AND(Assumptions!D11+Assumptions!D12*Assumptions!D15+Assumptions!D13*Assumptions!D16+Assumptions!D14*Assumptions!D17<=1,Assumptions!E11+Assumptions!E12*Assumptions!E15+Assumptions!E13*Assumptions!E16+Assumptions!E14*Assumptions!E17<=1,Assumptions!F11+Assumptions!F12*Assumptions!F15+Assumptions!F13*Assumptions!F16+Assumptions!F14*Assumptions!F17<=1),"OK","CHECK") -> OK
B102: GMV sources add up to incremental GMV (base, 8 quarters) | D102: =IF(ABS(SUM(L14:L18)-L13)<0.001,"OK","CHECK") -> OK
B103: Revenue streams add up to revenue (base, 8 quarters) | D103: =IF(ABS(SUM(L22:L27)-L21)<0.001,"OK","CHECK") -> OK
B104: Band contributions add up to total contribution (base, 8 quarters) | D104: =IF(ABS(SUM(L30:L33)-L29)<0.001,"OK","CHECK") -> OK
B105: Design flag: credit stays under half of revenue in the base case (lending is a tab, not the business) | D105: =IF(E49<0.5,"OK","CHECK") -> OK
B106: Base-case contribution is positive in every quarter | D106: =IF(MIN(D29:K29)>0,"OK","CHECK") -> OK
...

Sheet Sources
A1: Sources
A3: ID | B3: What it supports | C3: Link
A4: S1 | B4: Paytm Q1 FY27 earnings release (agent datapack): GMV, subscription merchants, net payment revenue 8.4 bps, processing margin >4 bps, cashback | C4: https://paytm.com/document/ir/financial-results/fy2026-27/Paytm_Q1_FY27_Agent_Datapack.md
A5: S2 | B5: Q2 FY26 (Sep-25): GMV Rs 5.67 lakh crore, subscriptions 1.37 crore | C5: https://ianslive.in/paytms-profitability-improves-to-rs-211-crore-in-q2-revenue-up-24-pc--20251104222037
A6: S3 | B6: Q3 FY26 (Dec-25): GMV Rs 6.2 lakh crore | C6: https://www.businesstoday.in/amp/latest/corporate/story/paytms-q3-net-profit-jumps-to-rs225-crore-on-upi-surge-and-merchant-services-boost-513573-2026-01-29
A7: S4 | B7: Q4 FY25 (Mar-25): GMV Rs 5.1 lakh crore, subscriptions 1.24 crore | C7: https://www.business-standard.com/companies/quarterly-results/one-97-communication-paytm-q4-fy25-result-loss-profit-revenue-stock-option-125050601030_1.html
A8: S5 | B8: Q3 FY25 (Dec-24): GMV Rs 5.0 lakh crore, up 13% QoQ from Rs 4.5 lakh crore; subscriptions 1.17 crore | C8: https://inc42.com/?p=495669
A9: S6 | B9: Q3 FY26 (Dec-25): subscription merchants 1.44 crore | C9: https://alphastreet.com/india/symbol/PAYTM
A10: S7 | B10: Soundbox rental Rs 125-150 a month (BofA merchant checks in Mumbai) | C10: https://www.outlookbusiness.com/amp/story/enterprise/bofa-research-paytm-soundbox-first-to-bring-audio-based-payments-confirmations-dominates-the-market-6795
A11: S8 | B11: Paytm subscription revenue ~Rs 90 per device a month (Q4 FY24) | C11: https://www.medianama.com/2024/10/223-paytm-to-monetize-soundbox-ads-in-partnership-with-meesho-a-shift-away-from-core-payments-business/
A12: S9 | B12: Several soundboxes on one counter (Inc42) | C12: https://inc42.com/buzz/upi-transactions-jump-3-8-mom-in-may-cross-23-bn-mark/
A13: S10 | B13: Paytm Q1 FY27 results: revenue Rs 2,448 crore, contribution profit Rs 1,350 crore at 55%, EBITDA Rs 203 crore, PAT Rs 220 crore, financial services Rs 814 crore | C13: https://paytm.com/blog/investor-relations/paytm-q1-fy27-results-revenue-grows-28-to-2448-crore-highest-ever-quarterly-ebitda-at-203-crore/
A14: S11 | B14: Paytm merchant loans, repeat borrowers (Aug 2022 release) | C14: https://bseindia.com/xml-data/corpfiling/AttachHis/01144943-65d3-465d-a4cc-f0556ff55ec5.pdf
... A42: S39 | B42: Merchant forum thread on Paytm Soundbox monthly charges rising from Rs 29 to Rs 135 (DesiDime; anecdotal) | C42: https://www.desidime.com/discussions/arbitrary-monthly-charges-on-paytm-business-soundbox
