Workbook

Sheet README
B2: Mohalla Network + Intent Guard: 8-quarter GMV projection
B3: Paytm Build for India AI Hackathon, Mumbai | Track 1: Merchant Growth AI | Kamalika Poddar
B5: What this model does
B6: 1. Baseline: Paytm merchant GMV and device (subscription) merchants for Q2 FY27 to Q3 FY29, projected with FORECAST (linear) on 8 reported quarters, Q2 FY25 to Q1 FY27. GROWTH (exponential) is shown alongside as a cross-check.
B7: 2. Bundle: incremental GMV from Mohalla Network (new customers, repeat visits, share of counter, merchants retained), plus Paytm revenue, costs and contribution, for 8 quarters from Q4 FY27 (Jan-Mar 2027 pilot) to Q3 FY29.
B8: 3. Three scenarios (Bear, Base, Bull) run side by side on the Model sheet. Summary pulls the numbers used on the pitch slide.
B10: How to use it
B11: Change blue cells on Assumptions (and reported actuals on Baseline). Every other number is a formula and recalculates.
B12: Colour code: blue text = input | black text = formula | green text = link to another sheet | yellow fill = key assumption.
B13: Units: lakh = 1,00,000 | crore = 1,00,00,000 | Rs 1 lakh crore = Rs 1,00,000 crore. Quarters follow India's April-March fiscal year.
B15: Metrics
B16: North Star: Paytm-processed GMV per active device merchant (tracked on the Model sheet for participating merchants).
... B27: Caveat: reported figures come from Paytm's disclosures and press coverage (see Sources). Everything on Assumptions is a team estimate for a hackathon pitch, not Paytm data.

Sheet Assumptions
A1: Assumptions: Mohalla Network + Intent Guard
A2: Blue cells are inputs. Bear / Base / Bull columns feed the three scenario blocks on the Model sheet. These are team estimates unless a source is named.
A4: ID | B4: Assumption | C4: Unit | D4: Bear | E4: Base | F4: Bull | L4: Why this number / source
A5: Scope and rollout
A6: A1 | B6: Share of device merchants in dense clusters that can run Mohalla | C6: % of device merchants | D6: 0.2 | E6: 0.3 | F6: 0.4 | L6: Needs two or more Paytm-acquired, non-competing shops within ~500 m that share payers. Paytm does not disclose the city split of its device base.
A7: A2 | B7: Participation: covered eligible merchants who accept at least one partnership | C7: % of covered merchants | D7: 0.08 | E7: 0.15 | F7: 0.25 | L7: Team estimate. No public benchmark for opt-in to merchant cross-promotion on payment devices.
A8: Demand: new customers
A9: A3 | B9: New customers (first redemptions) per participating merchant per month | C9: customers / month | D9: 5 | E9: 10 | F9: 15 | L9: About 1-1.5% of a partner shop's ~1,000 monthly payers redeeming. Each partnership runs both ways.
A10: A4 | B10: First-visit bill (offer minimum bill) | C10: Rs per visit | D10: 250 | E10: 300 | F10: 350 | L10: The reward only fires on a bill at or above the minimum, so the first visit is assumed to sit at the threshold.
A11: A5 | B11: Share of new customers who become regulars | C11: % of new customers | D11: 0.1 | E11: 0.2 | F11: 0.3 | L11: Team estimate.
A12: A6 | B12: Regulars lost each quarter | C12: % per quarter | D12: 0.4 | E12: 0.3 | F12: 0.2 | L12: Team estimate.
A13: A7 | B13: Repeat spend per regular per quarter | C13: Rs per quarter | D13: 450 | E13: 600 | F13: 750 | L13: Three visits a quarter at Rs 150 / 200 / 250.
A14: Share of counter and retention
A15: A8 | B15: Paytm-processed GMV per participating merchant per month, before Mohalla | C15: Rs / month | D15: 50000 | E15: 80000 | F15: 120000 | L15: Team estimate for dense urban shops. Ceiling check on Baseline: Q1 FY27 GMV / device merchants / 3 = ~Rs 1.5 lakh a month if all GMV came from device merchants (it does not).
A16: A9 | B16: Share-of-counter shift: extra share of the merchant's existing collections routed to Paytm | C16: % of A8 | D16: 0.01 | E16: 0.03 | F16: 0.05 | L16: Rewards only fire on Paytm payments, so shops with several QRs steer customers to Paytm's. Merchants often keep separate soundboxes for PhonePe, Paytm and Google Pay (Sources S9).
A17: A10 | B17: Drop in annual device churn for participating merchants | C17: percentage points / year | D17: 0.01 | E17: 0.02 | F17: 0.04 | L17: Team estimate. Paytm does not disclose device churn. Retained merchants keep A8 GMV.
A18: Pricing and revenue
A19: A11 | B19: Reward per redemption, funded by the merchant | C19: Rs per redemption | D19: 25 | E19: 30 | F19: 40 | L19: Team estimate. Merchant-funded, never counted as Paytm revenue.
A20: A12 | B20: Paytm fee per redemption (Mohalla pay-per-new-customer) | C20: Rs per redemption | D20: 3 | E20: 4 | F20: 5 | L20: Business model decision: a small fee per redeemed customer. One reward per UPI ID per partnership, so every redemption is a new customer.
A21: A13 | B21: Growth plan price (Intent Guard autopilot add-on to the Soundbox plan) | C21: Rs / month | D21: 29 | E21: 49 | F21: 79 | L21: Anchors: Soundbox rental Rs 125-150 a month (S7); Paytm subscription revenue ~Rs 90 per device a month in Q4 FY24 (S8).
A22: A14 | B22: Growth plan attach rate | C22: % of participating merchants | D22: 0.05 | E22: 0.1 | F22: 0.2 | L22: Team estimate.
A23: A15 | B23: Payment processing margin on incremental GMV | C23: % of GMV | D23: 0.0004 | E23: 0.0004 | F23: 0.0004 | L23: Paytm Q1 FY27: payment processing margin 'comfortably above 4 bps' (S1). Held at 4 bps in all scenarios.
A24: A16 | B24: Device subscription revenue per retained merchant | C24: Rs / month | D24: 80 | E24: 90 | F24: 100 | L24: ~Rs 90 per device a month in Q4 FY24 (S8); Q1 FY27 release notes a modest YoY decline per device (S1).
A25: Costs and Intent Guard
A26: A17 | B26: UPI payout cost per reward | C26: Rs per payout | D26: 2 | E26: 1 | F26: 0.5 | L26: Team estimate.
A27: A18 | B27: AI inference cost per participating merchant | C27: Rs / month | D27: 15 | E27: 8 | F27: 5 | L27: Team estimate. Paytm runs fine-tuned small models in-house (S1).
A28: A19 | B28: Extra inference per Growth plan merchant (autopilot, guard checks) | C28: Rs / month | D28: 25 | E28: 15 | F28: 10 | L28: Team estimate.
A29: A20 | B29: Share of reward spend Intent Guard blocks (farming, collusion, overspend, injected deals) | C29: % of reward spend | D29: 0.02 | E29: 0.05 | F29: 0.08 | L29: Team estimate. Shown as merchant money protected; not counted as Paytm revenue.
A31: Rollout coverage of eligible clusters (same in all scenarios)
B32: Quarter | D32: Q4 FY27 | E32: Q1 FY28 | F32: Q2 FY28 | G32: Q3 FY28 | H32: Q4 FY28 | I32: Q1 FY29 | J32: Q2 FY29 | K32: Q3 FY29
A33: A21 | B33: Share of eligible clusters live | C33: % of eligible | D33: 0.02 | E33: 0.08 | F33: 0.2 | G33: 0.35 | H33: 0.5 | I33: 0.65 | J33: 0.8 | K33: 0.9 | L33: Q4 FY27 is a Mumbai pilot; national rollout through FY28-FY29. Rollout pace is Paytm's choice, so it is held constant across scenarios.
A35: Structural rules built into the formulas
A36: R1 | B36: One reward per UPI ID per partnership, so every redemption is a new customer for that shop.
A37: R2 | B37: New regulars start repeat spending from the quarter after they are acquired.
A38: R3 | B38: Merchants kept by lower churn keep their pre-Mohalla GMV (A8). They count as 'GMV protected', not in the per-merchant North Star.
A39: R4 | B39: Baseline GMV and device merchants use FORECAST (linear) on 8 reported quarters, Q2 FY25 to Q1 FY27. GROWTH (exponential) is shown as a cross-check; the model uses the more conservative linear line.
A40: R5 | B40: Rewards are merchant-funded and never counted as Paytm revenue. Payment margin applies to all incremental GMV at A15.
A41: R6 | B41: Mohalla manual mode is free; merchants pay only the per-redemption fee. Intent Guard autopilot is the paid Growth plan.

Sheet Baseline
A1: Baseline: Paytm merchant GMV and device merchants
A2: Rows 5-12 are reported actuals (blue). Rows 13-22 are FORECAST (linear) on those 8 quarters. Column G is GROWTH (exponential) as a cross-check. The bundle model uses the linear forecast.
A4: x (period) | B4: Quarter | C4: Months | D4: Type | E4: Merchant GMV (Rs lakh crore) | F4: GMV YoY | G4: Cross-check: GROWTH (Rs lakh crore) | H4: Device merchants (crore) | I4: Source / method
A5: 1 | B5: Q2 FY25 | C5: Jul-Sep 2024 | D5: Actual | E5: 4.5 | H5: 1.12 | I5: GMV: S5 (Q3 FY25 GMV up 13% QoQ from Rs 4.5 lakh crore). Device merchants: derived, 1.17 crore at Dec-24 minus 5 lakh added that quarter (S5).
A6: 2 | B6: Q3 FY25 | C6: Oct-Dec 2024 | D6: Actual | E6: 5 | H6: 1.17 | I6: S5
A7: 3 | B7: Q4 FY25 | C7: Jan-Mar 2025 | D7: Actual | E7: 5.1 | H7: 1.24 | I7: S4
A8: 4 | B8: Q1 FY26 | C8: Apr-Jun 2025 | D8: Actual | E8: 5.4 | H8: 1.3 | I8: S1 (Jun-25 column of the Q1 FY27 release)
A9: 5 | B9: Q2 FY26 | C9: Jul-Sep 2025 | D9: Actual | E9: 5.67 | F9: =E9/E5-1 -> 0.26 | H9: 1.37 | I9: S2
A10: 6 | B10: Q3 FY26 | C10: Oct-Dec 2025 | D10: Actual | E10: 6.2 | F10: =E10/E6-1 -> 0.24 | H10: 1.44 | I10: GMV: S3. Device merchants: S6
A11: 7 | B11: Q4 FY26 | C11: Jan-Mar 2026 | D11: Actual | E11: 6.5 | F11: =E11/E7-1 -> 0.2745098 | H11: 1.51 | I11: S1 (Mar-26 column)
A12: 8 | B12: Q1 FY27 | C12: Apr-Jun 2026 | D12: Actual | E12: 7.1 | F12: =E12/E8-1 -> 0.31481481 | H12: 1.57 | I12: S1
A13: 9 | B13: Q2 FY27 | C13: Jul-Sep 2026 | D13: Forecast | E13: =FORECAST(A13,$E$5:$E$12,$A$5:$A$12) -> 7.2517857 | F13: =E13/E9-1 -> 0.27897455 | G13: =GROWTH($E$5:$E$12,$A$5:$A$12,A13) -> 7.4103976 | H13: =FORECAST(A13,$H$5:$H$12,$A$5:$A$12) -> 1.6357143 | I13: FORECAST (linear) on rows 5-12. Not yet reported; bridges to the projection window.
A14: 10 | B14: Q3 FY27 | C14: Oct-Dec 2026 | D14: Forecast | E14: =FORECAST(A14,$E$5:$E$12,$A$5:$A$12) -> 7.6002381 | F14: =E14/E10-1 -> 0.22584485 | G14: =GROWTH($E$5:$E$12,$A$5:$A$12,A14) -> 7.8778783 | H14: =FORECAST(A14,$H$5:$H$12,$A$5:$A$12) -> 1.7014286 | I14: FORECAST (linear) on rows 5-12. Not yet reported; bridges to the projection window. Rows 15-22 (shaded) are the 8-quarter projection window.
A15: 11 | B15: Q4 FY27 | C15: Jan-Mar 2027 | D15: Forecast | E15: =FORECAST(A15,$E$5:$E$12,$A$5:$A$12) -> 7.9486905 | F15: =E15/E11-1 -> 0.22287546 | G15: =GROWTH($E$5:$E$12,$A$5:$A$12,A15) -> 8.3748497 | H15: =FORECAST(A15,$H$5:$H$12,$A$5:$A$12) -> 1.7671429 | I15: FORECAST (linear) on rows 5-12
A16: 12 | B16: Q1 FY28 | C16: Apr-Jun 2027 | D16: Forecast | E16: =FORECAST(A16,$E$5:$E$12,$A$5:$A$12) -> 8.2971429 | F16: =E16/E12-1 -> 0.16861167 | G16: =GROWTH($E$5:$E$12,$A$5:$A$12,A16) -> 8.9031723 | H16: =FORECAST(A16,$H$5:$H$12,$A$5:$A$12) -> 1.8328571 | I16: FORECAST (linear) on rows 5-12
A17: 13 | B17: Q2 FY28 | C17: Jul-Sep 2027 | D17: Forecast | E17: =FORECAST(A17,$E$5:$E$12,$A$5:$A$12) -> 8.6455952 | F17: =E17/E13-1 -> 0.19220225 | G17: =GROWTH($E$5:$E$12,$A$5:$A$12,A17) -> 9.4648238 | H17: =FORECAST(A17,$H$5:$H$12,$A$5:$A$12) -> 1.8985714 | I17: FORECAST (linear) on rows 5-12
A18: 14 | B18: Q3 FY28 | C18: Oct-Dec 2027 | D18: Forecast | E18: =FORECAST(A18,$E$5:$E$12,$A$5:$A$12) -> 8.9940476 | F18: =E18/E14-1 -> 0.18339024 | G18: =GROWTH($E$5:$E$12,$A$5:$A$12,A18) -> 10.061907 | H18: =FORECAST(A18,$H$5:$H$12,$A$5:$A$12) -> 1.9642857 | I18: FORECAST (linear) on rows 5-12
A19: 15 | B19: Q4 FY28 | C19: Jan-Mar 2028 | D19: Forecast | E19: =FORECAST(A19,$E$5:$E$12,$A$5:$A$12) -> 9.3425 | F19: =E19/E15-1 -> 0.17535084 | G19: =GROWTH($E$5:$E$12,$A$5:$A$12,A19) -> 10.696656 | H19: =FORECAST(A19,$H$5:$H$12,$A$5:$A$12) -> 2.03 | I19: FORECAST (linear) on rows 5-12
A20: 16 | B20: Q1 FY29 | C20: Apr-Jun 2028 | D20: Forecast | E20: =FORECAST(A20,$E$5:$E$12,$A$5:$A$12) -> 9.6909524 | F20: =E20/E16-1 -> 0.16798669 | G20: =GROWTH($E$5:$E$12,$A$5:$A$12,A20) -> 11.371449 | H20: =FORECAST(A20,$H$5:$H$12,$A$5:$A$12) -> 2.0957143 | I20: FORECAST (linear) on rows 5-12
A21: 17 | B21: Q2 FY29 | C21: Jul-Sep 2028 | D21: Forecast | E21: =FORECAST(A21,$E$5:$E$12,$A$5:$A$12) -> 10.039405 | F21: =E21/E17-1 -> 0.16121614 | G21: =GROWTH($E$5:$E$12,$A$5:$A$12,A21) -> 12.08881 | H21: =FORECAST(A21,$H$5:$H$12,$A$5:$A$12) -> 2.1614286 | I21: FORECAST (linear) on rows 5-12
A22: 18 | B22: Q3 FY29 | C22: Oct-Dec 2028 | D22: Forecast | E22: =FORECAST(A22,$E$5:$E$12,$A$5:$A$12) -> 10.387857 | F22: =E22/E18-1 -> 0.15497022 | G22: =GROWTH($E$5:$E$12,$A$5:$A$12,A22) -> 12.851426 | H22: =FORECAST(A22,$H$5:$H$12,$A$5:$A$12) -> 2.2271429 | I22: FORECAST (linear) on rows 5-12
A25: Reported reference points (Q1 FY27, quarter ended 30 June 2026) and checks
B26: Net payment revenue, excluding PIDF | D26: Rs crore | F26: 601 | I26: S1
B27: Net payment revenue per Rs of GMV | D27: bps | F27: =F26/(E12*100000)*10000 -> 8.4647887 | I27: Formula. Paytm reports 8.4 bps (S1).
B28: Payment processing margin (reported as 'comfortably above 4 bps') | D28: bps | F28: 4 | I28: S1
B29: Net payment revenue from a 1% GMV lift | D29: Rs crore per quarter | F29: =E12*100000*0.01*F27/10000 -> 6.01 | I29: Formula: why raw GMV growth barely moves Paytm's P&L.
B30: Marketing Services revenue | D30: Rs crore | F30: 239 | I30: S1 (down 3% YoY)
B31: Promotional cashback and incentives | D31: Rs crore | F31: 90 | I31: S1 (up 143% YoY)
B32: Registered merchants | D32: crore | F32: 5 | I32: S1
B33: Ceiling: GMV per device merchant per month if all GMV came from device merchants | D33: Rs / month | F33: =E12*1000000000000/(H12*10000000)/3 -> 150743.1 | I33: Formula. Upper bound used to sanity-check A8.
B34: Q3 FY29 baseline: GROWTH cross-check vs FORECAST | D34: % above linear | F34: =G22/E22-1 -> 0.2371585 | I34: Formula. How conservative the linear baseline is.

Sheet Model
A1: Model: Mohalla Network + Intent Guard, quarter by quarter
A2: Every cell is a formula. Assumption references: Bear = Assumptions column D, Base = E, Bull = F. Column L sums flows over the 8 quarters; stock and ratio rows are read at Q3 FY29 (column K).
A4: # | B4: Quarter | C4: Unit | D4: Q4 FY27 | E4: Q1 FY28 | F4: Q2 FY28 | G4: Q3 FY28 | H4: Q4 FY28 | I4: Q1 FY29 | J4: Q2 FY29 | K4: Q3 FY29 | L4: 8-qtr total
B5: Months | D5: Jan-Mar 2027 | E5: Apr-Jun 2027 | F5: Jul-Sep 2027 | G5: Oct-Dec 2027 | H5: Jan-Mar 2028 | I5: Apr-Jun 2028 | J5: Jul-Sep 2028 | K5: Oct-Dec 2028
B6: Baseline period index (x) | D6: =Baseline!A15 -> 11 | E6: =Baseline!A16 -> 12 | F6: =Baseline!A17 -> 13 | G6: =Baseline!A18 -> 14 | H6: =Baseline!A19 -> 15 | I6: =Baseline!A20 -> 16 | J6: =Baseline!A21 -> 17 | K6: =Baseline!A22 -> 18
A8: BEAR scenario (Assumptions column D)
A9: 1 | B9: Device merchants, baseline | C9: lakh | D9: =Baseline!H15*100 -> 176.71429 | E9: =Baseline!H16*100 -> 183.28571 | F9: =Baseline!H17*100 -> 189.85714 | G9: =Baseline!H18*100 -> 196.42857 | H9: =Baseline!H19*100 -> 203 | I9: =Baseline!H20*100 -> 209.57143 | J9: =Baseline!H21*100 -> 216.14286 | K9: =Baseline!H22*100 -> 222.71429
A10: 2 | B10: Eligible merchants (dense clusters) | C10: lakh | D10: =D9*Assumptions!$D$6 -> 35.342857 | E10: =E9*Assumptions!$D$6 -> 36.657143 | F10: =F9*Assumptions!$D$6 -> 37.971429 | G10: =G9*Assumptions!$D$6 -> 39.285714 | H10: =H9*Assumptions!$D$6 -> 40.6 | I10: =I9*Assumptions!$D$6 -> 41.914286 | J10: =J9*Assumptions!$D$6 -> 43.228571 | K10: =K9*Assumptions!$D$6 -> 44.542857
A11: 3 | B11: Rollout coverage | C11: % of eligible | D11: =Assumptions!D$33 -> 0.02 | E11: =Assumptions!E$33 -> 0.08 | F11: =Assumptions!F$33 -> 0.2 | G11: =Assumptions!G$33 -> 0.35 | H11: =Assumptions!H$33 -> 0.5 | I11: =Assumptions!I$33 -> 0.65 | J11: =Assumptions!J$33 -> 0.8 | K11: =Assumptions!K$33 -> 0.9
A12: 4 | B12: Participating merchants | C12: lakh | D12: =D10*D11*Assumptions!$D$7 -> 0.056548571 | E12: =E10*E11*Assumptions!$D$7 -> 0.23460571 | F12: =F10*F11*Assumptions!$D$7 -> 0.60754286 | G12: =G10*G11*Assumptions!$D$7 -> 1.1 | H12: =H10*H11*Assumptions!$D$7 -> 1.624 | I12: =I10*I11*Assumptions!$D$7 -> 2.1795429 | J12: =J10*J11*Assumptions!$D$7 -> 2.7666286 | K12: =K10*K11*Assumptions!$D$7 -> 3.2070857
A13: 5 | B13: New customers acquired (= redemptions) | C13: lakh | D13: =D12*Assumptions!$D$9*3 -> 0.84822857 | E13: =E12*Assumptions!$D$9*3 -> 3.5190857 | F13: =F12*Assumptions!$D$9*3 -> 9.1131429 | G13: =G12*Assumptions!$D$9*3 -> 16.5 | H13: =H12*Assumptions!$D$9*3 -> 24.36 | I13: =I12*Assumptions!$D$9*3 -> 32.693143 | J13: =J12*Assumptions!$D$9*3 -> 41.499429 | K13: =K12*Assumptions!$D$9*3 -> 48.106286 | L13: =SUM(D13:K13) -> 176.63931
A14: 6 | B14: GMV: first visits | C14: Rs crore | D14: =D13*Assumptions!$D$10/100 -> 2.1205714 | E14: =E13*Assumptions!$D$10/100 -> 8.7977143 | F14: =F13*Assumptions!$D$10/100 -> 22.782857 | G14: =G13*Assumptions!$D$10/100 -> 41.25 | H14: =H13*Assumptions!$D$10/100 -> 60.9 | I14: =I13*Assumptions!$D$10/100 -> 81.732857 | J14: =J13*Assumptions!$D$10/100 -> 103.74857 | K14: =K13*Assumptions!$D$10/100 -> 120.26571 | L14: =SUM(D14:K14) -> 441.59829
A15: 7 | B15: New regulars | C15: lakh | D15: =D13*Assumptions!$D$11 -> 0.084822857 | E15: =E13*Assumptions!$D$11 -> 0.35190857 | F15: =F13*Assumptions!$D$11 -> 0.91131429 | G15: =G13*Assumptions!$D$11 -> 1.65 | H15: =H13*Assumptions!$D$11 -> 2.436 | I15: =I13*Assumptions!$D$11 -> 3.2693143 | J15: =J13*Assumptions!$D$11 -> 4.1499429 | K15: =K13*Assumptions!$D$11 -> 4.8106286 | L15: =SUM(D15:K15) -> 17.663931
A16: 8 | B16: Regulars at quarter end | C16: lakh | D16: =N(C16)*(1-Assumptions!$D$12)+D15 -> 0.084822857 | E16: =N(D16)*(1-Assumptions!$D$12)+E15 -> 0.40280229 | F16: =N(E16)*(1-Assumptions!$D$12)+F15 -> 1.1529957 | G16: =N(F16)*(1-Assumptions!$D$12)+G15 -> 2.3417974 | H16: =N(G16)*(1-Assumptions!$D$12)+H15 -> 3.8410784 | I16: =N(H16)*(1-Assumptions!$D$12)+I15 -> 5.5739613 | J16: =N(I16)*(1-Assumptions!$D$12)+J15 -> 7.4943197 | K16: =N(J16)*(1-Assumptions!$D$12)+K15 -> 9.3072204
A17: 9 | B17: GMV: repeat visits by regulars | C17: Rs crore | D17: =N(C16)*(1-Assumptions!$D$12)*Assumptions!$D$13/100 -> 0 | E17: =N(D16)*(1-Assumptions!$D$12)*Assumptions!$D$13/100 -> 0.22902171 | F17: =N(E16)*(1-Assumptions!$D$12)*Assumptions!$D$13/100 -> 1.0875662 | G17: =N(F16)*(1-Assumptions!$D$12)*Assumptions!$D$13/100 -> 3.1130883 | H17: =N(G16)*(1-Assumptions!$D$12)*Assumptions!$D$13/100 -> 6.322853 | I17: =N(H16)*(1-Assumptions!$D$12)*Assumptions!$D$13/100 -> 10.370912 | J17: =N(I16)*(1-Assumptions!$D$12)*Assumptions!$D$13/100 -> 15.049696 | K17: =N(J16)*(1-Assumptions!$D$12)*Assumptions!$D$13/100 -> 20.234663 | L17: =SUM(D17:K17) -> 56.4078
A18: 10 | B18: GMV: share-of-counter shift to Paytm | C18: Rs crore | D18: =D12*Assumptions!$D$15*3*Assumptions!$D$16/100 -> 0.84822857 | E18: =E12*Assumptions!$D$15*3*Assumptions!$D$16/100 -> 3.5190857 | F18: =F12*Assumptions!$D$15*3*Assumptions!$D$16/100 -> 9.1131429 | G18: =G12*Assumptions!$D$15*3*Assumptions!$D$16/100 -> 16.5 | H18: =H12*Assumptions!$D$15*3*Assumptions!$D$16/100 -> 24.36 | I18: =I12*Assumptions!$D$15*3*Assumptions!$D$16/100 -> 32.693143 | J18: =J12*Assumptions!$D$15*3*Assumptions!$D$16/100 -> 41.499429 | K18: =K12*Assumptions!$D$15*3*Assumptions!$D$16/100 -> 48.106286 | L18: =SUM(D18:K18) -> 176.63931
A19: 11 | B19: Merchants retained by lower churn (cumulative) | C19: lakh | D19: =N(C19)+D12*Assumptions!$D$17/4 -> 0.00014137143 | E19: =N(D19)+E12*Assumptions!$D$17/4 -> 0.00072788571 | F19: =N(E19)+F12*Assumptions!$D$17/4 -> 0.0022467429 | G19: =N(F19)+G12*Assumptions!$D$17/4 -> 0.0049967429 | H19: =N(G19)+H12*Assumptions!$D$17/4 -> 0.0090567429 | I19: =N(H19)+I12*Assumptions!$D$17/4 -> 0.0145056 | J19: =N(I19)+J12*Assumptions!$D$17/4 -> 0.021422171 | K19: =N(J19)+K12*Assumptions!$D$17/4 -> 0.029439886
A20: 12 | B20: GMV protected by retention | C20: Rs crore | D20: =D19*Assumptions!$D$15*3/100 -> 0.21205714 | E20: =E19*Assumptions!$D$15*3/100 -> 1.0918286 | F20: =F19*Assumptions!$D$15*3/100 -> 3.3701143 | G20: =G19*Assumptions!$D$15*3/100 -> 7.4951143 | H20: =H19*Assumptions!$D$15*3/100 -> 13.585114 | I20: =I19*Assumptions!$D$15*3/100 -> 21.7584 | J20: =J19*Assumptions!$D$15*3/100 -> 32.133257 | K20: =K19*Assumptions!$D$15*3/100 -> 44.159829 | L20: =SUM(D20:K20) -> 123.80571
A21: 13 | B21: Incremental GMV | C21: Rs crore | D21: =D14+D17+D18+D20 -> 3.1808571 | E21: =E14+E17+E18+E20 -> 13.63765 | F21: =F14+F17+F18+F20 -> 36.35368 | G21: =G14+G17+G18+G20 -> 68.358203 | H21: =H14+H17+H18+H20 -> 105.16797 | I21: =I14+I17+I18+I20 -> 146.55531 | J21: =J14+J17+J18+J20 -> 192.43095 | K21: =K14+K17+K18+K20 -> 232.76649 | L21: =SUM(D21:K21) -> 798.45111
A22: 14 | B22: Incremental GMV | C22: Rs lakh crore | D22: =D21/100000 -> 3.1808571e-05 | E22: =E21/100000 -> 0.0001363765 | F22: =F21/100000 -> 0.0003635368 | G22: =G21/100000 -> 0.00068358203 | H22: =H21/100000 -> 0.0010516797 | I22: =I21/100000 -> 0.0014655531 | J22: =J21/100000 -> 0.0019243095 | K22: =K21/100000 -> 0.0023276649 | L22: =SUM(D22:K22) -> 0.0079845111
A23: 15 | B23: Baseline Paytm merchant GMV | C23: Rs lakh crore | D23: =Baseline!E15 -> 7.9486905 | E23: =Baseline!E16 -> 8.2971429 | F23: =Baseline!E17 -> 8.6455952 | G23: =Baseline!E18 -> 8.9940476 | H23: =Baseline!E19 -> 9.3425 | I23: =Baseline!E20 -> 9.6909524 | J23: =Baseline!E21 -> 10.039405 | K23: =Baseline!E22 -> 10.387857 | L23: =SUM(D23:K23) -> 73.34619
A24: 16 | B24: Paytm merchant GMV with bundle | C24: Rs lakh crore | D24: =D23+D22 -> 7.9487223 | E24: =E23+E22 -> 8.2972792 | F24: =F23+F22 -> 8.6459588 | G24: =G23+G22 -> 8.9947312 | H24: =H23+H22 -> 9.3435517 | I24: =I23+I22 -> 9.6924179 | J24: =J23+J22 -> 10.041329 | K24: =K23+K22 -> 10.390185 | L24: =SUM(D24:K24) -> 73.354175
A25: 17 | B25: Uplift vs baseline GMV | C25: % | D25: =IF(D23>0,D22/D23,0) -> 4.0017373e-06 | E25: =IF(E23>0,E22/E23,0) -> 1.6436562e-05 | F25: =IF(F23>0,F22/F23,0) -> 4.2048788e-05 | G25: =IF(G23>0,G22/G23,0) -> 7.6003825e-05 | H25: =IF(H23>0,H22/H23,0) -> 0.00011256941 | I25: =IF(I23>0,I22/I23,0) -> 0.00015122901 | J25: =IF(J23>0,J22/J23,0) -> 0.00019167566 | K25: =IF(K23>0,K22/K23,0) -> 0.00022407556
A26: 18 | B26: North Star: Paytm GMV per participating merchant, without bundle | C26: Rs / quarter | D26: =Assumptions!$D$15*3 -> 150000 | E26: =Assumptions!$D$15*3 -> 150000 | F26: =Assumptions!$D$15*3 -> 150000 | G26: =Assumptions!$D$15*3 -> 150000 | H26: =Assumptions!$D$15*3 -> 150000 | I26: =Assumptions!$D$15*3 -> 150000 | J26: =Assumptions!$D$15*3 -> 150000 | K26: =Assumptions!$D$15*3 -> 150000
A27: 19 | B27: North Star: Paytm GMV per participating merchant, with bundle | C27: Rs / quarter | D27: =IF(D12>0,D26+(D14+D17+D18)*100/D12,D26) -> 155250 | E27: =IF(E12>0,E26+(E14+E17+E18)*100/E12,E26) -> 155347.62 | F27: =IF(F12>0,F26+(F14+F17+F18)*100/F12,F26) -> 155429.01 | G27: =IF(G12>0,G26+(G14+G17+G18)*100/G12,G26) -> 155533.01 | H27: =IF(H12>0,H26+(H14+H17+H18)*100/H12,H26) -> 155639.34 | I27: =IF(I12>0,I26+(I14+I17+I18)*100/I12,I26) -> 155725.83 | J27: =IF(J12>0,J26+(J14+J17+J18)*100/J12,J26) -> 155793.97 | K27: =IF(K12>0,K26+(K14+K17+K18)*100/K12,K26) -> 155880.94
A28: 20 | B28: North Star uplift per participating merchant | C28: % | D28: =IF(D26>0,D27/D26-1,0) -> 0.035 | E28: =IF(E26>0,E27/E26-1,0) -> 0.035650799 | F28: =IF(F26>0,F27/F26-1,0) -> 0.036193404 | G28: =IF(G26>0,G27/G26-1,0) -> 0.03688672 | H28: =IF(H26>0,H27/H26-1,0) -> 0.037595588 | I28: =IF(I26>0,I27/I26-1,0) -> 0.038172198 | J28: =IF(J26>0,J27/J26-1,0) -> 0.038626483 | K28: =IF(K26>0,K27/K26-1,0) -> 0.039206241
A29: 21 | B29: Paytm revenue: Mohalla fees | C29: Rs crore | D29: =D13*Assumptions!$D$20/100 -> 0.025446857 | E29: =E13*Assumptions!$D$20/100 -> 0.10557257 | F29: =F13*Assumptions!$D$20/100 -> 0.27339429 | G29: =G13*Assumptions!$D$20/100 -> 0.495 | H29: =H13*Assumptions!$D$20/100 -> 0.7308 | I29: =I13*Assumptions!$D$20/100 -> 0.98079429 | J29: =J13*Assumptions!$D$20/100 -> 1.2449829 | K29: =K13*Assumptions!$D$20/100 -> 1.4431886 | L29: =SUM(D29:K29) -> 5.2991794
A30: 22 | B30: Paytm revenue: Growth plan (Intent Guard) | C30: Rs crore | D30: =D12*Assumptions!$D$22*Assumptions!$D$21*3/100 -> 0.0024598629 | E30: =E12*Assumptions!$D$22*Assumptions!$D$21*3/100 -> 0.010205349 | F30: =F12*Assumptions!$D$22*Assumptions!$D$21*3/100 -> 0.026428114 | G30: =G12*Assumptions!$D$22*Assumptions!$D$21*3/100 -> 0.04785 | H30: =H12*Assumptions!$D$22*Assumptions!$D$21*3/100 -> 0.070644 | I30: =I12*Assumptions!$D$22*Assumptions!$D$21*3/100 -> 0.094810114 | J30: =J12*Assumptions!$D$22*Assumptions!$D$21*3/100 -> 0.12034834 | K30: =K12*Assumptions!$D$22*Assumptions!$D$21*3/100 -> 0.13950823 | L30: =SUM(D30:K30) -> 0.51225401
A31: 23 | B31: Paytm revenue: payment margin on incremental GMV | C31: Rs crore | D31: =D21*Assumptions!$D$23 -> 0.0012723429 | E31: =E21*Assumptions!$D$23 -> 0.0054550601 | F31: =F21*Assumptions!$D$23 -> 0.014541472 | G31: =G21*Assumptions!$D$23 -> 0.027343281 | H31: =H21*Assumptions!$D$23 -> 0.042067187 | I31: =I21*Assumptions!$D$23 -> 0.058622125 | J31: =J21*Assumptions!$D$23 -> 0.076972381 | K31: =K21*Assumptions!$D$23 -> 0.093106597 | L31: =SUM(D31:K31) -> 0.31938045
A32: 24 | B32: Paytm revenue: device subscriptions retained | C32: Rs crore | D32: =D19*Assumptions!$D$24*3/100 -> 0.00033929143 | E32: =E19*Assumptions!$D$24*3/100 -> 0.0017469257 | F32: =F19*Assumptions!$D$24*3/100 -> 0.0053921829 | G32: =G19*Assumptions!$D$24*3/100 -> 0.011992183 | H32: =H19*Assumptions!$D$24*3/100 -> 0.021736183 | I32: =I19*Assumptions!$D$24*3/100 -> 0.03481344 | J32: =J19*Assumptions!$D$24*3/100 -> 0.051413211 | K32: =K19*Assumptions!$D$24*3/100 -> 0.070655726 | L32: =SUM(D32:K32) -> 0.19808914
A33: 25 | B33: Total Paytm revenue from the bundle | C33: Rs crore | D33: =SUM(D29:D32) -> 0.029518354 | E33: =SUM(E29:E32) -> 0.12297991 | F33: =SUM(F29:F32) -> 0.31975606 | G33: =SUM(G29:G32) -> 0.58218546 | H33: =SUM(H29:H32) -> 0.86524737 | I33: =SUM(I29:I32) -> 1.16904 | J33: =SUM(J29:J32) -> 1.4937168 | K33: =SUM(K29:K32) -> 1.7464591 | L33: =SUM(D33:K33) -> 6.328903
A34: 26 | B34: Cost: reward payouts | C34: Rs crore | D34: =D13*Assumptions!$D$26/100 -> 0.016964571 | E34: =E13*Assumptions!$D$26/100 -> 0.070381714 | F34: =F13*Assumptions!$D$26/100 -> 0.18226286 | G34: =G13*Assumptions!$D$26/100 -> 0.33 | H34: =H13*Assumptions!$D$26/100 -> 0.4872 | I34: =I13*Assumptions!$D$26/100 -> 0.65386286 | J34: =J13*Assumptions!$D$26/100 -> 0.82998857 | K34: =K13*Assumptions!$D$26/100 -> 0.96212571 | L34: =SUM(D34:K34) -> 3.5327863
A35: 27 | B35: Cost: AI inference | C35: Rs crore | D35: =D12*Assumptions!$D$27*3/100+D12*Assumptions!$D$22*Assumptions!$D$28*3/100 -> 0.027567429 | E35: =E12*Assumptions!$D$27*3/100+E12*Assumptions!$D$22*Assumptions!$D$28*3/100 -> 0.11437029 | F35: =F12*Assumptions!$D$27*3/100+F12*Assumptions!$D$22*Assumptions!$D$28*3/100 -> 0.29617714 | G35: =G12*Assumptions!$D$27*3/100+G12*Assumptions!$D$22*Assumptions!$D$28*3/100 -> 0.53625 | H35: =H12*Assumptions!$D$27*3/100+H12*Assumptions!$D$22*Assumptions!$D$28*3/100 -> 0.7917 | I35: =I12*Assumptions!$D$27*3/100+I12*Assumptions!$D$22*Assumptions!$D$28*3/100 -> 1.0625271 | J35: =J12*Assumptions!$D$27*3/100+J12*Assumptions!$D$22*Assumptions!$D$28*3/100 -> 1.3487314 | K35: =K12*Assumptions!$D$27*3/100+K12*Assumptions!$D$22*Assumptions!$D$28*3/100 -> 1.5634543 | L35: =SUM(D35:K35) -> 5.7407777
A36: 28 | B36: Total cost | C36: Rs crore | D36: =D34+D35 -> 0.044532 | E36: =E34+E35 -> 0.184752 | F36: =F34+F35 -> 0.47844 | G36: =G34+G35 -> 0.86625 | H36: =H34+H35 -> 1.2789 | I36: =I34+I35 -> 1.71639 | J36: =J34+J35 -> 2.17872 | K36: =K34+K35 -> 2.52558 | L36: =SUM(D36:K36) -> 9.273564
A37: 29 | B37: Contribution to Paytm | C37: Rs crore | D37: =D33-D36 -> -0.015013646 | E37: =E33-E36 -> -0.061772094 | F37: =F33-F36 -> -0.15868394 | G37: =G33-G36 -> -0.28406454 | H37: =H33-H36 -> -0.41365263 | I37: =I33-I36 -> -0.54735004 | J37: =J33-J36 -> -0.68500321 | K37: =K33-K36 -> -0.77912088 | L37: =SUM(D37:K37) -> -2.944661
A38: 30 | B38: Merchant reward spend (merchant-funded) | C38: Rs crore | D38: =D13*Assumptions!$D$19/100 -> 0.21205714 | E38: =E13*Assumptions!$D$19/100 -> 0.87977143 | F38: =F13*Assumptions!$D$19/100 -> 2.2782857 | G38: =G13*Assumptions!$D$19/100 -> 4.125 | H38: =H13*Assumptions!$D$19/100 -> 6.09 | I38: =I13*Assumptions!$D$19/100 -> 8.1732857 | J38: =J13*Assumptions!$D$19/100 -> 10.374857 | K38: =K13*Assumptions!$D$19/100 -> 12.026571 | L38: =SUM(D38:K38) -> 44.159829
A39: 31 | B39: Merchant reward spend protected by Intent Guard | C39: Rs crore | D39: =D38*Assumptions!$D$29 -> 0.0042411429 | E39: =E38*Assumptions!$D$29 -> 0.017595429 | F39: =F38*Assumptions!$D$29 -> 0.045565714 | G39: =G38*Assumptions!$D$29 -> 0.0825 | H39: =H38*Assumptions!$D$29 -> 0.1218 | I39: =I38*Assumptions!$D$29 -> 0.16346571 | J39: =J38*Assumptions!$D$29 -> 0.20749714 | K39: =K38*Assumptions!$D$29 -> 0.24053143 | L39: =SUM(D39:K39) -> 0.88319657
A40: 32 | B40: Mohalla fees vs Paytm's Q1 FY27 Marketing Services revenue | C40: % | D40: =D29/Baseline!$F$30 -> 0.00010647221 | E40: =E29/Baseline!$F$30 -> 0.00044172624 | F40: =F29/Baseline!$F$30 -> 0.0011439091 | G40: =G29/Baseline!$F$30 -> 0.0020711297 | H40: =H29/Baseline!$F$30 -> 0.0030577406 | I40: =I29/Baseline!$F$30 -> 0.0041037418 | J40: =J29/Baseline!$F$30 -> 0.0052091333 | K40: =K29/Baseline!$F$30 -> 0.0060384459
A41: 33 | B41: Unit economics: Paytm contribution per participating merchant per month | C41: Rs / month | D41: =Assumptions!$D$9*(Assumptions!$D$20-Assumptions!$D$26)+Assumptions!$D$22*(Assumptions!$D$21-Assumptions!$D$28)-Assumptions!$D$27 -> -9.8 | E41: =Assumptions!$D$9*(Assumptions!$D$20-Assumptions!$D$26)+Assumptions!$D$22*(Assumptions!$D$21-Assumptions!$D$28)-Assumptions!$D$27 -> -9.8 | F41: =Assumptions!$D$9*(Assumptions!$D$20-Assumptions!$D$26)+Assumptions!$D$22*(Assumptions!$D$21-Assumptions!$D$28)-Assumptions!$D$27 -> -9.8 | G41: =Assumptions!$D$9*(Assumptions!$D$20-Assumptions!$D$26)+Assumptions!$D$22*(Assumptions!$D$21-Assumptions!$D$28)-Assumptions!$D$27 -> -9.8 | H41: =Assumptions!$D$9*(Assumptions!$D$20-Assumptions!$D$26)+Assumptions!$D$22*(Assumptions!$D$21-Assumptions!$D$28)-Assumptions!$D$27 -> -9.8 | I41: =Assumptions!$D$9*(Assumptions!$D$20-Assumptions!$D$26)+Assumptions!$D$22*(Assumptions!$D$21-Assumptions!$D$28)-Assumptions!$D$27 -> -9.8 | J41: =Assumptions!$D$9*(Assumptions!$D$20-Assumptions!$D$26)+Assumptions!$D$22*(Assumptions!$D$21-Assumptions!$D$28)-Assumptions!$D$27 -> -9.8 | K41: =Assumptions!$D$9*(Assumptions!$D$20-Assumptions!$D$26)+Assumptions!$D$22*(Assumptions!$D$21-Assumptions!$D$28)-Assumptions!$D$27 -> -9.8
A42: 34 | B42: Break-even new customers per merchant per month | C42: customers / month | D42: =IF(Assumptions!$D$20-Assumptions!$D$26>0,MAX(0,(Assumptions!$D$27-Assumptions!$D$22*(Assumptions!$D$21-Assumptions!$D$28))/(Assumptions!$D$20-Assumptions!$D$26)),0) -> 14.8 | E42: =IF(Assumptions!$D$20-Assumptions!$D$26>0,MAX(0,(Assumptions!$D$27-Assumptions!$D$22*(Assumptions!$D$21-Assumptions!$D$28))/(Assumptions!$D$20-Assumptions!$D$26)),0) -> 14.8 | F42: =IF(Assumptions!$D$20-Assumptions!$D$26>0,MAX(0,(Assumptions!$D$27-Assumptions!$D$22*(Assumptions!$D$21-Assumptions!$D$28))/(Assumptions!$D$20-Assumptions!$D$26)),0) -> 14.8 | G42: =IF(Assumptions!$D$20-Assumptions!$D$26>0,MAX(0,(Assumptions!$D$27-Assumptions!$D$22*(Assumptions!$D$21-Assumptions!$D$28))/(Assumptions!$D$20-Assumptions!$D$26)),0) -> 14.8 | H42: =IF(Assumptions!$D$20-Assumptions!$D$26>0,MAX(0,(Assumptions!$D$27-Assumptions!$D$22*(Assumptions!$D$21-Assumptions!$D$28))/(Assumptions!$D$20-Assumptions!$D$26)),0) -> 14.8 | I42: =IF(Assumptions!$D$20-Assumptions!$D$26>0,MAX(0,(Assumptions!$D$27-Assumptions!$D$22*(Assumptions!$D$21-Assumptions!$D$28))/(Assumptions!$D$20-Assumptions!$D$26)),0) -> 14.8 | J42: =IF(Assumptions!$D$20-Assumptions!$D$26>0,MAX(0,(Assumptions!$D$27-Assumptions!$D$22*(Assumptions!$D$21-Assumptions!$D$28))/(Assumptions!$D$20-Assumptions!$D$26)),0) -> 14.8 | K42: =IF(Assumptions!$D$20-Assumptions!$D$26>0,MAX(0,(Assumptions!$D$27-Assumptions!$D$22*(Assumptions!$D$21-Assumptions!$D$28))/(Assumptions!$D$20-Assumptions!$D$26)),0) -> 14.8
A43: 35 | B43: Merchant cost per new customer (reward + fee) | C43: Rs | D43: =Assumptions!$D$19+Assumptions!$D$20 -> 28 | E43: =Assumptions!$D$19+Assumptions!$D$20 -> 28 | F43: =Assumptions!$D$19+Assumptions!$D$20 -> 28 | G43: =Assumptions!$D$19+Assumptions!$D$20 -> 28 | H43: =Assumptions!$D$19+Assumptions!$D$20 -> 28 | I43: =Assumptions!$D$19+Assumptions!$D$20 -> 28 | J43: =Assumptions!$D$19+Assumptions!$D$20 -> 28 | K43: =Assumptions!$D$19+Assumptions!$D$20 -> 28
A44: 36 | B44: Merchant cost per new customer as % of first bill | C44: % | D44: =(Assumptions!$D$19+Assumptions!$D$20)/Assumptions!$D$10 -> 0.112 | E44: =(Assumptions!$D$19+Assumptions!$D$20)/Assumptions!$D$10 -> 0.112 | F44: =(Assumptions!$D$19+Assumptions!$D$20)/Assumptions!$D$10 -> 0.112 | G44: =(Assumptions!$D$19+Assumptions!$D$20)/Assumptions!$D$10 -> 0.112 | H44: =(Assumptions!$D$19+Assumptions!$D$20)/Assumptions!$D$10 -> 0.112 | I44: =(Assumptions!$D$19+Assumptions!$D$20)/Assumptions!$D$10 -> 0.112 | J44: =(Assumptions!$D$19+Assumptions!$D$20)/Assumptions!$D$10 -> 0.112 | K44: =(Assumptions!$D$19+Assumptions!$D$20)/Assumptions!$D$10 -> 0.112
A48: BASE scenario (Assumptions column E)
A49: 1 | B49: Device merchants, baseline | C49: lakh | D49: =Baseline!H15*100 -> 176.71429 | E49: =Baseline!H16*100 -> 183.28571 | F49: =Baseline!H17*100 -> 189.85714 | G49: =Baseline!H18*100 -> 196.42857 | H49: =Baseline!H19*100 -> 203 | I49: =Baseline!H20*100 -> 209.57143 | J49: =Baseline!H21*100 -> 216.14286 | K49: =Baseline!H22*100 -> 222.71429
A50: 2 | B50: Eligible merchants (dense clusters) | C50: lakh | D50: =D49*Assumptions!$E$6 -> 53.014286 | E50: =E49*Assumptions!$E$6 -> 54.985714 | F50: =F49*Assumptions!$E$6 -> 56.957143 | G50: =G49*Assumptions!$E$6 -> 58.928571 | H50: =H49*Assumptions!$E$6 -> 60.9 | I50: =I49*Assumptions!$E$6 -> 62.871429 | J50: =J49*Assumptions!$E$6 -> 64.842857 | K50: =K49*Assumptions!$E$6 -> 66.814286
A51: 3 | B51: Rollout coverage | C51: % of eligible | D51: =Assumptions!D$33 -> 0.02 | E51: =Assumptions!E$33 -> 0.08 | F51: =Assumptions!F$33 -> 0.2 | G51: =Assumptions!G$33 -> 0.35 | H51: =Assumptions!H$33 -> 0.5 | I51: =Assumptions!I$33 -> 0.65 | J51: =Assumptions!J$33 -> 0.8 | K51: =Assumptions!K$33 -> 0.9
A52: 4 | B52: Participating merchants | C52: lakh | D52: =D50*D51*Assumptions!$E$7 -> 0.15904286 | E52: =E50*E51*Assumptions!$E$7 -> 0.65982857 | F52: =F50*F51*Assumptions!$E$7 -> 1.7087143 | G52: =G50*G51*Assumptions!$E$7 -> 3.09375 | H52: =H50*H51*Assumptions!$E$7 -> 4.5675 | I52: =I50*I51*Assumptions!$E$7 -> 6.1299643 | J52: =J50*J51*Assumptions!$E$7 -> 7.7811429 | K52: =K50*K51*Assumptions!$E$7 -> 9.0199286
A53: 5 | B53: New customers acquired (= redemptions) | C53: lakh | D53: =D52*Assumptions!$E$9*3 -> 4.7712857 | E53: =E52*Assumptions!$E$9*3 -> 19.794857 | F53: =F52*Assumptions!$E$9*3 -> 51.261429 | G53: =G52*Assumptions!$E$9*3 -> 92.8125 | H53: =H52*Assumptions!$E$9*3 -> 137.025 | I53: =I52*Assumptions!$E$9*3 -> 183.89893 | J53: =J52*Assumptions!$E$9*3 -> 233.43429 | K53: =K52*Assumptions!$E$9*3 -> 270.59786 | L53: =SUM(D53:K53) -> 993.59614
A54: 6 | B54: GMV: first visits | C54: Rs crore | D54: =D53*Assumptions!$E$10/100 -> 14.313857 | E54: =E53*Assumptions!$E$10/100 -> 59.384571 | F54: =F53*Assumptions!$E$10/100 -> 153.78429 | G54: =G53*Assumptions!$E$10/100 -> 278.4375 | H54: =H53*Assumptions!$E$10/100 -> 411.075 | I54: =I53*Assumptions!$E$10/100 -> 551.69679 | J54: =J53*Assumptions!$E$10/100 -> 700.30286 | K54: =K53*Assumptions!$E$10/100 -> 811.79357 | L54: =SUM(D54:K54) -> 2980.7884
A55: 7 | B55: New regulars | C55: lakh | D55: =D53*Assumptions!$E$11 -> 0.95425714 | E55: =E53*Assumptions!$E$11 -> 3.9589714 | F55: =F53*Assumptions!$E$11 -> 10.252286 | G55: =G53*Assumptions!$E$11 -> 18.5625 | H55: =H53*Assumptions!$E$11 -> 27.405 | I55: =I53*Assumptions!$E$11 -> 36.779786 | J55: =J53*Assumptions!$E$11 -> 46.686857 | K55: =K53*Assumptions!$E$11 -> 54.119571 | L55: =SUM(D55:K55) -> 198.71923
A56: 8 | B56: Regulars at quarter end | C56: lakh | D56: =N(C56)*(1-Assumptions!$E$12)+D55 -> 0.95425714 | E56: =N(D56)*(1-Assumptions!$E$12)+E55 -> 4.6269514 | F56: =N(E56)*(1-Assumptions!$E$12)+F55 -> 13.491152 | G56: =N(F56)*(1-Assumptions!$E$12)+G55 -> 28.006306 | H56: =N(G56)*(1-Assumptions!$E$12)+H55 -> 47.009414 | I56: =N(H56)*(1-Assumptions!$E$12)+I55 -> 69.686376 | J56: =N(I56)*(1-Assumptions!$E$12)+J55 -> 95.46732 | K56: =N(J56)*(1-Assumptions!$E$12)+K55 -> 120.9467
A57: 9 | B57: GMV: repeat visits by regulars | C57: Rs crore | D57: =N(C56)*(1-Assumptions!$E$12)*Assumptions!$E$13/100 -> 0 | E57: =N(D56)*(1-Assumptions!$E$12)*Assumptions!$E$13/100 -> 4.00788 | F57: =N(E56)*(1-Assumptions!$E$12)*Assumptions!$E$13/100 -> 19.433196 | G57: =N(F56)*(1-Assumptions!$E$12)*Assumptions!$E$13/100 -> 56.662837 | H57: =N(G56)*(1-Assumptions!$E$12)*Assumptions!$E$13/100 -> 117.62649 | I57: =N(H56)*(1-Assumptions!$E$12)*Assumptions!$E$13/100 -> 197.43954 | J57: =N(I56)*(1-Assumptions!$E$12)*Assumptions!$E$13/100 -> 292.68278 | K57: =N(J56)*(1-Assumptions!$E$12)*Assumptions!$E$13/100 -> 400.96274 | L57: =SUM(D57:K57) -> 1088.8155
A58: 10 | B58: GMV: share-of-counter shift to Paytm | C58: Rs crore | D58: =D52*Assumptions!$E$15*3*Assumptions!$E$16/100 -> 11.451086 | E58: =E52*Assumptions!$E$15*3*Assumptions!$E$16/100 -> 47.507657 | F58: =F52*Assumptions!$E$15*3*Assumptions!$E$16/100 -> 123.02743 | G58: =G52*Assumptions!$E$15*3*Assumptions!$E$16/100 -> 222.75 | H58: =H52*Assumptions!$E$15*3*Assumptions!$E$16/100 -> 328.86 | I58: =I52*Assumptions!$E$15*3*Assumptions!$E$16/100 -> 441.35743 | J58: =J52*Assumptions!$E$15*3*Assumptions!$E$16/100 -> 560.24229 | K58: =K52*Assumptions!$E$15*3*Assumptions!$E$16/100 -> 649.43486 | L58: =SUM(D58:K58) -> 2384.6307
A59: 11 | B59: Merchants retained by lower churn (cumulative) | C59: lakh | D59: =N(C59)+D52*Assumptions!$E$17/4 -> 0.00079521429 | E59: =N(D59)+E52*Assumptions!$E$17/4 -> 0.0040943571 | F59: =N(E59)+F52*Assumptions!$E$17/4 -> 0.012637929 | G59: =N(F59)+G52*Assumptions!$E$17/4 -> 0.028106679 | H59: =N(G59)+H52*Assumptions!$E$17/4 -> 0.050944179 | I59: =N(H59)+I52*Assumptions!$E$17/4 -> 0.081594 | J59: =N(I59)+J52*Assumptions!$E$17/4 -> 0.12049971 | K59: =N(J59)+K52*Assumptions!$E$17/4 -> 0.16559936
A60: 12 | B60: GMV protected by retention | C60: Rs crore | D60: =D59*Assumptions!$E$15*3/100 -> 1.9085143 | E60: =E59*Assumptions!$E$15*3/100 -> 9.8264571 | F60: =F59*Assumptions!$E$15*3/100 -> 30.331029 | G60: =G59*Assumptions!$E$15*3/100 -> 67.456029 | H60: =H59*Assumptions!$E$15*3/100 -> 122.26603 | I60: =I59*Assumptions!$E$15*3/100 -> 195.8256 | J60: =J59*Assumptions!$E$15*3/100 -> 289.19931 | K60: =K59*Assumptions!$E$15*3/100 -> 397.43846 | L60: =SUM(D60:K60) -> 1114.2514
A61: 13 | B61: Incremental GMV | C61: Rs crore | D61: =D54+D57+D58+D60 -> 27.673457 | E61: =E54+E57+E58+E60 -> 120.72657 | F61: =F54+F57+F58+F60 -> 326.57594 | G61: =G54+G57+G58+G60 -> 625.30637 | H61: =H54+H57+H58+H60 -> 979.82751 | I61: =I54+I57+I58+I60 -> 1386.3194 | J61: =J54+J57+J58+J60 -> 1842.4272 | K61: =K54+K57+K58+K60 -> 2259.6296 | L61: =SUM(D61:K61) -> 7568.4861
A62: 14 | B62: Incremental GMV | C62: Rs lakh crore | D62: =D61/100000 -> 0.00027673457 | E62: =E61/100000 -> 0.0012072657 | F62: =F61/100000 -> 0.0032657594 | G62: =G61/100000 -> 0.0062530637 | H62: =H61/100000 -> 0.0097982751 | I62: =I61/100000 -> 0.013863194 | J62: =J61/100000 -> 0.018424272 | K62: =K61/100000 -> 0.022596296 | L62: =SUM(D62:K62) -> 0.075684861
A63: 15 | B63: Baseline Paytm merchant GMV | C63: Rs lakh crore | D63: =Baseline!E15 -> 7.9486905 | E63: =Baseline!E16 -> 8.2971429 | F63: =Baseline!E17 -> 8.6455952 | G63: =Baseline!E18 -> 8.9940476 | H63: =Baseline!E19 -> 9.3425 | I63: =Baseline!E20 -> 9.6909524 | J63: =Baseline!E21 -> 10.039405 | K63: =Baseline!E22 -> 10.387857 | L63: =SUM(D63:K63) -> 73.34619
A64: 16 | B64: Paytm merchant GMV with bundle | C64: Rs lakh crore | D64: =D63+D62 -> 7.9489672 | E64: =E63+E62 -> 8.2983501 | F64: =F63+F62 -> 8.648861 | G64: =G63+G62 -> 9.0003007 | H64: =H63+H62 -> 9.3522983 | I64: =I63+I62 -> 9.7048156 | J64: =J63+J62 -> 10.057829 | K64: =K63+K62 -> 10.410453 | L64: =SUM(D64:K64) -> 73.421875
A65: 17 | B65: Uplift vs baseline GMV | C65: % | D65: =IF(D63>0,D62/D63,0) -> 3.4815115e-05 | E65: =IF(E63>0,E62/E63,0) -> 0.00014550378 | F65: =IF(F63>0,F62/F63,0) -> 0.00037773679 | G65: =IF(G63>0,G62/G63,0) -> 0.00069524467 | H65: =IF(H63>0,H62/H63,0) -> 0.0010487851 | I65: =IF(I63>0,I62/I63,0) -> 0.0014305295 | J65: =IF(J63>0,J62/J63,0) -> 0.0018351957 | K65: =IF(K63>0,K62/K63,0) -> 0.0021752606
A66: 18 | B66: North Star: Paytm GMV per participating merchant, without bundle | C66: Rs / quarter | D66: =Assumptions!$E$15*3 -> 240000 | E66: =Assumptions!$E$15*3 -> 240000 | F66: =Assumptions!$E$15*3 -> 240000 | G66: =Assumptions!$E$15*3 -> 240000 | H66: =Assumptions!$E$15*3 -> 240000 | I66: =Assumptions!$E$15*3 -> 240000 | J66: =Assumptions!$E$15*3 -> 240000 | K66: =Assumptions!$E$15*3 -> 240000
A67: 19 | B67: North Star: Paytm GMV per participating merchant, with bundle | C67: Rs / quarter | D67: =IF(D52>0,D66+(D54+D57+D58)*100/D52,D66) -> 256200 | E67: =IF(E52>0,E66+(E54+E57+E58)*100/E52,E66) -> 256807.41 | F67: =IF(F52>0,F66+(F54+F57+F58)*100/F52,F66) -> 257337.3 | G67: =IF(G52>0,G66+(G54+G57+G58)*100/G52,G66) -> 258031.53 | H67: =IF(H52>0,H66+(H54+H57+H58)*100/H52,H66) -> 258775.29 | I67: =IF(I52>0,I66+(I54+I57+I58)*100/I52,I66) -> 259420.89 | J67: =IF(J52>0,J66+(J54+J57+J58)*100/J52,J66) -> 259961.44 | K67: =IF(K52>0,K66+(K54+K57+K58)*100/K52,K66) -> 260645.3
A68: 20 | B68: North Star uplift per participating merchant | C68: % | D68: =IF(D66>0,D67/D66-1,0) -> 0.0675 | E68: =IF(E66>0,E67/E66-1,0) -> 0.070030885 | F68: =IF(F66>0,F67/F66-1,0) -> 0.072238747 | G68: =IF(G66>0,G67/G66-1,0) -> 0.075131359 | H68: =IF(H66>0,H67/H66-1,0) -> 0.078230386 | I68: =IF(I66>0,I67/I66-1,0) -> 0.080920384 | J68: =IF(J66>0,J67/J66-1,0) -> 0.083172654 | K68: =IF(K66>0,K67/K66-1,0) -> 0.086022077
A69: 21 | B69: Paytm revenue: Mohalla fees | C69: Rs crore | D69: =D53*Assumptions!$E$20/100 -> 0.19085143 | E69: =E53*Assumptions!$E$20/100 -> 0.79179429 | F69: =F53*Assumptions!$E$20/100 -> 2.0504571 | G69: =G53*Assumptions!$E$20/100 -> 3.7125 | H69: =H53*Assumptions!$E$20/100 -> 5.481 | I69: =I53*Assumptions!$E$20/100 -> 7.3559571 | J69: =J53*Assumptions!$E$20/100 -> 9.3373714 | K69: =K53*Assumptions!$E$20/100 -> 10.823914 | L69: =SUM(D69:K69) -> 39.743846
A70: 22 | B70: Paytm revenue: Growth plan (Intent Guard) | C70: Rs crore | D70: =D52*Assumptions!$E$22*Assumptions!$E$21*3/100 -> 0.0233793 | E70: =E52*Assumptions!$E$22*Assumptions!$E$21*3/100 -> 0.0969948 | F70: =F52*Assumptions!$E$22*Assumptions!$E$21*3/100 -> 0.251181 | G70: =G52*Assumptions!$E$22*Assumptions!$E$21*3/100 -> 0.45478125 | H70: =H52*Assumptions!$E$22*Assumptions!$E$21*3/100 -> 0.6714225 | I70: =I52*Assumptions!$E$22*Assumptions!$E$21*3/100 -> 0.90110475 | J70: =J52*Assumptions!$E$22*Assumptions!$E$21*3/100 -> 1.143828 | K70: =K52*Assumptions!$E$22*Assumptions!$E$21*3/100 -> 1.3259295 | L70: =SUM(D70:K70) -> 4.8686211
A71: 23 | B71: Paytm revenue: payment margin on incremental GMV | C71: Rs crore | D71: =D61*Assumptions!$E$23 -> 0.011069383 | E71: =E61*Assumptions!$E$23 -> 0.048290626 | F71: =F61*Assumptions!$E$23 -> 0.13063038 | G71: =G61*Assumptions!$E$23 -> 0.25012255 | H71: =H61*Assumptions!$E$23 -> 0.39193101 | I71: =I61*Assumptions!$E$23 -> 0.55452774 | J71: =J61*Assumptions!$E$23 -> 0.73697089 | K71: =K61*Assumptions!$E$23 -> 0.90385185 | L71: =SUM(D71:K71) -> 3.0273944
A72: 24 | B72: Paytm revenue: device subscriptions retained | C72: Rs crore | D72: =D59*Assumptions!$E$24*3/100 -> 0.0021470786 | E72: =E59*Assumptions!$E$24*3/100 -> 0.011054764 | F72: =F59*Assumptions!$E$24*3/100 -> 0.034122407 | G72: =G59*Assumptions!$E$24*3/100 -> 0.075888032 | H72: =H59*Assumptions!$E$24*3/100 -> 0.13754928 | I72: =I59*Assumptions!$E$24*3/100 -> 0.2203038 | J72: =J59*Assumptions!$E$24*3/100 -> 0.32534923 | K72: =K59*Assumptions!$E$24*3/100 -> 0.44711826 | L72: =SUM(D72:K72) -> 1.2535329
A73: 25 | B73: Total Paytm revenue from the bundle | C73: Rs crore | D73: =SUM(D69:D72) -> 0.22744719 | E73: =SUM(E69:E72) -> 0.94813448 | F73: =SUM(F69:F72) -> 2.4663909 | G73: =SUM(G69:G72) -> 4.4932918 | H73: =SUM(H69:H72) -> 6.6819028 | I73: =SUM(I69:I72) -> 9.0318934 | J73: =SUM(J69:J72) -> 11.54352 | K73: =SUM(K69:K72) -> 13.500814 | L73: =SUM(D73:K73) -> 48.893394
A74: 26 | B74: Cost: reward payouts | C74: Rs crore | D74: =D53*Assumptions!$E$26/100 -> 0.047712857 | E74: =E53*Assumptions!$E$26/100 -> 0.19794857 | F74: =F53*Assumptions!$E$26/100 -> 0.51261429 | G74: =G53*Assumptions!$E$26/100 -> 0.928125 | H74: =H53*Assumptions!$E$26/100 -> 1.37025 | I74: =I53*Assumptions!$E$26/100 -> 1.8389893 | J74: =J53*Assumptions!$E$26/100 -> 2.3343429 | K74: =K53*Assumptions!$E$26/100 -> 2.7059786 | L74: =SUM(D74:K74) -> 9.9359614
A75: 27 | B75: Cost: AI inference | C75: Rs crore | D75: =D52*Assumptions!$E$27*3/100+D52*Assumptions!$E$22*Assumptions!$E$28*3/100 -> 0.045327214 | E75: =E52*Assumptions!$E$27*3/100+E52*Assumptions!$E$22*Assumptions!$E$28*3/100 -> 0.18805114 | F75: =F52*Assumptions!$E$27*3/100+F52*Assumptions!$E$22*Assumptions!$E$28*3/100 -> 0.48698357 | G75: =G52*Assumptions!$E$27*3/100+G52*Assumptions!$E$22*Assumptions!$E$28*3/100 -> 0.88171875 | H75: =H52*Assumptions!$E$27*3/100+H52*Assumptions!$E$22*Assumptions!$E$28*3/100 -> 1.3017375 | I75: =I52*Assumptions!$E$27*3/100+I52*Assumptions!$E$22*Assumptions!$E$28*3/100 -> 1.7470398 | J75: =J52*Assumptions!$E$27*3/100+J52*Assumptions!$E$22*Assumptions!$E$28*3/100 -> 2.2176257 | K75: =K52*Assumptions!$E$27*3/100+K52*Assumptions!$E$22*Assumptions!$E$28*3/100 -> 2.5706796 | L75: =SUM(D75:K75) -> 9.4391634
A76: 28 | B76: Total cost | C76: Rs crore | D76: =D74+D75 -> 0.093040071 | E76: =E74+E75 -> 0.38599971 | F76: =F74+F75 -> 0.99959786 | G76: =G74+G75 -> 1.8098437 | H76: =H74+H75 -> 2.6719875 | I76: =I74+I75 -> 3.5860291 | J76: =J74+J75 -> 4.5519686 | K76: =K74+K75 -> 5.2766582 | L76: =SUM(D76:K76) -> 19.375125
A77: 29 | B77: Contribution to Paytm | C77: Rs crore | D77: =D73-D76 -> 0.13440712 | E77: =E73-E76 -> 0.56213476 | F77: =F73-F76 -> 1.4667931 | G77: =G73-G76 -> 2.6834481 | H77: =H73-H76 -> 4.0099153 | I77: =I73-I76 -> 5.4458643 | J77: =J73-J76 -> 6.991551 | K77: =K73-K76 -> 8.2241557 | L77: =SUM(D77:K77) -> 29.518269
A78: 30 | B78: Merchant reward spend (merchant-funded) | C78: Rs crore | D78: =D53*Assumptions!$E$19/100 -> 1.4313857 | E78: =E53*Assumptions!$E$19/100 -> 5.9384571 | F78: =F53*Assumptions!$E$19/100 -> 15.378429 | G78: =G53*Assumptions!$E$19/100 -> 27.84375 | H78: =H53*Assumptions!$E$19/100 -> 41.1075 | I78: =I53*Assumptions!$E$19/100 -> 55.169679 | J78: =J53*Assumptions!$E$19/100 -> 70.030286 | K78: =K53*Assumptions!$E$19/100 -> 81.179357 | L78: =SUM(D78:K78) -> 298.07884
A79: 31 | B79: Merchant reward spend protected by Intent Guard | C79: Rs crore | D79: =D78*Assumptions!$E$29 -> 0.071569286 | E79: =E78*Assumptions!$E$29 -> 0.29692286 | F79: =F78*Assumptions!$E$29 -> 0.76892143 | G79: =G78*Assumptions!$E$29 -> 1.3921875 | H79: =H78*Assumptions!$E$29 -> 2.055375 | I79: =I78*Assumptions!$E$29 -> 2.7584839 | J79: =J78*Assumptions!$E$29 -> 3.5015143 | K79: =K78*Assumptions!$E$29 -> 4.0589679 | L79: =SUM(D79:K79) -> 14.903942
A80: 32 | B80: Mohalla fees vs Paytm's Q1 FY27 Marketing Services revenue | C80: % | D80: =D69/Baseline!$F$30 -> 0.00079854154 | E80: =E69/Baseline!$F$30 -> 0.0033129468 | F80: =F69/Baseline!$F$30 -> 0.0085793186 | G80: =G69/Baseline!$F$30 -> 0.015533473 | H80: =H69/Baseline!$F$30 -> 0.022933054 | I80: =I69/Baseline!$F$30 -> 0.030778063 | J80: =J69/Baseline!$F$30 -> 0.0390685 | K80: =K69/Baseline!$F$30 -> 0.045288344
A81: 33 | B81: Unit economics: Paytm contribution per participating merchant per month | C81: Rs / month | D81: =Assumptions!$E$9*(Assumptions!$E$20-Assumptions!$E$26)+Assumptions!$E$22*(Assumptions!$E$21-Assumptions!$E$28)-Assumptions!$E$27 -> 25.4 | E81: =Assumptions!$E$9*(Assumptions!$E$20-Assumptions!$E$26)+Assumptions!$E$22*(Assumptions!$E$21-Assumptions!$E$28)-Assumptions!$E$27 -> 25.4 | F81: =Assumptions!$E$9*(Assumptions!$E$20-Assumptions!$E$26)+Assumptions!$E$22*(Assumptions!$E$21-Assumptions!$E$28)-Assumptions!$E$27 -> 25.4 | G81: =Assumptions!$E$9*(Assumptions!$E$20-Assumptions!$E$26)+Assumptions!$E$22*(Assumptions!$E$21-Assumptions!$E$28)-Assumptions!$E$27 -> 25.4 | H81: =Assumptions!$E$9*(Assumptions!$E$20-Assumptions!$E$26)+Assumptions!$E$22*(Assumptions!$E$21-Assumptions!$E$28)-Assumptions!$E$27 -> 25.4 | I81: =Assumptions!$E$9*(Assumptions!$E$20-Assumptions!$E$26)+Assumptions!$E$22*(Assumptions!$E$21-Assumptions!$E$28)-Assumptions!$E$27 -> 25.4 | J81: =Assumptions!$E$9*(Assumptions!$E$20-Assumptions!$E$26)+Assumptions!$E$22*(Assumptions!$E$21-Assumptions!$E$28)-Assumptions!$E$27 -> 25.4 | K81: =Assumptions!$E$9*(Assumptions!$E$20-Assumptions!$E$26)+Assumptions!$E$22*(Assumptions!$E$21-Assumptions!$E$28)-Assumptions!$E$27 -> 25.4
A82: 34 | B82: Break-even new customers per merchant per month | C82: customers / month | D82: =IF(Assumptions!$E$20-Assumptions!$E$26>0,MAX(0,(Assumptions!$E$27-Assumptions!$E$22*(Assumptions!$E$21-Assumptions!$E$28))/(Assumptions!$E$20-Assumptions!$E$26)),0) -> 1.5333333 | E82: =IF(Assumptions!$E$20-Assumptions!$E$26>0,MAX(0,(Assumptions!$E$27-Assumptions!$E$22*(Assumptions!$E$21-Assumptions!$E$28))/(Assumptions!$E$20-Assumptions!$E$26)),0) -> 1.5333333 | F82: =IF(Assumptions!$E$20-Assumptions!$E$26>0,MAX(0,(Assumptions!$E$27-Assumptions!$E$22*(Assumptions!$E$21-Assumptions!$E$28))/(Assumptions!$E$20-Assumptions!$E$26)),0) -> 1.5333333 | G82: =IF(Assumptions!$E$20-Assumptions!$E$26>0,MAX(0,(Assumptions!$E$27-Assumptions!$E$22*(Assumptions!$E$21-Assumptions!$E$28))/(Assumptions!$E$20-Assumptions!$E$26)),0) -> 1.5333333 | H82: =IF(Assumptions!$E$20-Assumptions!$E$26>0,MAX(0,(Assumptions!$E$27-Assumptions!$E$22*(Assumptions!$E$21-Assumptions!$E$28))/(Assumptions!$E$20-Assumptions!$E$26)),0) -> 1.5333333 | I82: =IF(Assumptions!$E$20-Assumptions!$E$26>0,MAX(0,(Assumptions!$E$27-Assumptions!$E$22*(Assumptions!$E$21-Assumptions!$E$28))/(Assumptions!$E$20-Assumptions!$E$26)),0) -> 1.5333333 | J82: =IF(Assumptions!$E$20-Assumptions!$E$26>0,MAX(0,(Assumptions!$E$27-Assumptions!$E$22*(Assumptions!$E$21-Assumptions!$E$28))/(Assumptions!$E$20-Assumptions!$E$26)),0) -> 1.5333333 | K82: =IF(Assumptions!$E$20-Assumptions!$E$26>0,MAX(0,(Assumptions!$E$27-Assumptions!$E$22*(Assumptions!$E$21-Assumptions!$E$28))/(Assumptions!$E$20-Assumptions!$E$26)),0) -> 1.5333333
A83: 35 | B83: Merchant cost per new customer (reward + fee) | C83: Rs | D83: =Assumptions!$E$19+Assumptions!$E$20 -> 34 | E83: =Assumptions!$E$19+Assumptions!$E$20 -> 34 | F83: =Assumptions!$E$19+Assumptions!$E$20 -> 34 | G83: =Assumptions!$E$19+Assumptions!$E$20 -> 34 | H83: =Assumptions!$E$19+Assumptions!$E$20 -> 34 | I83: =Assumptions!$E$19+Assumptions!$E$20 -> 34 | J83: =Assumptions!$E$19+Assumptions!$E$20 -> 34 | K83: =Assumptions!$E$19+Assumptions!$E$20 -> 34
A84: 36 | B84: Merchant cost per new customer as % of first bill | C84: % | D84: =(Assumptions!$E$19+Assumptions!$E$20)/Assumptions!$E$10 -> 0.11333333 | E84: =(Assumptions!$E$19+Assumptions!$E$20)/Assumptions!$E$10 -> 0.11333333 | F84: =(Assumptions!$E$19+Assumptions!$E$20)/Assumptions!$E$10 -> 0.11333333 | G84: =(Assumptions!$E$19+Assumptions!$E$20)/Assumptions!$E$10 -> 0.11333333 | H84: =(Assumptions!$E$19+Assumptions!$E$20)/Assumptions!$E$10 -> 0.11333333 | I84: =(Assumptions!$E$19+Assumptions!$E$20)/Assumptions!$E$10 -> 0.11333333 | J84: =(Assumptions!$E$19+Assumptions!$E$20)/Assumptions!$E$10 -> 0.11333333 | K84: =(Assumptions!$E$19+Assumptions!$E$20)/Assumptions!$E$10 -> 0.11333333
A88: BULL scenario (Assumptions column F)
A89: 1 | B89: Device merchants, baseline | C89: lakh | D89: =Baseline!H15*100 -> 176.71429 | E89: =Baseline!H16*100 -> 183.28571 | F89: =Baseline!H17*100 -> 189.85714 | G89: =Baseline!H18*100 -> 196.42857 | H89: =Baseline!H19*100 -> 203 | I89: =Baseline!H20*100 -> 209.57143 | J89: =Baseline!H21*100 -> 216.14286 | K89: =Baseline!H22*100 -> 222.71429
A90: 2 | B90: Eligible merchants (dense clusters) | C90: lakh | D90: =D89*Assumptions!$F$6 -> 70.685714 | E90: =E89*Assumptions!$F$6 -> 73.314286 | F90: =F89*Assumptions!$F$6 -> 75.942857 | G90: =G89*Assumptions!$F$6 -> 78.571429 | H90: =H89*Assumptions!$F$6 -> 81.2 | I90: =I89*Assumptions!$F$6 -> 83.828571 | J90: =J89*Assumptions!$F$6 -> 86.457143 | K90: =K89*Assumptions!$F$6 -> 89.085714
A91: 3 | B91: Rollout coverage | C91: % of eligible | D91: =Assumptions!D$33 -> 0.02 | E91: =Assumptions!E$33 -> 0.08 | F91: =Assumptions!F$33 -> 0.2 | G91: =Assumptions!G$33 -> 0.35 | H91: =Assumptions!H$33 -> 0.5 | I91: =Assumptions!I$33 -> 0.65 | J91: =Assumptions!J$33 -> 0.8 | K91: =Assumptions!K$33 -> 0.9
A92: 4 | B92: Participating merchants | C92: lakh | D92: =D90*D91*Assumptions!$F$7 -> 0.35342857 | E92: =E90*E91*Assumptions!$F$7 -> 1.4662857 | F92: =F90*F91*Assumptions!$F$7 -> 3.7971429 | G92: =G90*G91*Assumptions!$F$7 -> 6.875 | H92: =H90*H91*Assumptions!$F$7 -> 10.15 | I92: =I90*I91*Assumptions!$F$7 -> 13.622143 | J92: =J90*J91*Assumptions!$F$7 -> 17.291429 | K92: =K90*K91*Assumptions!$F$7 -> 20.044286
A93: 5 | B93: New customers acquired (= redemptions) | C93: lakh | D93: =D92*Assumptions!$F$9*3 -> 15.904286 | E93: =E92*Assumptions!$F$9*3 -> 65.982857 | F93: =F92*Assumptions!$F$9*3 -> 170.87143 | G93: =G92*Assumptions!$F$9*3 -> 309.375 | H93: =H92*Assumptions!$F$9*3 -> 456.75 | I93: =I92*Assumptions!$F$9*3 -> 612.99643 | J93: =J92*Assumptions!$F$9*3 -> 778.11429 | K93: =K92*Assumptions!$F$9*3 -> 901.99286 | L93: =SUM(D93:K93) -> 3311.9871
A94: 6 | B94: GMV: first visits | C94: Rs crore | D94: =D93*Assumptions!$F$10/100 -> 55.665 | E94: =E93*Assumptions!$F$10/100 -> 230.94 | F94: =F93*Assumptions!$F$10/100 -> 598.05 | G94: =G93*Assumptions!$F$10/100 -> 1082.8125 | H94: =H93*Assumptions!$F$10/100 -> 1598.625 | I94: =I93*Assumptions!$F$10/100 -> 2145.4875 | J94: =J93*Assumptions!$F$10/100 -> 2723.4 | K94: =K93*Assumptions!$F$10/100 -> 3156.975 | L94: =SUM(D94:K94) -> 11591.955
A95: 7 | B95: New regulars | C95: lakh | D95: =D93*Assumptions!$F$11 -> 4.7712857 | E95: =E93*Assumptions!$F$11 -> 19.794857 | F95: =F93*Assumptions!$F$11 -> 51.261429 | G95: =G93*Assumptions!$F$11 -> 92.8125 | H95: =H93*Assumptions!$F$11 -> 137.025 | I95: =I93*Assumptions!$F$11 -> 183.89893 | J95: =J93*Assumptions!$F$11 -> 233.43429 | K95: =K93*Assumptions!$F$11 -> 270.59786 | L95: =SUM(D95:K95) -> 993.59614
A96: 8 | B96: Regulars at quarter end | C96: lakh | D96: =N(C96)*(1-Assumptions!$F$12)+D95 -> 4.7712857 | E96: =N(D96)*(1-Assumptions!$F$12)+E95 -> 23.611886 | F96: =N(E96)*(1-Assumptions!$F$12)+F95 -> 70.150937 | G96: =N(F96)*(1-Assumptions!$F$12)+G95 -> 148.93325 | H96: =N(G96)*(1-Assumptions!$F$12)+H95 -> 256.1716 | I96: =N(H96)*(1-Assumptions!$F$12)+I95 -> 388.83621 | J96: =N(I96)*(1-Assumptions!$F$12)+J95 -> 544.50325 | K96: =N(J96)*(1-Assumptions!$F$12)+K95 -> 706.20046
A97: 9 | B97: GMV: repeat visits by regulars | C97: Rs crore | D97: =N(C96)*(1-Assumptions!$F$12)*Assumptions!$F$13/100 -> 0 | E97: =N(D96)*(1-Assumptions!$F$12)*Assumptions!$F$13/100 -> 28.627714 | F97: =N(E96)*(1-Assumptions!$F$12)*Assumptions!$F$13/100 -> 141.67131 | G97: =N(F96)*(1-Assumptions!$F$12)*Assumptions!$F$13/100 -> 420.90562 | H97: =N(G96)*(1-Assumptions!$F$12)*Assumptions!$F$13/100 -> 893.5995 | I97: =N(H96)*(1-Assumptions!$F$12)*Assumptions!$F$13/100 -> 1537.0296 | J97: =N(I96)*(1-Assumptions!$F$12)*Assumptions!$F$13/100 -> 2333.0173 | K97: =N(J96)*(1-Assumptions!$F$12)*Assumptions!$F$13/100 -> 3267.0195 | L97: =SUM(D97:K97) -> 8621.8705
A98: 10 | B98: GMV: share-of-counter shift to Paytm | C98: Rs crore | D98: =D92*Assumptions!$F$15*3*Assumptions!$F$16/100 -> 63.617143 | E98: =E92*Assumptions!$F$15*3*Assumptions!$F$16/100 -> 263.93143 | F98: =F92*Assumptions!$F$15*3*Assumptions!$F$16/100 -> 683.48571 | G98: =G92*Assumptions!$F$15*3*Assumptions!$F$16/100 -> 1237.5 | H98: =H92*Assumptions!$F$15*3*Assumptions!$F$16/100 -> 1827 | I98: =I92*Assumptions!$F$15*3*Assumptions!$F$16/100 -> 2451.9857 | J98: =J92*Assumptions!$F$15*3*Assumptions!$F$16/100 -> 3112.4571 | K98: =K92*Assumptions!$F$15*3*Assumptions!$F$16/100 -> 3607.9714 | L98: =SUM(D98:K98) -> 13247.949
A99: 11 | B99: Merchants retained by lower churn (cumulative) | C99: lakh | D99: =N(C99)+D92*Assumptions!$F$17/4 -> 0.0035342857 | E99: =N(D99)+E92*Assumptions!$F$17/4 -> 0.018197143 | F99: =N(E99)+F92*Assumptions!$F$17/4 -> 0.056168571 | G99: =N(F99)+G92*Assumptions!$F$17/4 -> 0.12491857 | H99: =N(G99)+H92*Assumptions!$F$17/4 -> 0.22641857 | I99: =N(H99)+I92*Assumptions!$F$17/4 -> 0.36264 | J99: =N(I99)+J92*Assumptions!$F$17/4 -> 0.53555429 | K99: =N(J99)+K92*Assumptions!$F$17/4 -> 0.73599714
A100: 12 | B100: GMV protected by retention | C100: Rs crore | D100: =D99*Assumptions!$F$15*3/100 -> 12.723429 | E100: =E99*Assumptions!$F$15*3/100 -> 65.509714 | F100: =F99*Assumptions!$F$15*3/100 -> 202.20686 | G100: =G99*Assumptions!$F$15*3/100 -> 449.70686 | H100: =H99*Assumptions!$F$15*3/100 -> 815.10686 | I100: =I99*Assumptions!$F$15*3/100 -> 1305.504 | J100: =J99*Assumptions!$F$15*3/100 -> 1927.9954 | K100: =K99*Assumptions!$F$15*3/100 -> 2649.5897 | L100: =SUM(D100:K100) -> 7428.3429
A101: 13 | B101: Incremental GMV | C101: Rs crore | D101: =D94+D97+D98+D100 -> 132.00557 | E101: =E94+E97+E98+E100 -> 589.00886 | F101: =F94+F97+F98+F100 -> 1625.4139 | G101: =G94+G97+G98+G100 -> 3190.925 | H101: =H94+H97+H98+H100 -> 5134.3314 | I101: =I94+I97+I98+I100 -> 7440.0068 | J101: =J94+J97+J98+J100 -> 10096.87 | K101: =K94+K97+K98+K100 -> 12681.556 | L101: =SUM(D101:K101) -> 40890.117
A102: 14 | B102: Incremental GMV | C102: Rs lakh crore | D102: =D101/100000 -> 0.0013200557 | E102: =E101/100000 -> 0.0058900886 | F102: =F101/100000 -> 0.016254139 | G102: =G101/100000 -> 0.03190925 | H102: =H101/100000 -> 0.051343314 | I102: =I101/100000 -> 0.074400068 | J102: =J101/100000 -> 0.1009687 | K102: =K101/100000 -> 0.12681556 | L102: =SUM(D102:K102) -> 0.40890117
A103: 15 | B103: Baseline Paytm merchant GMV | C103: Rs lakh crore | D103: =Baseline!E15 -> 7.9486905 | E103: =Baseline!E16 -> 8.2971429 | F103: =Baseline!E17 -> 8.6455952 | G103: =Baseline!E18 -> 8.9940476 | H103: =Baseline!E19 -> 9.3425 | I103: =Baseline!E20 -> 9.6909524 | J103: =Baseline!E21 -> 10.039405 | K103: =Baseline!E22 -> 10.387857 | L103: =SUM(D103:K103) -> 73.34619
A104: 16 | B104: Paytm merchant GMV with bundle | C104: Rs lakh crore | D104: =D103+D102 -> 7.9500105 | E104: =E103+E102 -> 8.3030329 | F104: =F103+F102 -> 8.6618494 | G104: =G103+G102 -> 9.0259569 | H104: =H103+H102 -> 9.3938433 | I104: =I103+I102 -> 9.7653524 | J104: =J103+J102 -> 10.140373 | K104: =K103+K102 -> 10.514673 | L104: =SUM(D104:K104) -> 73.755092
A105: 17 | B105: Uplift vs baseline GMV | C105: % | D105: =IF(D103>0,D102/D103,0) -> 0.0001660721 | E105: =IF(E103>0,E102/E103,0) -> 0.0007098936 | F105: =IF(F103>0,F102/F103,0) -> 0.0018800486 | G105: =IF(G103>0,G102/G103,0) -> 0.0035478186 | H105: =IF(H103>0,H102/H103,0) -> 0.0054956718 | I105: =IF(I103>0,I102/I103,0) -> 0.007677271 | J105: =IF(J103>0,J102/J103,0) -> 0.01005724 | K105: =IF(K103>0,K102/K103,0) -> 0.012208057
A106: 18 | B106: North Star: Paytm GMV per participating merchant, without bundle | C106: Rs / quarter | D106: =Assumptions!$F$15*3 -> 360000 | E106: =Assumptions!$F$15*3 -> 360000 | F106: =Assumptions!$F$15*3 -> 360000 | G106: =Assumptions!$F$15*3 -> 360000 | H106: =Assumptions!$F$15*3 -> 360000 | I106: =Assumptions!$F$15*3 -> 360000 | J106: =Assumptions!$F$15*3 -> 360000 | K106: =Assumptions!$F$15*3 -> 360000
A107: 19 | B107: North Star: Paytm GMV per participating merchant, with bundle | C107: Rs / quarter | D107: =IF(D92>0,D106+(D94+D97+D98)*100/D92,D106) -> 393750 | E107: =IF(E92>0,E106+(E94+E97+E98)*100/E92,E106) -> 395702.4 | F107: =IF(F92>0,F106+(F94+F97+F98)*100/F92,F106) -> 397481 | G107: =IF(G92>0,G106+(G94+G97+G98)*100/G92,G106) -> 399872.26 | H107: =IF(H92>0,H106+(H94+H97+H98)*100/H92,H106) -> 402553.94 | I107: =IF(I92>0,I106+(I94+I97+I98)*100/I92,I106) -> 405033.32 | J107: =IF(J92>0,J106+(J94+J97+J98)*100/J92,J106) -> 407242.33 | K107: =IF(K92>0,K106+(K94+K97+K98)*100/K92,K106) -> 410049.01
A108: 20 | B108: North Star uplift per participating merchant | C108: % | D108: =IF(D106>0,D107/D106-1,0) -> 0.09375 | E108: =IF(E106>0,E107/E106-1,0) -> 0.099173324 | F108: =IF(F106>0,F107/F106-1,0) -> 0.10411388 | G108: =IF(G106>0,G107/G106-1,0) -> 0.11075629 | H108: =IF(H106>0,H107/H106-1,0) -> 0.11820538 | I108: =IF(I106>0,I107/I106-1,0) -> 0.12509255 | J108: =IF(J106>0,J107/J106-1,0) -> 0.1312287 | K108: =IF(K106>0,K107/K106-1,0) -> 0.13902502
...

Sheet Summary
B1: Summary: numbers for the projection slide
B2: All cells link to the Model sheet.
B4: A. Base case, quarter by quarter
B5: Metric | C5: Unit | D5: Q4 FY27 | E5: Q1 FY28 | F5: Q2 FY28 | G5: Q3 FY28 | H5: Q4 FY28 | I5: Q1 FY29 | J5: Q2 FY29 | K5: Q3 FY29 | L5: 8-qtr total
B6: Baseline Paytm merchant GMV (FORECAST) | C6: Rs lakh crore | D6: =Model!D63 -> 7.9486905 | E6: =Model!E63 -> 8.2971429 | F6: =Model!F63 -> 8.6455952 | G6: =Model!G63 -> 8.9940476 | H6: =Model!H63 -> 9.3425 | I6: =Model!I63 -> 9.6909524 | J6: =Model!J63 -> 10.039405 | K6: =Model!K63 -> 10.387857
B7: Incremental GMV from the bundle | C7: Rs crore | D7: =Model!D61 -> 27.673457 | E7: =Model!E61 -> 120.72657 | F7: =Model!F61 -> 326.57594 | G7: =Model!G61 -> 625.30637 | H7: =Model!H61 -> 979.82751 | I7: =Model!I61 -> 1386.3194 | J7: =Model!J61 -> 1842.4272 | K7: =Model!K61 -> 2259.6296 | L7: =Model!L61 -> 7568.4861
B8: of which first visits | C8: Rs crore | D8: =Model!D54 -> 14.313857 | E8: =Model!E54 -> 59.384571 | F8: =Model!F54 -> 153.78429 | G8: =Model!G54 -> 278.4375 | H8: =Model!H54 -> 411.075 | I8: =Model!I54 -> 551.69679 | J8: =Model!J54 -> 700.30286 | K8: =Model!K54 -> 811.79357 | L8: =Model!L54 -> 2980.7884
B9: of which repeat visits | C9: Rs crore | D9: =Model!D57 -> 0 | E9: =Model!E57 -> 4.00788 | F9: =Model!F57 -> 19.433196 | G9: =Model!G57 -> 56.662837 | H9: =Model!H57 -> 117.62649 | I9: =Model!I57 -> 197.43954 | J9: =Model!J57 -> 292.68278 | K9: =Model!K57 -> 400.96274 | L9: =Model!L57 -> 1088.8155
B10: of which share-of-counter shift | C10: Rs crore | D10: =Model!D58 -> 11.451086 | E10: =Model!E58 -> 47.507657 | F10: =Model!F58 -> 123.02743 | G10: =Model!G58 -> 222.75 | H10: =Model!H58 -> 328.86 | I10: =Model!I58 -> 441.35743 | J10: =Model!J58 -> 560.24229 | K10: =Model!K58 -> 649.43486 | L10: =Model!L58 -> 2384.6307
B11: of which GMV protected by retention | C11: Rs crore | D11: =Model!D60 -> 1.9085143 | E11: =Model!E60 -> 9.8264571 | F11: =Model!F60 -> 30.331029 | G11: =Model!G60 -> 67.456029 | H11: =Model!H60 -> 122.26603 | I11: =Model!I60 -> 195.8256 | J11: =Model!J60 -> 289.19931 | K11: =Model!K60 -> 397.43846 | L11: =Model!L60 -> 1114.2514
B12: Paytm merchant GMV with bundle | C12: Rs lakh crore | D12: =Model!D64 -> 7.9489672 | E12: =Model!E64 -> 8.2983501 | F12: =Model!F64 -> 8.648861 | G12: =Model!G64 -> 9.0003007 | H12: =Model!H64 -> 9.3522983 | I12: =Model!I64 -> 9.7048156 | J12: =Model!J64 -> 10.057829 | K12: =Model!K64 -> 10.410453
B13: Uplift vs baseline | C13: % | D13: =Model!D65 -> 3.4815115e-05 | E13: =Model!E65 -> 0.00014550378 | F13: =Model!F65 -> 0.00037773679 | G13: =Model!G65 -> 0.00069524467 | H13: =Model!H65 -> 0.0010487851 | I13: =Model!I65 -> 0.0014305295 | J13: =Model!J65 -> 0.0018351957 | K13: =Model!K65 -> 0.0021752606
B14: Participating merchants | C14: lakh | D14: =Model!D52 -> 0.15904286 | E14: =Model!E52 -> 0.65982857 | F14: =Model!F52 -> 1.7087143 | G14: =Model!G52 -> 3.09375 | H14: =Model!H52 -> 4.5675 | I14: =Model!I52 -> 6.1299643 | J14: =Model!J52 -> 7.7811429 | K14: =Model!K52 -> 9.0199286
B15: New customers acquired | C15: lakh | D15: =Model!D53 -> 4.7712857 | E15: =Model!E53 -> 19.794857 | F15: =Model!F53 -> 51.261429 | G15: =Model!G53 -> 92.8125 | H15: =Model!H53 -> 137.025 | I15: =Model!I53 -> 183.89893 | J15: =Model!J53 -> 233.43429 | K15: =Model!K53 -> 270.59786 | L15: =Model!L53 -> 993.59614
B16: North Star without bundle (per participating merchant) | C16: Rs / quarter | D16: =Model!D66 -> 240000 | E16: =Model!E66 -> 240000 | F16: =Model!F66 -> 240000 | G16: =Model!G66 -> 240000 | H16: =Model!H66 -> 240000 | I16: =Model!I66 -> 240000 | J16: =Model!J66 -> 240000 | K16: =Model!K66 -> 240000
B17: North Star with bundle (per participating merchant) | C17: Rs / quarter | D17: =Model!D67 -> 256200 | E17: =Model!E67 -> 256807.41 | F17: =Model!F67 -> 257337.3 | G17: =Model!G67 -> 258031.53 | H17: =Model!H67 -> 258775.29 | I17: =Model!I67 -> 259420.89 | J17: =Model!J67 -> 259961.44 | K17: =Model!K67 -> 260645.3
B18: North Star uplift | C18: % | D18: =Model!D68 -> 0.0675 | E18: =Model!E68 -> 0.070030885 | F18: =Model!F68 -> 0.072238747 | G18: =Model!G68 -> 0.075131359 | H18: =Model!H68 -> 0.078230386 | I18: =Model!I68 -> 0.080920384 | J18: =Model!J68 -> 0.083172654 | K18: =Model!K68 -> 0.086022077
B19: Paytm revenue from the bundle | C19: Rs crore | D19: =Model!D73 -> 0.22744719 | E19: =Model!E73 -> 0.94813448 | F19: =Model!F73 -> 2.4663909 | G19: =Model!G73 -> 4.4932918 | H19: =Model!H73 -> 6.6819028 | I19: =Model!I73 -> 9.0318934 | J19: =Model!J73 -> 11.54352 | K19: =Model!K73 -> 13.500814 | L19: =Model!L73 -> 48.893394
B20: Contribution to Paytm | C20: Rs crore | D20: =Model!D77 -> 0.13440712 | E20: =Model!E77 -> 0.56213476 | F20: =Model!F77 -> 1.4667931 | G20: =Model!G77 -> 2.6834481 | H20: =Model!H77 -> 4.0099153 | I20: =Model!I77 -> 5.4458643 | J20: =Model!J77 -> 6.991551 | K20: =Model!K77 -> 8.2241557 | L20: =Model!L77 -> 29.518269
B21: Merchant reward spend protected by Intent Guard | C21: Rs crore | D21: =Model!D79 -> 0.071569286 | E21: =Model!E79 -> 0.29692286 | F21: =Model!F79 -> 0.76892143 | G21: =Model!G79 -> 1.3921875 | H21: =Model!H79 -> 2.055375 | I21: =Model!I79 -> 2.7584839 | J21: =Model!J79 -> 3.5015143 | K21: =Model!K79 -> 4.0589679 | L21: =Model!L79 -> 14.903942
B23: B. Scenarios side by side
B24: Metric | C24: Unit | D24: Bear | E24: Base | F24: Bull
B25: Participating merchants at Q3 FY29 | C25: lakh | D25: =Model!K12 -> 3.2070857 | E25: =Model!K52 -> 9.0199286 | F25: =Model!K92 -> 20.044286
B26: Incremental GMV in Q3 FY29 | C26: Rs crore | D26: =Model!K21 -> 232.76649 | E26: =Model!K61 -> 2259.6296 | F26: =Model!K101 -> 12681.556
B27: Incremental GMV, 8 quarters cumulative | C27: Rs crore | D27: =Model!L21 -> 798.45111 | E27: =Model!L61 -> 7568.4861 | F27: =Model!L101 -> 40890.117
B28: Uplift vs baseline GMV at Q3 FY29 | C28: % | D28: =Model!K25 -> 0.00022407556 | E28: =Model!K65 -> 0.0021752606 | F28: =Model!K105 -> 0.012208057
B29: North Star uplift per participating merchant at Q3 FY29 | C29: % | D29: =Model!K28 -> 0.039206241 | E29: =Model!K68 -> 0.086022077 | F29: =Model!K108 -> 0.13902502
B30: New customers acquired, 8 quarters | C30: lakh | D30: =Model!L13 -> 176.63931 | E30: =Model!L53 -> 993.59614 | F30: =Model!L93 -> 3311.9871
B31: Paytm revenue in Q3 FY29 | C31: Rs crore | D31: =Model!K33 -> 1.7464591 | E31: =Model!K73 -> 13.500814 | F31: =Model!K113 -> 61.881248
B32: Paytm revenue, 8 quarters cumulative | C32: Rs crore | D32: =Model!L33 -> 6.328903 | E32: =Model!L73 -> 48.893394 | F32: =Model!L113 -> 223.03195
B33: Contribution to Paytm, 8 quarters cumulative | C33: Rs crore | D33: =Model!L37 -> -2.944661 | E33: =Model!L77 -> 29.518269 | F33: =Model!L117 -> 191.01608
B34: Mohalla fees vs Q1 FY27 Marketing Services revenue, at Q3 FY29 | C34: % | D34: =Model!K40 -> 0.0060384459 | E34: =Model!K80 -> 0.045288344 | F34: =Model!K120 -> 0.18870143
B35: Merchant reward spend protected by Intent Guard, 8 quarters | C35: Rs crore | D35: =Model!L39 -> 0.88319657 | E35: =Model!L79 -> 14.903942 | F35: =Model!L119 -> 105.98359
B36: Unit economics: Paytm contribution per participating merchant | C36: Rs / month | D36: =Model!K41 -> -9.8 | E36: =Model!K81 -> 25.4 | F36: =Model!K121 -> 76.3
B37: Break-even new customers per merchant | C37: customers / month | D37: =Model!K42 -> 14.8 | E37: =Model!K82 -> 1.5333333 | F37: =Model!K122 -> 0
B38: Merchant cost per new customer as % of first bill | C38: % | D38: =Model!K44 -> 0.112 | E38: =Model!K84 -> 0.11333333 | F38: =Model!K124 -> 0.12857143
B40: C. Baseline context
B41: Baseline GMV, Q1 FY27 actual | C41: Rs lakh crore | D41: =Baseline!E12 -> 7.1
B42: Baseline GMV, Q3 FY29 FORECAST (linear) | C42: Rs lakh crore | D42: =Baseline!E22 -> 10.387857
B43: Baseline GMV, Q3 FY29 GROWTH cross-check | C43: Rs lakh crore | D43: =Baseline!G22 -> 12.851426
B44: Device merchants, Q3 FY29 FORECAST | C44: crore | D44: =Baseline!H22 -> 2.2271429
B45: Net payment revenue from a 1% GMV lift (Q1 FY27 base) | C45: Rs crore / quarter | D45: =Baseline!F29 -> 6.01

Sheet Sources
A1: Sources
A3: ID | B3: What it supports | C3: Link
A4: S1 | B4: Paytm Q1 FY27 earnings release (agent datapack): GMV Jun-25 / Mar-26 / Jun-26, subscription merchants, net payment revenue 8.4 bps, processing margin >4 bps, Marketing Services Rs 239 crore, cashback Rs 90 crore, registered merchants, in-house fine-tuned models | C4: https://paytm.com/document/ir/financial-results/fy2026-27/Paytm_Q1_FY27_Agent_Datapack.md
A5: S2 | B5: Q2 FY26 (Sep-25): GMV Rs 5.67 lakh crore, subscriptions 1.37 crore | C5: https://ianslive.in/paytms-profitability-improves-to-rs-211-crore-in-q2-revenue-up-24-pc--20251104222037
A6: S3 | B6: Q3 FY26 (Dec-25): GMV Rs 6.2 lakh crore | C6: https://www.businesstoday.in/amp/latest/corporate/story/paytms-q3-net-profit-jumps-to-rs225-crore-on-upi-surge-and-merchant-services-boost-513573-2026-01-29
A7: S4 | B7: Q4 FY25 (Mar-25): GMV Rs 5.1 lakh crore, subscriptions 1.24 crore | C7: https://www.business-standard.com/companies/quarterly-results/one-97-communication-paytm-q4-fy25-result-loss-profit-revenue-stock-option-125050601030_1.html
A8: S5 | B8: Q3 FY25 (Dec-24): GMV Rs 5.0 lakh crore, up 13% QoQ from Rs 4.5 lakh crore; subscriptions 1.17 crore after 5 lakh QoQ additions | C8: https://inc42.com/?p=495669
A9: S6 | B9: Q3 FY26 (Dec-25): subscription merchants 1.44 crore | C9: https://alphastreet.com/india/symbol/PAYTM
A10: S7 | B10: Soundbox rental Rs 125-150 a month (BofA merchant checks in Mumbai) | C10: https://www.outlookbusiness.com/amp/story/enterprise/bofa-research-paytm-soundbox-first-to-bring-audio-based-payments-confirmations-dominates-the-market-6795
A11: S8 | B11: Paytm subscription revenue ~Rs 90 per device a month (Q4 FY24) | C11: https://www.medianama.com/2024/10/223-paytm-to-monetize-soundbox-ads-in-partnership-with-meesho-a-shift-away-from-core-payments-business/
A12: S9 | B12: Merchants often keep separate soundboxes for PhonePe, Paytm and Google Pay | C12: https://inc42.com/buzz/upi-transactions-jump-3-8-mom-in-may-cross-23-bn-mark/
