Workbook

Sheet README
B2: Restock Agent (with Intent Guard) + Soundbox Care: 8-quarter GMV and contribution projection
B3: Paytm Build for India AI Hackathon, Mumbai | Track 1: Merchant Growth AI | Kamalika Poddar
B5: What this model does
B6: 1. Baseline: Paytm merchant GMV and device (subscription) merchants, projected with FORECAST (linear) on 8 reported quarters, Q2 FY25 to Q1 FY27. GROWTH (exponential) is shown alongside as a cross-check.
B7: 2. Restock Agent: grocery and FMCG shops order stock from their suppliers through an agent that pays inside the owner's limits (Intent Guard). Credit is routed to whichever rail gives the merchant the best hit rate: Paytm partner lenders, MUDRA credit line on UPI, OCEN or ONDC Financial Services, all underwritten with Account Aggregator data.
B8: 3. Soundbox Care: devices detect and fix their own faults, keep confirmations going on the owner's phone while down, and flag failures early, cutting field visits, replacements, downtime and churn.
B9: 4. Nearby (Phase 2): consented hyperlocal offers inside the Paytm app, priced per verified new customer. Off by default; switch on only if NPCI's 30% UPI cap is enforced.
B10: 5. Outputs: incremental GMV and contribution for 8 quarters from Q4 FY27 (Jan-Mar 2027 pilot) to Q3 FY29, in three scenarios (Bear, Base, Bull).
B12: How to use it
B13: Change blue cells on Assumptions (and reported actuals on Baseline). Every other number is a formula and recalculates.
B14: Colour code: blue text = input | black text = formula | green text = link to another sheet | yellow fill = key assumption.
B15: Units: lakh = 1,00,000 | crore = 1,00,00,000 | Rs 1 lakh crore = Rs 1,00,000 crore. Quarters follow India's April-March fiscal year.
... B29: Caveat: reported figures come from Paytm's disclosures, regulators and press coverage (see Sources). Everything else on Assumptions is a team estimate for a hackathon pitch, not Paytm data. Paytm's own device-ticket, lending and category data would replace several estimates directly.

Sheet Assumptions
A1: Assumptions: Restock Agent (with Intent Guard) + Soundbox Care
A2: Blue cells are inputs. Bear / Base / Bull columns feed the three scenario blocks on the Model sheet. Team estimates unless a source is named (Sources sheet).
A4: ID | B4: Assumption | C4: Unit | D4: Bear | E4: Base | F4: Bull | L4: Why this number / source
A5: Common
A6: K1 | B6: Payment processing margin on incremental GMV | C6: % of GMV | D6: 0.0004 | E6: 0.0004 | F6: 0.0004 | L6: Paytm Q1 FY27: payment processing margin 'comfortably above 4 bps' (S1, S10). Held at 4 bps in all scenarios.
A7: K2 | B7: Paytm-processed GMV per average device merchant per month | C7: Rs / month | D7: 50000 | E7: 60000 | F7: 80000 | L7: Team estimate. Ceiling check on Baseline: Q1 FY27 GMV / device merchants / 3 = ~Rs 1.5 lakh a month if all GMV came from device merchants (it does not).
A8: K3 | B8: Device subscription revenue per merchant per month | C8: Rs / month | D8: 80 | E8: 90 | F8: 100 | L8: ~Rs 90 per device a month in Q4 FY24 (S8); the Q1 FY27 release notes a modest YoY decline per device (S1).
A9: Restock Agent: scope and payment routing
A10: R1 | B10: Grocery and FMCG general-trade shops (kiranas, provision and general stores) among device merchants | C10: % of device merchants | D10: 0.3 | E10: 0.4 | F10: 0.5 | L10: Team estimate. Paytm does not disclose its merchant category mix.
A11: R2 | B11: Active users: covered eligible merchants who finish onboarding (supplier invoices captured or supplier linked) and order through the agent every month | C11: % of covered merchants | D11: 0.05 | E11: 0.1 | F11: 0.15 | L11: Team estimate. Onboarding is the data gate: no invoices or supplier link, no suggestions.
A12: R3 | B12: Supplier purchases per active merchant per month | C12: Rs / month | D12: 150000 | E12: 250000 | F12: 350000 | L12: Team estimate. Kirana gross margins on national brands run ~5-10% (S14), so purchases are ~90% of sales; the base implies ~Rs 2.75 lakh of monthly sales.
A13: R4 | B13: Share of purchases ordered through the agent | C13: % of purchases | D13: 0.2 | E13: 0.35 | F13: 0.5 | L13: Team estimate. FMCG companies' own retailer apps keep their share: HUL's Shikhar handled about a quarter of HUL's general trade by 2023 (S15).
A14: R5 | B14: Share of agent orders paid through Paytm (UPI, payment link or credit) | C14: % of agent orders | D14: 0.5 | E14: 0.7 | F14: 0.85 | L14: Team estimate. The rest stays cash or bank transfer; distributors opposing MDR may push cash (S16).
A15: R6 | B15: Share of those Paytm payments that are new to Paytm (previously cash, cheque, bank transfer or another app) | C15: % of Paytm-paid orders | D15: 0.4 | E15: 0.6 | F15: 0.75 | L15: Team estimate. Only new-to-Paytm payments count as incremental GMV.
A16: Restock Agent: credit, routed to the rail with the best hit rate (AA-based underwriting on every rail)
A17: R7 | B17: Share of agent-ordered value where the merchant asks for pay-later | C17: % of agent orders | D17: 0.15 | E17: 0.25 | F17: 0.35 | L17: Team estimate. Distributors already give 7-21 days of free credit, so pay-later has to beat it.
A18: R8 | B18: Router hit rate: share of pay-later requests approved on at least one rail | C18: % of requests | D18: 0.35 | E18: 0.5 | F18: 0.65 | L18: Benchmarks: public-sector banks' digital MSME model approved ~47% of applications in Apr-Oct FY26 (S12); open-network leads approve under 1% (team field estimate); a MUDRA credit line on UPI clears instantly when it has headroom (S18).
A19: R9 | B19: Rail mix: Paytm partner lenders (pay-later paid straight to the supplier) | C19: % of pay-later value | D19: 0.45 | E19: 0.45 | F19: 0.45 | L19: Team estimate of where merchant-first routing lands. Same in all scenarios.
A20: R10 | B20: Rail mix: MUDRA credit line on UPI | C20: % of pay-later value | D20: 0.25 | E20: 0.25 | F20: 0.25 | L20: Credit line on UPI covers PM MUDRA loans, with 8 banks live since Sep 2026 (S18).
A21: R11 | B21: Rail mix: OCEN lenders | C21: % of pay-later value | D21: 0.15 | E21: 0.15 | F21: 0.15 | L21: Team estimate. OCEN handled 5,641 loans in Q1 2025 (Mohalla model sources).
A22: R12 | B22: Rail mix: ONDC Financial Services lenders | C22: % of pay-later value | D22: =1-D19-D20-D21 -> 0.15 | E22: =1-E19-E20-E21 -> 0.15 | F22: =1-F19-F20-F21 -> 0.15 | L22: Formula: the remainder.
A23: R13 | B23: Paytm take per 30-day pay-later cycle: partner lenders | C23: % of value per cycle | D23: 0.003 | E23: 0.005 | F23: 0.007 | L23: Team estimate: a share of the lender's ~1.5-2% monthly yield (18-24% a year). Paytm doesn't publish take rates.
A24: R14 | B24: Paytm take per cycle: MUDRA credit line on UPI | C24: % of value per cycle | D24: 0 | E24: 0 | F24: 0.001 | L24: Pays Paytm little or nothing directly; any interchange on credit-line UPI payments is unconfirmed.
A25: R15 | B25: Paytm take per cycle: OCEN (Paytm as loan service provider) | C25: % of value per cycle | D25: 0.002 | E25: 0.004 | F25: 0.005 | L25: Team estimate.
A26: R16 | B26: Paytm take per cycle: ONDC Financial Services (Paytm as buyer app) | C26: % of value per cycle | D26: 0.002 | E26: 0.003 | F26: 0.005 | L26: Team estimate.
A27: R17 | B27: Working-capital loans: share of active merchants taking a new loan through the router each year | C27: % per year | D27: 0.05 | E27: 0.1 | F27: 0.15 | L27: Team estimate, incremental to Paytm's existing lending: purchase history and verified suppliers improve approvals. Paytm merchant loans run 6-24 months with daily instalments (S11).
A28: R18 | B28: Average working-capital loan | C28: Rs per loan | D28: 100000 | E28: 150000 | F28: 200000 | L28: Team estimate. Paytm merchant loans go up to Rs 10 lakh (S11); MUDRA has averaged ~Rs 69,000 per loan over 11 years (S22).
A29: R19 | B29: Paytm revenue per working-capital loan (distribution and collection) | C29: % of loan value | D29: 0.02 | E29: 0.03 | F29: 0.04 | L29: Team estimate. Paytm doesn't publish take rates.
A30: R20 | B30: Paytm credit-loss sharing on partner-lender pay-later | C30: % of value per cycle | D30: 0.0025 | E30: 0.001 | F30: 0 | L30: Team estimate. RBI caps default-loss guarantees at 5% of a loan portfolio (S26); whether Paytm gives one to merchant-loan partners isn't public.
A31: R21 | B31: Paytm credit-loss sharing on working-capital loans | C31: % of loan value | D31: 0.015 | E31: 0.005 | F31: 0 | L31: Team estimate, as R20.
A32: Restock Agent: MDR, paid plan, merchant sales
A33: R22 | B33: MDR switch: 1 = MDR on UPI merchant payments above Rs 2,000 is live | C33: 1 or 0 | D33: 0 | E33: 1 | F33: 1 | L33: Finance Ministry notified MDR on 14 Sep 2026 (S17); NPCI deferred the 15 Oct start to after Diwali (S16). Bear assumes it doesn't reach distributors.
A34: R23 | B34: Share of new-to-Paytm supplier payments above Rs 2,000 that go to non-exempt (larger) distributors | C34: % of value | D34: 0.4 | E34: 0.6 | F34: 0.75 | L34: Team estimate. Restock invoices are usually above Rs 2,000; an exemption for businesses under Rs 40 lakh turnover was under consideration (S16).
A35: R24 | B35: Paytm's effective share of MDR, as % of payment value | C35: % of value | D35: 0.0005 | E35: 0.001 | F35: 0.0015 | L35: MDR is ~0.40%, capped at Rs 300 (S16), split among banks, payment aggregators and apps; the split isn't decided (S17). Paytm earns most where it acquires the distributor.
A36: R25 | B36: Paid plan attach rate (autopilot ordering, Intent Guard, credit routing) | C36: % of active merchants | D36: 0.1 | E36: 0.2 | F36: 0.3 | L36: Team estimate.
A37: R26 | B37: Paid plan price | C37: Rs / month | D37: 49 | E37: 99 | F37: 149 | L37: Anchored to Soundbox rental of Rs 125-150 a month (S7).
A38: R27 | B38: Paytm-processed sales per active Restock merchant per month, before Restock | C38: Rs / month | D38: 50000 | E38: 80000 | F38: 120000 | L38: Team estimate, same as the Mohalla model's A8.
A39: R28 | B39: Sales increase from fewer stock-outs and more stock on credit | C39: % of sales | D39: 0.01 | E39: 0.02 | F39: 0.03 | L39: Team estimate. No public figure for kirana stock-out losses; HUL built Shikhar partly to tackle stock-outs (S15). The pilot measures this against holdout shops.
A40: Restock Agent: costs
A41: R29 | B41: AI cost per active merchant (invoice reading, voice, agent) | C41: Rs / month | D41: 25 | E41: 15 | F41: 10 | L41: Team estimate.
A42: R30 | B42: Extra AI and Intent Guard checks per paid-plan merchant | C42: Rs / month | D42: 25 | E42: 15 | F42: 10 | L42: Team estimate.
A43: R31 | B43: One-time onboarding per newly active merchant (field visit, invoice digitisation) | C43: Rs per merchant | D43: 400 | E43: 250 | F43: 150 | L43: Team estimate.
A44: R32 | B44: Support per active merchant | C44: Rs / month | D44: 20 | E44: 12 | F44: 8 | L44: Team estimate.
A45: R33 | B45: Processing cost on new-to-Paytm supplier payments | C45: % of value | D45: 0.0002 | E45: 0.0001 | F45: 5e-05 | L45: Team estimate.
A46: Restock Agent: merchant view (a merchant on the paid plan who uses pay-later)
A47: R34 | B47: Merchant gross margin | C47: % of sales | D47: 0.07 | E47: 0.09 | F47: 0.11 | L47: Kirana margins run ~5-10% on national brands and 10-18% on regional brands (S14).
A48: R35 | B48: Merchant's cost of pay-later | C48: % per 30-day cycle | D48: 0.02 | E48: 0.0175 | F48: 0.015 | L48: Team estimate: 18-24% a year.
A49: R36 | B49: Supplier-payment value Intent Guard stops going wrong (payee swaps, duplicates, price errors) | C49: % of agent-ordered value | D49: 0.001 | E49: 0.002 | F49: 0.003 | L49: Team estimate. Merchant money protected, not Paytm revenue.
A50: Soundbox Care
A51: C1 | B51: Device incidents per 100 covered devices per year (offline, not announcing, battery, damage) | C51: per 100 devices / year | D51: 40 | E51: 40 | F51: 40 | L51: Team estimate. Paytm knows the real number from its tickets; held constant so scenarios differ only in how well Care works.
A52: C2 | B52: Share of incidents that need a field visit today | C52: % of incidents | D52: 0.6 | E52: 0.6 | F52: 0.6 | L52: Team estimate.
A53: C3 | B53: Share of field visits avoided by remote or guided fixes | C53: % of visits | D53: 0.15 | E53: 0.3 | F53: 0.45 | L53: Team estimate: network failover (Wi-Fi/4G), remote reboot, firmware rollback, voice-guided fixes.
A54: C4 | B54: Cost per field visit | C54: Rs per visit | D54: 350 | E54: 350 | F54: 350 | L54: Team estimate.
A55: C5 | B55: Share of incidents ending in a replacement device today | C55: % of incidents | D55: 0.25 | E55: 0.25 | F55: 0.25 | L55: Team estimate.
A56: C6 | B56: Share of replacements avoided (fixed remotely or caught early) | C56: % of replacements | D56: 0.05 | E56: 0.1 | F56: 0.2 | L56: Team estimate.
A57: C7 | B57: Cost of a replacement, including logistics | C57: Rs per device | D57: 1500 | E57: 1500 | F57: 1500 | L57: Team estimate.
A58: C8 | B58: Days down per incident today | C58: days | D58: 4 | E58: 4 | F58: 4 | L58: Team estimate.
A59: C9 | B59: Cut in days down per incident | C59: % of days | D59: 0.25 | E59: 0.5 | F59: 0.65 | L59: Team estimate.
A60: C10 | B60: Share of a down device's Paytm GMV lost while it's down | C60: % of daily GMV | D60: 0.1 | E60: 0.2 | F60: 0.3 | L60: UPI QR still works without the Soundbox. Losses come from missing confirmations (merchants fall back on screenshots, which Paytm has warned can be spoofed, S20) and failed card payments on AI Soundboxes (S19).
A61: C11 | B61: Share of incident devices the merchant returns within a year, today | C61: % of incident devices | D61: 0.08 | E61: 0.08 | F61: 0.08 | L61: Team estimate. Paytm does not disclose device churn.
A62: C12 | B62: Cut in post-incident device returns with Care | C62: % of churn | D62: 0.15 | E62: 0.3 | F62: 0.45 | L62: Team estimate.
... A64: C14 | B64: Phone fallback cost per incident (push alert, voice call) | C64: Rs per incident | D64: 15 | E64: 10 | F64: 5 | L64: Team estimate.
A65: Nearby (Phase 2 switch): consented offers inside the Paytm app, merchant pays per verified new customer
A66: N0 | B66: Nearby switch: 1 = NPCI's 30% UPI cap is enforced and Nearby runs | C66: 1 or 0 | D66: 0 | E66: 0 | F66: 0 | L66: Off in all scenarios. The cap is due 31 Dec 2026 and has been extended twice (S24). Summary shows what Nearby would add if switched on.
A67: N1 | B67: Device merchants in dense clusters | C67: % of device merchants | D67: 0.2 | E67: 0.3 | F67: 0.4 | L67: Same as the Mohalla model's A1.
A68: N2 | B68: Participation | C68: % of covered merchants | D68: 0.05 | E68: 0.1 | F68: 0.15 | L68: Team estimate.
A69: N3 | B69: Verified new customers per merchant per month (Paytm-app payers who wouldn't have come anyway) | C69: customers / month | D69: 2 | E69: 4 | F69: 6 | L69: Team estimate. Offers reach only Paytm-app payers (Paytm ~8% of UPI payments, S24); the uplift model filters out customers who would have come anyway.
A70: N4 | B70: First bill | C70: Rs per visit | D70: 250 | E70: 300 | F70: 350 | L70: Same as the Mohalla model's A4.
A71: N5 | B71: Share of Nearby GMV that's new to Paytm (not moved from another Paytm shop) | C71: % of GMV | D71: 0.3 | E71: 0.5 | F71: 0.7 | L71: Team estimate.
A72: N6 | B72: Paytm fee per verified new customer | C72: Rs per customer | D72: 8 | E72: 12 | F72: 15 | L72: Team estimate. Merchant pays only for customers the model verifies as new.
A73: N7 | B73: Paytm-funded cashback replaced per verified new customer | C73: Rs per customer | D73: 5 | E73: 10 | F73: 15 | L73: Paytm spent Rs 90 crore on cashback and incentives in Q1 FY27 (S1).
A74: N8 | B74: Uplift model and offer cost per merchant | C74: Rs / month | D74: 10 | E74: 6 | F74: 4 | L74: Team estimate.
A75: N9 | B75: Payout cost per reward | C75: Rs per payout | D75: 2 | E75: 1 | F75: 0.5 | L75: Same as the Mohalla model's A17.
A77: Rollout ramps (Paytm controls the pace, so the same in all scenarios)
B78: Quarter | D78: Q4 FY27 | E78: Q1 FY28 | F78: Q2 FY28 | G78: Q3 FY28 | H78: Q4 FY28 | I78: Q1 FY29 | J78: Q2 FY29 | K78: Q3 FY29
A79: RR | B79: Restock: share of eligible shops in live cities | C79: % of eligible | D79: 0.02 | E79: 0.06 | F79: 0.12 | G79: 0.2 | H79: 0.3 | I79: 0.4 | J79: 0.5 | K79: 0.6 | L79: Q4 FY27 Mumbai pilot. Slower than a software rollout because suppliers have to be onboarded city by city.
A80: CR | B80: Soundbox Care: share of the device base with Care switched on | C80: % of devices | D80: 0.05 | E80: 0.15 | F80: 0.3 | G80: 0.45 | H80: 0.6 | I80: 0.7 | J80: 0.8 | K80: 0.85 | L80: Firmware and backend rollout; older models get a subset (remote diagnostics, phone fallback).
A81: NR | B81: Nearby: share of eligible clusters live (only if switched on) | C81: % of eligible | D81: 0 | E81: 0.05 | F81: 0.15 | G81: 0.25 | H81: 0.35 | I81: 0.45 | J81: 0.55 | K81: 0.6 | L81: Starts the quarter after the 31 Dec 2026 cap date.
A83: Checks
B84: Rail mix adds up to 100% | D84: =IF(ABS(D19+D20+D21+D22-1)<0.0001,"OK","CHECK") -> OK | E84: =IF(ABS(E19+E20+E21+E22-1)<0.0001,"OK","CHECK") -> OK | F84: =IF(ABS(F19+F20+F21+F22-1)<0.0001,"OK","CHECK") -> OK
B85: Pay-later approved stays within orders paid through Paytm (R7 x R8 <= R5) | D85: =IF(D17*D18<=D14,"OK","CHECK") -> OK | E85: =IF(E17*E18<=E14,"OK","CHECK") -> OK | F85: =IF(F17*F18<=F14,"OK","CHECK") -> OK
A87: Structural rules built into the formulas
A88: Rule 1 | B88: Only supplier payments that are new to Paytm (R6) count as incremental GMV; MDR and processing cost apply to that new value only.
A89: Rule 2 | B89: Pay-later revolves every 30 days: each month's approved orders are a new cycle that earns Paytm's take for its rail.
A90: Rule 3 | B90: Working-capital loans are counted at disbursal; Paytm earns a share of loan value (R19) and bears any credit-loss sharing (R21).
A91: Rule 4 | B91: Soundbox Care savings (field visits and replacements avoided) count toward contribution as avoided variable cost.
A92: Rule 5 | B92: Devices kept by Care are cumulative and keep the average device merchant's GMV (K2) and subscription (K3).
A93: Rule 6 | B93: Baseline GMV and device merchants use FORECAST (linear) on 8 reported quarters; GROWTH (exponential) is shown as a cross-check.
A94: Rule 7 | B94: Contribution = revenue - variable costs + avoided costs. Fixed engineering and platform costs are excluded.
A95: Rule 8 | B95: Nearby counts in totals only when its switch (N0) is 1; its standalone numbers are always computed for reference.

Sheet Baseline
A1: Baseline: Paytm merchant GMV and device merchants
A2: Rows 5-12 are reported actuals (blue). Rows 13-22 are FORECAST (linear) on those 8 quarters. Column G is GROWTH (exponential) as a cross-check. The model uses the linear forecast.
A4: x (period) | B4: Quarter | C4: Months | D4: Type | E4: Merchant GMV (Rs lakh crore) | F4: GMV YoY | G4: Cross-check: GROWTH (Rs lakh crore) | H4: Device merchants (crore) | I4: Source / method
A5: 1 | B5: Q2 FY25 | C5: Jul-Sep 2024 | D5: Actual | E5: 4.5 | H5: 1.12 | I5: GMV: S5 (Q3 FY25 GMV up 13% QoQ from Rs 4.5 lakh crore). Device merchants: derived, 1.17 crore at Dec-24 minus 5 lakh added that quarter (S5).
A6: 2 | B6: Q3 FY25 | C6: Oct-Dec 2024 | D6: Actual | E6: 5 | H6: 1.17 | I6: S5
A7: 3 | B7: Q4 FY25 | C7: Jan-Mar 2025 | D7: Actual | E7: 5.1 | H7: 1.24 | I7: S4
A8: 4 | B8: Q1 FY26 | C8: Apr-Jun 2025 | D8: Actual | E8: 5.4 | H8: 1.3 | I8: S1 (Jun-25 column of the Q1 FY27 release)
A9: 5 | B9: Q2 FY26 | C9: Jul-Sep 2025 | D9: Actual | E9: 5.67 | F9: =E9/E5-1 -> 0.26 | H9: 1.37 | I9: S2
A10: 6 | B10: Q3 FY26 | C10: Oct-Dec 2025 | D10: Actual | E10: 6.2 | F10: =E10/E6-1 -> 0.24 | H10: 1.44 | I10: GMV: S3. Device merchants: S6
A11: 7 | B11: Q4 FY26 | C11: Jan-Mar 2026 | D11: Actual | E11: 6.5 | F11: =E11/E7-1 -> 0.2745098 | H11: 1.51 | I11: S1 (Mar-26 column)
A12: 8 | B12: Q1 FY27 | C12: Apr-Jun 2026 | D12: Actual | E12: 7.1 | F12: =E12/E8-1 -> 0.31481481 | H12: 1.57 | I12: S1, S10
A13: 9 | B13: Q2 FY27 | C13: Jul-Sep 2026 | D13: Forecast | E13: =FORECAST(A13,$E$5:$E$12,$A$5:$A$12) -> 7.2517857 | F13: =E13/E9-1 -> 0.27897455 | G13: =GROWTH($E$5:$E$12,$A$5:$A$12,A13) -> 7.4103976 | H13: =FORECAST(A13,$H$5:$H$12,$A$5:$A$12) -> 1.6357143 | I13: FORECAST (linear) on rows 5-12. Not yet reported; bridges to the projection window.
A14: 10 | B14: Q3 FY27 | C14: Oct-Dec 2026 | D14: Forecast | E14: =FORECAST(A14,$E$5:$E$12,$A$5:$A$12) -> 7.6002381 | F14: =E14/E10-1 -> 0.22584485 | G14: =GROWTH($E$5:$E$12,$A$5:$A$12,A14) -> 7.8778783 | H14: =FORECAST(A14,$H$5:$H$12,$A$5:$A$12) -> 1.7014286 | I14: FORECAST (linear) on rows 5-12. Not yet reported; bridges to the projection window. Rows 15-22 (shaded) are the 8-quarter projection window.
A15: 11 | B15: Q4 FY27 | C15: Jan-Mar 2027 | D15: Forecast | E15: =FORECAST(A15,$E$5:$E$12,$A$5:$A$12) -> 7.9486905 | F15: =E15/E11-1 -> 0.22287546 | G15: =GROWTH($E$5:$E$12,$A$5:$A$12,A15) -> 8.3748497 | H15: =FORECAST(A15,$H$5:$H$12,$A$5:$A$12) -> 1.7671429 | I15: FORECAST (linear) on rows 5-12
A16: 12 | B16: Q1 FY28 | C16: Apr-Jun 2027 | D16: Forecast | E16: =FORECAST(A16,$E$5:$E$12,$A$5:$A$12) -> 8.2971429 | F16: =E16/E12-1 -> 0.16861167 | G16: =GROWTH($E$5:$E$12,$A$5:$A$12,A16) -> 8.9031723 | H16: =FORECAST(A16,$H$5:$H$12,$A$5:$A$12) -> 1.8328571 | I16: FORECAST (linear) on rows 5-12
A17: 13 | B17: Q2 FY28 | C17: Jul-Sep 2027 | D17: Forecast | E17: =FORECAST(A17,$E$5:$E$12,$A$5:$A$12) -> 8.6455952 | F17: =E17/E13-1 -> 0.19220225 | G17: =GROWTH($E$5:$E$12,$A$5:$A$12,A17) -> 9.4648238 | H17: =FORECAST(A17,$H$5:$H$12,$A$5:$A$12) -> 1.8985714 | I17: FORECAST (linear) on rows 5-12
A18: 14 | B18: Q3 FY28 | C18: Oct-Dec 2027 | D18: Forecast | E18: =FORECAST(A18,$E$5:$E$12,$A$5:$A$12) -> 8.9940476 | F18: =E18/E14-1 -> 0.18339024 | G18: =GROWTH($E$5:$E$12,$A$5:$A$12,A18) -> 10.061907 | H18: =FORECAST(A18,$H$5:$H$12,$A$5:$A$12) -> 1.9642857 | I18: FORECAST (linear) on rows 5-12
A19: 15 | B19: Q4 FY28 | C19: Jan-Mar 2028 | D19: Forecast | E19: =FORECAST(A19,$E$5:$E$12,$A$5:$A$12) -> 9.3425 | F19: =E19/E15-1 -> 0.17535084 | G19: =GROWTH($E$5:$E$12,$A$5:$A$12,A19) -> 10.696656 | H19: =FORECAST(A19,$H$5:$H$12,$A$5:$A$12) -> 2.03 | I19: FORECAST (linear) on rows 5-12
A20: 16 | B20: Q1 FY29 | C20: Apr-Jun 2028 | D20: Forecast | E20: =FORECAST(A20,$E$5:$E$12,$A$5:$A$12) -> 9.6909524 | F20: =E20/E16-1 -> 0.16798669 | G20: =GROWTH($E$5:$E$12,$A$5:$A$12,A20) -> 11.371449 | H20: =FORECAST(A20,$H$5:$H$12,$A$5:$A$12) -> 2.0957143 | I20: FORECAST (linear) on rows 5-12
A21: 17 | B21: Q2 FY29 | C21: Jul-Sep 2028 | D21: Forecast | E21: =FORECAST(A21,$E$5:$E$12,$A$5:$A$12) -> 10.039405 | F21: =E21/E17-1 -> 0.16121614 | G21: =GROWTH($E$5:$E$12,$A$5:$A$12,A21) -> 12.08881 | H21: =FORECAST(A21,$H$5:$H$12,$A$5:$A$12) -> 2.1614286 | I21: FORECAST (linear) on rows 5-12
A22: 18 | B22: Q3 FY29 | C22: Oct-Dec 2028 | D22: Forecast | E22: =FORECAST(A22,$E$5:$E$12,$A$5:$A$12) -> 10.387857 | F22: =E22/E18-1 -> 0.15497022 | G22: =GROWTH($E$5:$E$12,$A$5:$A$12,A22) -> 12.851426 | H22: =FORECAST(A22,$H$5:$H$12,$A$5:$A$12) -> 2.2271429 | I22: FORECAST (linear) on rows 5-12
A25: Reported reference points (Q1 FY27, quarter ended 30 June 2026) and checks
B26: Revenue from operations | D26: Rs crore | F26: 2448 | I26: S10 (up 28% YoY)
B27: Contribution profit | D27: Rs crore | F27: 1350 | I27: S10 (up 17% YoY)
B28: Contribution margin | D28: % of revenue | F28: 0.55 | I28: S10
B29: EBITDA | D29: Rs crore | F29: 203 | I29: S10 (8% margin, highest ever)
B30: Profit after tax | D30: Rs crore | F30: 220 | I30: S10 (up 79% YoY)
B31: Financial services revenue (merchant loans, personal loans, insurance distribution) | D31: Rs crore | F31: 814 | I31: S10 (up 45% YoY)
B32: Net payment revenue, excluding PIDF | D32: Rs crore | F32: 601 | I32: S1, S10
B33: Net payment revenue per Rs of GMV | D33: bps | F33: =F32/(E12*100000)*10000 -> 8.4647887 | I33: Formula. Paytm reports 8.4 bps (S1).
B34: Payment processing margin (reported as 'comfortably above 4 bps') | D34: bps | F34: 4 | I34: S1, S10
B35: Net payment revenue from a 1% GMV lift, at the blended rate | D35: Rs crore per quarter | F35: =E12*100000*0.01*F33/10000 -> 6.01 | I35: Formula. Blended rate; payments under Rs 2,000 carry no MDR, so kirana UPI earns far less.
B36: Marketing Services revenue | D36: Rs crore | F36: 239 | I36: S1 (down 3% YoY)
B37: Promotional cashback and incentives | D37: Rs crore | F37: 90 | I37: S1 (up 143% YoY)
B38: Registered merchants | D38: crore | F38: 5 | I38: S1
B39: Ceiling: GMV per device merchant per month if all GMV came from device merchants | D39: Rs / month | F39: =E12*1000000000000/(H12*10000000)/3 -> 150743.1 | I39: Formula. Upper bound used to sanity-check K2 and R27.
B40: Q3 FY29 baseline: GROWTH cross-check vs FORECAST | D40: % above linear | F40: =G22/E22-1 -> 0.2371585 | I40: Formula. How conservative the linear baseline is.
B41: Mohalla Network (assessed and dropped): base-case contribution over the same 8 quarters | D41: Rs crore | F41: 29.52 | I41: Mohalla_GMV_Projection.xlsx, Summary sheet, base case. Kept for comparison.

Sheet Model
A1: Model: Restock Agent (with Intent Guard) + Soundbox Care, quarter by quarter
A2: Every cell is a formula. Assumption references: Bear = Assumptions column D, Base = E, Bull = F. Column L sums flows over the 8 quarters; stock rows show Q3 FY29; ratio rows divide the 8-quarter totals.
A4: # | B4: Quarter | C4: Unit | D4: Q4 FY27 | E4: Q1 FY28 | F4: Q2 FY28 | G4: Q3 FY28 | H4: Q4 FY28 | I4: Q1 FY29 | J4: Q2 FY29 | K4: Q3 FY29 | L4: 8-qtr total
B5: Months | D5: Jan-Mar 2027 | E5: Apr-Jun 2027 | F5: Jul-Sep 2027 | G5: Oct-Dec 2027 | H5: Jan-Mar 2028 | I5: Apr-Jun 2028 | J5: Jul-Sep 2028 | K5: Oct-Dec 2028
B6: Baseline period index (x) | D6: =Baseline!A15 -> 11 | E6: =Baseline!A16 -> 12 | F6: =Baseline!A17 -> 13 | G6: =Baseline!A18 -> 14 | H6: =Baseline!A19 -> 15 | I6: =Baseline!A20 -> 16 | J6: =Baseline!A21 -> 17 | K6: =Baseline!A22 -> 18
A8: BEAR scenario (Assumptions column D)
B9: Restock Agent: shops, orders and payments
A10: 1 | B10: Device merchants, baseline | C10: lakh | D10: =Baseline!H15*100 -> 176.71429 | E10: =Baseline!H16*100 -> 183.28571 | F10: =Baseline!H17*100 -> 189.85714 | G10: =Baseline!H18*100 -> 196.42857 | H10: =Baseline!H19*100 -> 203 | I10: =Baseline!H20*100 -> 209.57143 | J10: =Baseline!H21*100 -> 216.14286 | K10: =Baseline!H22*100 -> 222.71429 | L10: =K10 -> 222.71429
A11: 2 | B11: Grocery and FMCG shops among device merchants | C11: lakh | D11: =D10*Assumptions!$D$10 -> 53.014286 | E11: =E10*Assumptions!$D$10 -> 54.985714 | F11: =F10*Assumptions!$D$10 -> 56.957143 | G11: =G10*Assumptions!$D$10 -> 58.928571 | H11: =H10*Assumptions!$D$10 -> 60.9 | I11: =I10*Assumptions!$D$10 -> 62.871429 | J11: =J10*Assumptions!$D$10 -> 64.842857 | K11: =K10*Assumptions!$D$10 -> 66.814286 | L11: =K11 -> 66.814286
A12: 3 | B12: Restock rollout coverage | C12: % of eligible | D12: =Assumptions!D$79 -> 0.02 | E12: =Assumptions!E$79 -> 0.06 | F12: =Assumptions!F$79 -> 0.12 | G12: =Assumptions!G$79 -> 0.2 | H12: =Assumptions!H$79 -> 0.3 | I12: =Assumptions!I$79 -> 0.4 | J12: =Assumptions!J$79 -> 0.5 | K12: =Assumptions!K$79 -> 0.6 | L12: =K12 -> 0.6
A13: 4 | B13: Active Restock merchants | C13: lakh | D13: =D11*D12*Assumptions!$D$11 -> 0.053014286 | E13: =E11*E12*Assumptions!$D$11 -> 0.16495714 | F13: =F11*F12*Assumptions!$D$11 -> 0.34174286 | G13: =G11*G12*Assumptions!$D$11 -> 0.58928571 | H13: =H11*H12*Assumptions!$D$11 -> 0.9135 | I13: =I11*I12*Assumptions!$D$11 -> 1.2574286 | J13: =J11*J12*Assumptions!$D$11 -> 1.6210714 | K13: =K11*K12*Assumptions!$D$11 -> 2.0044286 | L13: =K13 -> 2.0044286
A14: 5 | B14: Newly active merchants | C14: lakh | D14: =MAX(0,D13-N(C13)) -> 0.053014286 | E14: =MAX(0,E13-N(D13)) -> 0.11194286 | F14: =MAX(0,F13-N(E13)) -> 0.17678571 | G14: =MAX(0,G13-N(F13)) -> 0.24754286 | H14: =MAX(0,H13-N(G13)) -> 0.32421429 | I14: =MAX(0,I13-N(H13)) -> 0.34392857 | J14: =MAX(0,J13-N(I13)) -> 0.36364286 | K14: =MAX(0,K13-N(J13)) -> 0.38335714 | L14: =SUM(D14:K14) -> 2.0044286
A15: 6 | B15: Supplier purchases by active merchants | C15: Rs crore | D15: =D13*Assumptions!$D$12*3/100 -> 238.56429 | E15: =E13*Assumptions!$D$12*3/100 -> 742.30714 | F15: =F13*Assumptions!$D$12*3/100 -> 1537.8429 | G15: =G13*Assumptions!$D$12*3/100 -> 2651.7857 | H15: =H13*Assumptions!$D$12*3/100 -> 4110.75 | I15: =I13*Assumptions!$D$12*3/100 -> 5658.4286 | J15: =J13*Assumptions!$D$12*3/100 -> 7294.8214 | K15: =K13*Assumptions!$D$12*3/100 -> 9019.9286 | L15: =SUM(D15:K15) -> 31254.429
A16: 7 | B16: Ordered through the agent | C16: Rs crore | D16: =D15*Assumptions!$D$13 -> 47.712857 | E16: =E15*Assumptions!$D$13 -> 148.46143 | F16: =F15*Assumptions!$D$13 -> 307.56857 | G16: =G15*Assumptions!$D$13 -> 530.35714 | H16: =H15*Assumptions!$D$13 -> 822.15 | I16: =I15*Assumptions!$D$13 -> 1131.6857 | J16: =J15*Assumptions!$D$13 -> 1458.9643 | K16: =K15*Assumptions!$D$13 -> 1803.9857 | L16: =SUM(D16:K16) -> 6250.8857
A17: 8 | B17: Paid through Paytm | C17: Rs crore | D17: =D16*Assumptions!$D$14 -> 23.856429 | E17: =E16*Assumptions!$D$14 -> 74.230714 | F17: =F16*Assumptions!$D$14 -> 153.78429 | G17: =G16*Assumptions!$D$14 -> 265.17857 | H17: =H16*Assumptions!$D$14 -> 411.075 | I17: =I16*Assumptions!$D$14 -> 565.84286 | J17: =J16*Assumptions!$D$14 -> 729.48214 | K17: =K16*Assumptions!$D$14 -> 901.99286 | L17: =SUM(D17:K17) -> 3125.4429
A18: 9 | B18: GMV: supplier payments new to Paytm | C18: Rs crore | D18: =D17*Assumptions!$D$15 -> 9.5425714 | E18: =E17*Assumptions!$D$15 -> 29.692286 | F18: =F17*Assumptions!$D$15 -> 61.513714 | G18: =G17*Assumptions!$D$15 -> 106.07143 | H18: =H17*Assumptions!$D$15 -> 164.43 | I18: =I17*Assumptions!$D$15 -> 226.33714 | J18: =J17*Assumptions!$D$15 -> 291.79286 | K18: =K17*Assumptions!$D$15 -> 360.79714 | L18: =SUM(D18:K18) -> 1250.1771
A19: 10 | B19: GMV: extra merchant sales on Paytm (fewer stock-outs) | C19: Rs crore | D19: =D13*Assumptions!$D$38*Assumptions!$D$39*3/100 -> 0.79521429 | E19: =E13*Assumptions!$D$38*Assumptions!$D$39*3/100 -> 2.4743571 | F19: =F13*Assumptions!$D$38*Assumptions!$D$39*3/100 -> 5.1261429 | G19: =G13*Assumptions!$D$38*Assumptions!$D$39*3/100 -> 8.8392857 | H19: =H13*Assumptions!$D$38*Assumptions!$D$39*3/100 -> 13.7025 | I19: =I13*Assumptions!$D$38*Assumptions!$D$39*3/100 -> 18.861429 | J19: =J13*Assumptions!$D$38*Assumptions!$D$39*3/100 -> 24.316071 | K19: =K13*Assumptions!$D$38*Assumptions!$D$39*3/100 -> 30.066429 | L19: =SUM(D19:K19) -> 104.18143
B20: Credit router (pay-later per order, plus working-capital loans)
A21: 11 | B21: Pay-later approved (30-day cycles) | C21: Rs crore | D21: =D16*Assumptions!$D$17*Assumptions!$D$18 -> 2.504925 | E21: =E16*Assumptions!$D$17*Assumptions!$D$18 -> 7.794225 | F21: =F16*Assumptions!$D$17*Assumptions!$D$18 -> 16.14735 | G21: =G16*Assumptions!$D$17*Assumptions!$D$18 -> 27.84375 | H21: =H16*Assumptions!$D$17*Assumptions!$D$18 -> 43.162875 | I21: =I16*Assumptions!$D$17*Assumptions!$D$18 -> 59.4135 | J21: =J16*Assumptions!$D$17*Assumptions!$D$18 -> 76.595625 | K21: =K16*Assumptions!$D$17*Assumptions!$D$18 -> 94.70925 | L21: =SUM(D21:K21) -> 328.1715
A22: 12 | B22: via Paytm partner lenders | C22: Rs crore | D22: =D21*Assumptions!$D$19 -> 1.1272163 | E22: =E21*Assumptions!$D$19 -> 3.5074013 | F22: =F21*Assumptions!$D$19 -> 7.2663075 | G22: =G21*Assumptions!$D$19 -> 12.529687 | H22: =H21*Assumptions!$D$19 -> 19.423294 | I22: =I21*Assumptions!$D$19 -> 26.736075 | J22: =J21*Assumptions!$D$19 -> 34.468031 | K22: =K21*Assumptions!$D$19 -> 42.619163 | L22: =SUM(D22:K22) -> 147.67718
A23: 13 | B23: via MUDRA credit line on UPI | C23: Rs crore | D23: =D21*Assumptions!$D$20 -> 0.62623125 | E23: =E21*Assumptions!$D$20 -> 1.9485562 | F23: =F21*Assumptions!$D$20 -> 4.0368375 | G23: =G21*Assumptions!$D$20 -> 6.9609375 | H23: =H21*Assumptions!$D$20 -> 10.790719 | I23: =I21*Assumptions!$D$20 -> 14.853375 | J23: =J21*Assumptions!$D$20 -> 19.148906 | K23: =K21*Assumptions!$D$20 -> 23.677312 | L23: =SUM(D23:K23) -> 82.042875
A24: 14 | B24: via OCEN | C24: Rs crore | D24: =D21*Assumptions!$D$21 -> 0.37573875 | E24: =E21*Assumptions!$D$21 -> 1.1691338 | F24: =F21*Assumptions!$D$21 -> 2.4221025 | G24: =G21*Assumptions!$D$21 -> 4.1765625 | H24: =H21*Assumptions!$D$21 -> 6.4744313 | I24: =I21*Assumptions!$D$21 -> 8.912025 | J24: =J21*Assumptions!$D$21 -> 11.489344 | K24: =K21*Assumptions!$D$21 -> 14.206387 | L24: =SUM(D24:K24) -> 49.225725
A25: 15 | B25: via ONDC Financial Services | C25: Rs crore | D25: =D21*Assumptions!$D$22 -> 0.37573875 | E25: =E21*Assumptions!$D$22 -> 1.1691338 | F25: =F21*Assumptions!$D$22 -> 2.4221025 | G25: =G21*Assumptions!$D$22 -> 4.1765625 | H25: =H21*Assumptions!$D$22 -> 6.4744313 | I25: =I21*Assumptions!$D$22 -> 8.912025 | J25: =J21*Assumptions!$D$22 -> 11.489344 | K25: =K21*Assumptions!$D$22 -> 14.206387 | L25: =SUM(D25:K25) -> 49.225725
A26: 16 | B26: Working-capital loans disbursed | C26: lakh loans | D26: =D13*Assumptions!$D$27/4 -> 0.00066267857 | E26: =E13*Assumptions!$D$27/4 -> 0.0020619643 | F26: =F13*Assumptions!$D$27/4 -> 0.0042717857 | G26: =G13*Assumptions!$D$27/4 -> 0.0073660714 | H26: =H13*Assumptions!$D$27/4 -> 0.01141875 | I26: =I13*Assumptions!$D$27/4 -> 0.015717857 | J26: =J13*Assumptions!$D$27/4 -> 0.020263393 | K26: =K13*Assumptions!$D$27/4 -> 0.025055357 | L26: =SUM(D26:K26) -> 0.086817857
A27: 17 | B27: Working-capital loan value | C27: Rs crore | D27: =D26*Assumptions!$D$28/100 -> 0.66267857 | E27: =E26*Assumptions!$D$28/100 -> 2.0619643 | F27: =F26*Assumptions!$D$28/100 -> 4.2717857 | G27: =G26*Assumptions!$D$28/100 -> 7.3660714 | H27: =H26*Assumptions!$D$28/100 -> 11.41875 | I27: =I26*Assumptions!$D$28/100 -> 15.717857 | J27: =J26*Assumptions!$D$28/100 -> 20.263393 | K27: =K26*Assumptions!$D$28/100 -> 25.055357 | L27: =SUM(D27:K27) -> 86.817857
A28: 18 | B28: Credit routed (pay-later + working capital) | C28: Rs crore | D28: =D21+D27 -> 3.1676036 | E28: =E21+E27 -> 9.8561893 | F28: =F21+F27 -> 20.419136 | G28: =G21+G27 -> 35.209821 | H28: =H21+H27 -> 54.581625 | I28: =I21+I27 -> 75.131357 | J28: =J21+J27 -> 96.859018 | K28: =K21+K27 -> 119.76461 | L28: =SUM(D28:K28) -> 414.98936
B29: Restock Agent: Paytm revenue, costs and contribution
A30: 19 | B30: Revenue: pay-later take | C30: Rs crore | D30: =D22*Assumptions!$D$23+D23*Assumptions!$D$24+D24*Assumptions!$D$25+D25*Assumptions!$D$26 -> 0.0048846037 | E30: =E22*Assumptions!$D$23+E23*Assumptions!$D$24+E24*Assumptions!$D$25+E25*Assumptions!$D$26 -> 0.015198739 | F30: =F22*Assumptions!$D$23+F23*Assumptions!$D$24+F24*Assumptions!$D$25+F25*Assumptions!$D$26 -> 0.031487332 | G30: =G22*Assumptions!$D$23+G23*Assumptions!$D$24+G24*Assumptions!$D$25+G25*Assumptions!$D$26 -> 0.054295312 | H30: =H22*Assumptions!$D$23+H23*Assumptions!$D$24+H24*Assumptions!$D$25+H25*Assumptions!$D$26 -> 0.084167606 | I30: =I22*Assumptions!$D$23+I23*Assumptions!$D$24+I24*Assumptions!$D$25+I25*Assumptions!$D$26 -> 0.11585632 | J30: =J22*Assumptions!$D$23+J23*Assumptions!$D$24+J24*Assumptions!$D$25+J25*Assumptions!$D$26 -> 0.14936147 | K30: =K22*Assumptions!$D$23+K23*Assumptions!$D$24+K24*Assumptions!$D$25+K25*Assumptions!$D$26 -> 0.18468304 | L30: =SUM(D30:K30) -> 0.63993442
A31: 20 | B31: Revenue: working-capital loans | C31: Rs crore | D31: =D27*Assumptions!$D$29 -> 0.013253571 | E31: =E27*Assumptions!$D$29 -> 0.041239286 | F31: =F27*Assumptions!$D$29 -> 0.085435714 | G31: =G27*Assumptions!$D$29 -> 0.14732143 | H31: =H27*Assumptions!$D$29 -> 0.228375 | I31: =I27*Assumptions!$D$29 -> 0.31435714 | J31: =J27*Assumptions!$D$29 -> 0.40526786 | K31: =K27*Assumptions!$D$29 -> 0.50110714 | L31: =SUM(D31:K31) -> 1.7363571
A32: 21 | B32: Revenue: MDR on supplier payments (switch R22) | C32: Rs crore | D32: =D18*Assumptions!$D$34*Assumptions!$D$35*Assumptions!$D$33 -> 0 | E32: =E18*Assumptions!$D$34*Assumptions!$D$35*Assumptions!$D$33 -> 0 | F32: =F18*Assumptions!$D$34*Assumptions!$D$35*Assumptions!$D$33 -> 0 | G32: =G18*Assumptions!$D$34*Assumptions!$D$35*Assumptions!$D$33 -> 0 | H32: =H18*Assumptions!$D$34*Assumptions!$D$35*Assumptions!$D$33 -> 0 | I32: =I18*Assumptions!$D$34*Assumptions!$D$35*Assumptions!$D$33 -> 0 | J32: =J18*Assumptions!$D$34*Assumptions!$D$35*Assumptions!$D$33 -> 0 | K32: =K18*Assumptions!$D$34*Assumptions!$D$35*Assumptions!$D$33 -> 0 | L32: =SUM(D32:K32) -> 0
A33: 22 | B33: Revenue: paid plan | C33: Rs crore | D33: =D13*Assumptions!$D$36*Assumptions!$D$37*3/100 -> 0.0077931 | E33: =E13*Assumptions!$D$36*Assumptions!$D$37*3/100 -> 0.0242487 | F33: =F13*Assumptions!$D$36*Assumptions!$D$37*3/100 -> 0.0502362 | G33: =G13*Assumptions!$D$36*Assumptions!$D$37*3/100 -> 0.086625 | H33: =H13*Assumptions!$D$36*Assumptions!$D$37*3/100 -> 0.1342845 | I33: =I13*Assumptions!$D$36*Assumptions!$D$37*3/100 -> 0.184842 | J33: =J13*Assumptions!$D$36*Assumptions!$D$37*3/100 -> 0.2382975 | K33: =K13*Assumptions!$D$36*Assumptions!$D$37*3/100 -> 0.294651 | L33: =SUM(D33:K33) -> 1.020978
A34: 23 | B34: Revenue: payment margin on extra sales | C34: Rs crore | D34: =D19*Assumptions!$D$6 -> 0.00031808571 | E34: =E19*Assumptions!$D$6 -> 0.00098974286 | F34: =F19*Assumptions!$D$6 -> 0.0020504571 | G34: =G19*Assumptions!$D$6 -> 0.0035357143 | H34: =H19*Assumptions!$D$6 -> 0.005481 | I34: =I19*Assumptions!$D$6 -> 0.0075445714 | J34: =J19*Assumptions!$D$6 -> 0.0097264286 | K34: =K19*Assumptions!$D$6 -> 0.012026571 | L34: =SUM(D34:K34) -> 0.041672571
A35: 24 | B35: Restock revenue | C35: Rs crore | D35: =SUM(D30:D34) -> 0.026249361 | E35: =SUM(E30:E34) -> 0.081676467 | F35: =SUM(F30:F34) -> 0.1692097 | G35: =SUM(G30:G34) -> 0.29177746 | H35: =SUM(H30:H34) -> 0.45230811 | I35: =SUM(I30:I34) -> 0.62260004 | J35: =SUM(J30:J34) -> 0.80265325 | K35: =SUM(K30:K34) -> 0.99246775 | L35: =SUM(D35:K35) -> 3.4389421
A36: 25 | B36: Cost: AI and Intent Guard checks | C36: Rs crore | D36: =D13*Assumptions!$D$41*3/100+D13*Assumptions!$D$36*Assumptions!$D$42*3/100 -> 0.043736786 | E36: =E13*Assumptions!$D$41*3/100+E13*Assumptions!$D$36*Assumptions!$D$42*3/100 -> 0.13608964 | F36: =F13*Assumptions!$D$41*3/100+F13*Assumptions!$D$36*Assumptions!$D$42*3/100 -> 0.28193786 | G36: =G13*Assumptions!$D$41*3/100+G13*Assumptions!$D$36*Assumptions!$D$42*3/100 -> 0.48616071 | H36: =H13*Assumptions!$D$41*3/100+H13*Assumptions!$D$36*Assumptions!$D$42*3/100 -> 0.7536375 | I36: =I13*Assumptions!$D$41*3/100+I13*Assumptions!$D$36*Assumptions!$D$42*3/100 -> 1.0373786 | J36: =J13*Assumptions!$D$41*3/100+J13*Assumptions!$D$36*Assumptions!$D$42*3/100 -> 1.3373839 | K36: =K13*Assumptions!$D$41*3/100+K13*Assumptions!$D$36*Assumptions!$D$42*3/100 -> 1.6536536 | L36: =SUM(D36:K36) -> 5.7299786
A37: 26 | B37: Cost: onboarding newly active merchants | C37: Rs crore | D37: =D14*Assumptions!$D$43/100 -> 0.21205714 | E37: =E14*Assumptions!$D$43/100 -> 0.44777143 | F37: =F14*Assumptions!$D$43/100 -> 0.70714286 | G37: =G14*Assumptions!$D$43/100 -> 0.99017143 | H37: =H14*Assumptions!$D$43/100 -> 1.2968571 | I37: =I14*Assumptions!$D$43/100 -> 1.3757143 | J37: =J14*Assumptions!$D$43/100 -> 1.4545714 | K37: =K14*Assumptions!$D$43/100 -> 1.5334286 | L37: =SUM(D37:K37) -> 8.0177143
A38: 27 | B38: Cost: support | C38: Rs crore | D38: =D13*Assumptions!$D$44*3/100 -> 0.031808571 | E38: =E13*Assumptions!$D$44*3/100 -> 0.098974286 | F38: =F13*Assumptions!$D$44*3/100 -> 0.20504571 | G38: =G13*Assumptions!$D$44*3/100 -> 0.35357143 | H38: =H13*Assumptions!$D$44*3/100 -> 0.5481 | I38: =I13*Assumptions!$D$44*3/100 -> 0.75445714 | J38: =J13*Assumptions!$D$44*3/100 -> 0.97264286 | K38: =K13*Assumptions!$D$44*3/100 -> 1.2026571 | L38: =SUM(D38:K38) -> 4.1672571
A39: 28 | B39: Cost: payment processing | C39: Rs crore | D39: =D18*Assumptions!$D$45 -> 0.0019085143 | E39: =E18*Assumptions!$D$45 -> 0.0059384571 | F39: =F18*Assumptions!$D$45 -> 0.012302743 | G39: =G18*Assumptions!$D$45 -> 0.021214286 | H39: =H18*Assumptions!$D$45 -> 0.032886 | I39: =I18*Assumptions!$D$45 -> 0.045267429 | J39: =J18*Assumptions!$D$45 -> 0.058358571 | K39: =K18*Assumptions!$D$45 -> 0.072159429 | L39: =SUM(D39:K39) -> 0.25003543
A40: 29 | B40: Cost: credit-loss sharing | C40: Rs crore | D40: =D22*Assumptions!$D$30+D27*Assumptions!$D$31 -> 0.012758219 | E40: =E22*Assumptions!$D$30+E27*Assumptions!$D$31 -> 0.039697967 | F40: =F22*Assumptions!$D$30+F27*Assumptions!$D$31 -> 0.082242554 | G40: =G22*Assumptions!$D$30+G27*Assumptions!$D$31 -> 0.14181529 | H40: =H22*Assumptions!$D$30+H27*Assumptions!$D$31 -> 0.21983948 | I40: =I22*Assumptions!$D$30+I27*Assumptions!$D$31 -> 0.30260804 | J40: =J22*Assumptions!$D$30+J27*Assumptions!$D$31 -> 0.39012097 | K40: =K22*Assumptions!$D$30+K27*Assumptions!$D$31 -> 0.48237826 | L40: =SUM(D40:K40) -> 1.6714608
A41: 30 | B41: Restock variable cost | C41: Rs crore | D41: =SUM(D36:D40) -> 0.30226923 | E41: =SUM(E36:E40) -> 0.72847178 | F41: =SUM(F36:F40) -> 1.2886717 | G41: =SUM(G36:G40) -> 1.9929331 | H41: =SUM(H36:H40) -> 2.8513201 | I41: =SUM(I36:I40) -> 3.5154255 | J41: =SUM(J36:J40) -> 4.2130778 | K41: =SUM(K36:K40) -> 4.944277 | L41: =SUM(D41:K41) -> 19.836446
A42: 31 | B42: Restock contribution | C42: Rs crore | D42: =D35-D41 -> -0.27601987 | E42: =E35-E41 -> -0.64679531 | F42: =F35-F41 -> -1.119462 | G42: =G35-G41 -> -1.7011557 | H42: =H35-H41 -> -2.399012 | I42: =I35-I41 -> -2.8928254 | J42: =J35-J41 -> -3.4104245 | K42: =K35-K41 -> -3.9518092 | L42: =SUM(D42:K42) -> -16.397504
A43: 32 | B43: Merchant money protected by Intent Guard | C43: Rs crore | D43: =D16*Assumptions!$D$49 -> 0.047712857 | E43: =E16*Assumptions!$D$49 -> 0.14846143 | F43: =F16*Assumptions!$D$49 -> 0.30756857 | G43: =G16*Assumptions!$D$49 -> 0.53035714 | H43: =H16*Assumptions!$D$49 -> 0.82215 | I43: =I16*Assumptions!$D$49 -> 1.1316857 | J43: =J16*Assumptions!$D$49 -> 1.4589643 | K43: =K16*Assumptions!$D$49 -> 1.8039857 | L43: =SUM(D43:K43) -> 6.2508857
B44: Soundbox Care
A45: 33 | B45: Care coverage of the device base | C45: % of devices | D45: =Assumptions!D$80 -> 0.05 | E45: =Assumptions!E$80 -> 0.15 | F45: =Assumptions!F$80 -> 0.3 | G45: =Assumptions!G$80 -> 0.45 | H45: =Assumptions!H$80 -> 0.6 | I45: =Assumptions!I$80 -> 0.7 | J45: =Assumptions!J$80 -> 0.8 | K45: =Assumptions!K$80 -> 0.85 | L45: =K45 -> 0.85
A46: 34 | B46: Devices covered | C46: lakh | D46: =D10*D45 -> 8.8357143 | E46: =E10*E45 -> 27.492857 | F46: =F10*F45 -> 56.957143 | G46: =G10*G45 -> 88.392857 | H46: =H10*H45 -> 121.8 | I46: =I10*I45 -> 146.7 | J46: =J10*J45 -> 172.91429 | K46: =K10*K45 -> 189.30714 | L46: =K46 -> 189.30714
A47: 35 | B47: Incidents on covered devices | C47: lakh | D47: =D46*Assumptions!$D$51/100/4 -> 0.88357143 | E47: =E46*Assumptions!$D$51/100/4 -> 2.7492857 | F47: =F46*Assumptions!$D$51/100/4 -> 5.6957143 | G47: =G46*Assumptions!$D$51/100/4 -> 8.8392857 | H47: =H46*Assumptions!$D$51/100/4 -> 12.18 | I47: =I46*Assumptions!$D$51/100/4 -> 14.67 | J47: =J46*Assumptions!$D$51/100/4 -> 17.291429 | K47: =K46*Assumptions!$D$51/100/4 -> 18.930714 | L47: =SUM(D47:K47) -> 81.24
A48: 36 | B48: Field visits avoided | C48: lakh | D48: =D47*Assumptions!$D$52*Assumptions!$D$53 -> 0.079521429 | E48: =E47*Assumptions!$D$52*Assumptions!$D$53 -> 0.24743571 | F48: =F47*Assumptions!$D$52*Assumptions!$D$53 -> 0.51261429 | G48: =G47*Assumptions!$D$52*Assumptions!$D$53 -> 0.79553571 | H48: =H47*Assumptions!$D$52*Assumptions!$D$53 -> 1.0962 | I48: =I47*Assumptions!$D$52*Assumptions!$D$53 -> 1.3203 | J48: =J47*Assumptions!$D$52*Assumptions!$D$53 -> 1.5562286 | K48: =K47*Assumptions!$D$52*Assumptions!$D$53 -> 1.7037643 | L48: =SUM(D48:K48) -> 7.3116
A49: 37 | B49: Replacements avoided | C49: lakh | D49: =D47*Assumptions!$D$55*Assumptions!$D$56 -> 0.011044643 | E49: =E47*Assumptions!$D$55*Assumptions!$D$56 -> 0.034366071 | F49: =F47*Assumptions!$D$55*Assumptions!$D$56 -> 0.071196429 | G49: =G47*Assumptions!$D$55*Assumptions!$D$56 -> 0.11049107 | H49: =H47*Assumptions!$D$55*Assumptions!$D$56 -> 0.15225 | I49: =I47*Assumptions!$D$55*Assumptions!$D$56 -> 0.183375 | J49: =J47*Assumptions!$D$55*Assumptions!$D$56 -> 0.21614286 | K49: =K47*Assumptions!$D$55*Assumptions!$D$56 -> 0.23663393 | L49: =SUM(D49:K49) -> 1.0155
A50: 38 | B50: Device-days of downtime avoided | C50: lakh days | D50: =D47*Assumptions!$D$58*Assumptions!$D$59 -> 0.88357143 | E50: =E47*Assumptions!$D$58*Assumptions!$D$59 -> 2.7492857 | F50: =F47*Assumptions!$D$58*Assumptions!$D$59 -> 5.6957143 | G50: =G47*Assumptions!$D$58*Assumptions!$D$59 -> 8.8392857 | H50: =H47*Assumptions!$D$58*Assumptions!$D$59 -> 12.18 | I50: =I47*Assumptions!$D$58*Assumptions!$D$59 -> 14.67 | J50: =J47*Assumptions!$D$58*Assumptions!$D$59 -> 17.291429 | K50: =K47*Assumptions!$D$58*Assumptions!$D$59 -> 18.930714 | L50: =SUM(D50:K50) -> 81.24
A51: 39 | B51: GMV: kept during downtime | C51: Rs crore | D51: =D50*Assumptions!$D$7/30*Assumptions!$D$60/100 -> 1.472619 | E51: =E50*Assumptions!$D$7/30*Assumptions!$D$60/100 -> 4.5821429 | F51: =F50*Assumptions!$D$7/30*Assumptions!$D$60/100 -> 9.4928571 | G51: =G50*Assumptions!$D$7/30*Assumptions!$D$60/100 -> 14.732143 | H51: =H50*Assumptions!$D$7/30*Assumptions!$D$60/100 -> 20.3 | I51: =I50*Assumptions!$D$7/30*Assumptions!$D$60/100 -> 24.45 | J51: =J50*Assumptions!$D$7/30*Assumptions!$D$60/100 -> 28.819048 | K51: =K50*Assumptions!$D$7/30*Assumptions!$D$60/100 -> 31.55119 | L51: =SUM(D51:K51) -> 135.4
A52: 40 | B52: Devices kept by Care (cumulative) | C52: lakh | D52: =N(C52)+D47*Assumptions!$D$61*Assumptions!$D$62 -> 0.010602857 | E52: =N(D52)+E47*Assumptions!$D$61*Assumptions!$D$62 -> 0.043594286 | F52: =N(E52)+F47*Assumptions!$D$61*Assumptions!$D$62 -> 0.11194286 | G52: =N(F52)+G47*Assumptions!$D$61*Assumptions!$D$62 -> 0.21801429 | H52: =N(G52)+H47*Assumptions!$D$61*Assumptions!$D$62 -> 0.36417429 | I52: =N(H52)+I47*Assumptions!$D$61*Assumptions!$D$62 -> 0.54021429 | J52: =N(I52)+J47*Assumptions!$D$61*Assumptions!$D$62 -> 0.74771143 | K52: =N(J52)+K47*Assumptions!$D$61*Assumptions!$D$62 -> 0.97488 | L52: =K52 -> 0.97488
A53: 41 | B53: GMV: kept by lower device churn | C53: Rs crore | D53: =D52*Assumptions!$D$7*3/100 -> 15.904286 | E53: =E52*Assumptions!$D$7*3/100 -> 65.391429 | F53: =F52*Assumptions!$D$7*3/100 -> 167.91429 | G53: =G52*Assumptions!$D$7*3/100 -> 327.02143 | H53: =H52*Assumptions!$D$7*3/100 -> 546.26143 | I53: =I52*Assumptions!$D$7*3/100 -> 810.32143 | J53: =J52*Assumptions!$D$7*3/100 -> 1121.5671 | K53: =K52*Assumptions!$D$7*3/100 -> 1462.32 | L53: =SUM(D53:K53) -> 4516.7014
A54: 42 | B54: Revenue: device subscriptions kept | C54: Rs crore | D54: =D52*Assumptions!$D$8*3/100 -> 0.025446857 | E54: =E52*Assumptions!$D$8*3/100 -> 0.10462629 | F54: =F52*Assumptions!$D$8*3/100 -> 0.26866286 | G54: =G52*Assumptions!$D$8*3/100 -> 0.52323429 | H54: =H52*Assumptions!$D$8*3/100 -> 0.87401829 | I54: =I52*Assumptions!$D$8*3/100 -> 1.2965143 | J54: =J52*Assumptions!$D$8*3/100 -> 1.7945074 | K54: =K52*Assumptions!$D$8*3/100 -> 2.339712 | L54: =SUM(D54:K54) -> 7.2267223
A55: 43 | B55: Revenue: payment margin on GMV kept | C55: Rs crore | D55: =(D51+D53)*Assumptions!$D$6 -> 0.0069507619 | E55: =(E51+E53)*Assumptions!$D$6 -> 0.027989429 | F55: =(F51+F53)*Assumptions!$D$6 -> 0.070962857 | G55: =(G51+G53)*Assumptions!$D$6 -> 0.13670143 | H55: =(H51+H53)*Assumptions!$D$6 -> 0.22662457 | I55: =(I51+I53)*Assumptions!$D$6 -> 0.33390857 | J55: =(J51+J53)*Assumptions!$D$6 -> 0.46015448 | K55: =(K51+K53)*Assumptions!$D$6 -> 0.59754848 | L55: =SUM(D55:K55) -> 1.8608406
A56: 44 | B56: Care revenue | C56: Rs crore | D56: =D54+D55 -> 0.032397619 | E56: =E54+E55 -> 0.13261571 | F56: =F54+F55 -> 0.33962571 | G56: =G54+G55 -> 0.65993571 | H56: =H54+H55 -> 1.1006429 | I56: =I54+I55 -> 1.6304229 | J56: =J54+J55 -> 2.2546619 | K56: =K54+K55 -> 2.9372605 | L56: =SUM(D56:K56) -> 9.0875629
A57: 45 | B57: Saving: field visits avoided | C57: Rs crore | D57: =D48*Assumptions!$D$54/100 -> 0.278325 | E57: =E48*Assumptions!$D$54/100 -> 0.866025 | F57: =F48*Assumptions!$D$54/100 -> 1.79415 | G57: =G48*Assumptions!$D$54/100 -> 2.784375 | H57: =H48*Assumptions!$D$54/100 -> 3.8367 | I57: =I48*Assumptions!$D$54/100 -> 4.62105 | J57: =J48*Assumptions!$D$54/100 -> 5.4468 | K57: =K48*Assumptions!$D$54/100 -> 5.963175 | L57: =SUM(D57:K57) -> 25.5906
A58: 46 | B58: Saving: replacements avoided | C58: Rs crore | D58: =D49*Assumptions!$D$57/100 -> 0.16566964 | E58: =E49*Assumptions!$D$57/100 -> 0.51549107 | F58: =F49*Assumptions!$D$57/100 -> 1.0679464 | G58: =G49*Assumptions!$D$57/100 -> 1.6573661 | H58: =H49*Assumptions!$D$57/100 -> 2.28375 | I58: =I49*Assumptions!$D$57/100 -> 2.750625 | J58: =J49*Assumptions!$D$57/100 -> 3.2421429 | K58: =K49*Assumptions!$D$57/100 -> 3.5495089 | L58: =SUM(D58:K58) -> 15.2325
A59: 47 | B59: Care savings (avoided costs) | C59: Rs crore | D59: =D57+D58 -> 0.44399464 | E59: =E57+E58 -> 1.3815161 | F59: =F57+F58 -> 2.8620964 | G59: =G57+G58 -> 4.4417411 | H59: =H57+H58 -> 6.12045 | I59: =I57+I58 -> 7.371675 | J59: =J57+J58 -> 8.6889429 | K59: =K57+K58 -> 9.5126839 | L59: =SUM(D59:K59) -> 40.8231
A60: 48 | B60: Care variable cost (telemetry, phone fallback) | C60: Rs crore | D60: =D46*Assumptions!$D$63*3/100+D47*Assumptions!$D$64/100 -> 0.66267857 | E60: =E46*Assumptions!$D$63*3/100+E47*Assumptions!$D$64/100 -> 2.0619643 | F60: =F46*Assumptions!$D$63*3/100+F47*Assumptions!$D$64/100 -> 4.2717857 | G60: =G46*Assumptions!$D$63*3/100+G47*Assumptions!$D$64/100 -> 6.6294643 | H60: =H46*Assumptions!$D$63*3/100+H47*Assumptions!$D$64/100 -> 9.135 | I60: =I46*Assumptions!$D$63*3/100+I47*Assumptions!$D$64/100 -> 11.0025 | J60: =J46*Assumptions!$D$63*3/100+J47*Assumptions!$D$64/100 -> 12.968571 | K60: =K46*Assumptions!$D$63*3/100+K47*Assumptions!$D$64/100 -> 14.198036 | L60: =SUM(D60:K60) -> 60.93
A61: 49 | B61: Care contribution | C61: Rs crore | D61: =D56+D59-D60 -> -0.18628631 | E61: =E56+E59-E60 -> -0.5478325 | F61: =F56+F59-F60 -> -1.0700636 | G61: =G56+G59-G60 -> -1.5277875 | H61: =H56+H59-H60 -> -1.9139071 | I61: =I56+I59-I60 -> -2.0004021 | J61: =J56+J59-J60 -> -2.0249667 | K61: =K56+K59-K60 -> -1.7480913 | L61: =SUM(D61:K61) -> -11.019337
B62: Nearby (Phase 2): computed for reference, counted only if switch N0 = 1
A63: 50 | B63: Nearby coverage | C63: % of eligible | D63: =Assumptions!D$81 -> 0 | E63: =Assumptions!E$81 -> 0.05 | F63: =Assumptions!F$81 -> 0.15 | G63: =Assumptions!G$81 -> 0.25 | H63: =Assumptions!H$81 -> 0.35 | I63: =Assumptions!I$81 -> 0.45 | J63: =Assumptions!J$81 -> 0.55 | K63: =Assumptions!K$81 -> 0.6 | L63: =K63 -> 0.6
A64: 51 | B64: Nearby merchants | C64: lakh | D64: =D10*Assumptions!$D$67*D63*Assumptions!$D$68 -> 0 | E64: =E10*Assumptions!$D$67*E63*Assumptions!$D$68 -> 0.091642857 | F64: =F10*Assumptions!$D$67*F63*Assumptions!$D$68 -> 0.28478571 | G64: =G10*Assumptions!$D$67*G63*Assumptions!$D$68 -> 0.49107143 | H64: =H10*Assumptions!$D$67*H63*Assumptions!$D$68 -> 0.7105 | I64: =I10*Assumptions!$D$67*I63*Assumptions!$D$68 -> 0.94307143 | J64: =J10*Assumptions!$D$67*J63*Assumptions!$D$68 -> 1.1887857 | K64: =K10*Assumptions!$D$67*K63*Assumptions!$D$68 -> 1.3362857 | L64: =K64 -> 1.3362857
A65: 52 | B65: Verified new customers | C65: lakh | D65: =D64*Assumptions!$D$69*3 -> 0 | E65: =E64*Assumptions!$D$69*3 -> 0.54985714 | F65: =F64*Assumptions!$D$69*3 -> 1.7087143 | G65: =G64*Assumptions!$D$69*3 -> 2.9464286 | H65: =H64*Assumptions!$D$69*3 -> 4.263 | I65: =I64*Assumptions!$D$69*3 -> 5.6584286 | J65: =J64*Assumptions!$D$69*3 -> 7.1327143 | K65: =K64*Assumptions!$D$69*3 -> 8.0177143 | L65: =SUM(D65:K65) -> 30.276857
A66: 53 | B66: GMV new to Paytm | C66: Rs crore | D66: =D65*Assumptions!$D$70/100*Assumptions!$D$71 -> 0 | E66: =E65*Assumptions!$D$70/100*Assumptions!$D$71 -> 0.41239286 | F66: =F65*Assumptions!$D$70/100*Assumptions!$D$71 -> 1.2815357 | G66: =G65*Assumptions!$D$70/100*Assumptions!$D$71 -> 2.2098214 | H66: =H65*Assumptions!$D$70/100*Assumptions!$D$71 -> 3.19725 | I66: =I65*Assumptions!$D$70/100*Assumptions!$D$71 -> 4.2438214 | J66: =J65*Assumptions!$D$70/100*Assumptions!$D$71 -> 5.3495357 | K66: =K65*Assumptions!$D$70/100*Assumptions!$D$71 -> 6.0132857 | L66: =SUM(D66:K66) -> 22.707643
A67: 54 | B67: Revenue: fees and payment margin | C67: Rs crore | D67: =D65*Assumptions!$D$72/100+D66*Assumptions!$D$6 -> 0 | E67: =E65*Assumptions!$D$72/100+E66*Assumptions!$D$6 -> 0.044153529 | F67: =F65*Assumptions!$D$72/100+F66*Assumptions!$D$6 -> 0.13720976 | G67: =G65*Assumptions!$D$72/100+G66*Assumptions!$D$6 -> 0.23659821 | H67: =H65*Assumptions!$D$72/100+H66*Assumptions!$D$6 -> 0.3423189 | I67: =I65*Assumptions!$D$72/100+I66*Assumptions!$D$6 -> 0.45437181 | J67: =J65*Assumptions!$D$72/100+J66*Assumptions!$D$6 -> 0.57275696 | K67: =K65*Assumptions!$D$72/100+K66*Assumptions!$D$6 -> 0.64382246 | L67: =SUM(D67:K67) -> 2.4312316
A68: 55 | B68: Saving: Paytm-funded cashback replaced | C68: Rs crore | D68: =D65*Assumptions!$D$73/100 -> 0 | E68: =E65*Assumptions!$D$73/100 -> 0.027492857 | F68: =F65*Assumptions!$D$73/100 -> 0.085435714 | G68: =G65*Assumptions!$D$73/100 -> 0.14732143 | H68: =H65*Assumptions!$D$73/100 -> 0.21315 | I68: =I65*Assumptions!$D$73/100 -> 0.28292143 | J68: =J65*Assumptions!$D$73/100 -> 0.35663571 | K68: =K65*Assumptions!$D$73/100 -> 0.40088571 | L68: =SUM(D68:K68) -> 1.5138429
A69: 56 | B69: Variable cost | C69: Rs crore | D69: =D64*Assumptions!$D$74*3/100+D65*Assumptions!$D$75/100 -> 0 | E69: =E64*Assumptions!$D$74*3/100+E65*Assumptions!$D$75/100 -> 0.03849 | F69: =F64*Assumptions!$D$74*3/100+F65*Assumptions!$D$75/100 -> 0.11961 | G69: =G64*Assumptions!$D$74*3/100+G65*Assumptions!$D$75/100 -> 0.20625 | H69: =H64*Assumptions!$D$74*3/100+H65*Assumptions!$D$75/100 -> 0.29841 | I69: =I64*Assumptions!$D$74*3/100+I65*Assumptions!$D$75/100 -> 0.39609 | J69: =J64*Assumptions!$D$74*3/100+J65*Assumptions!$D$75/100 -> 0.49929 | K69: =K64*Assumptions!$D$74*3/100+K65*Assumptions!$D$75/100 -> 0.56124 | L69: =SUM(D69:K69) -> 2.11938
A70: 57 | B70: Nearby contribution if switched on | C70: Rs crore | D70: =D67+D68-D69 -> 0 | E70: =E67+E68-E69 -> 0.033156386 | F70: =F67+F68-F69 -> 0.10303547 | G70: =G67+G68-G69 -> 0.17766964 | H70: =H67+H68-H69 -> 0.2570589 | I70: =I67+I68-I69 -> 0.34120324 | J70: =J67+J68-J69 -> 0.43010267 | K70: =K67+K68-K69 -> 0.48346817 | L70: =SUM(D70:K70) -> 1.8256945
B71: Bundle totals
A72: 58 | B72: Incremental GMV | C72: Rs crore | D72: =D18+D19+D51+D53+D66*Assumptions!$D$66 -> 27.71469 | E72: =E18+E19+E51+E53+E66*Assumptions!$D$66 -> 102.14021 | F72: =F18+F19+F51+F53+F66*Assumptions!$D$66 -> 244.047 | G72: =G18+G19+G51+G53+G66*Assumptions!$D$66 -> 456.66429 | H72: =H18+H19+H51+H53+H66*Assumptions!$D$66 -> 744.69393 | I72: =I18+I19+I51+I53+I66*Assumptions!$D$66 -> 1079.97 | J72: =J18+J19+J51+J53+J66*Assumptions!$D$66 -> 1466.4951 | K72: =K18+K19+K51+K53+K66*Assumptions!$D$66 -> 1884.7348 | L72: =SUM(D72:K72) -> 6006.46
A73: 59 | B73: Incremental GMV | C73: Rs lakh crore | D73: =D72/100000 -> 0.0002771469 | E73: =E72/100000 -> 0.0010214021 | F73: =F72/100000 -> 0.00244047 | G73: =G72/100000 -> 0.0045666429 | H73: =H72/100000 -> 0.0074469393 | I73: =I72/100000 -> 0.0107997 | J73: =J72/100000 -> 0.014664951 | K73: =K72/100000 -> 0.018847348 | L73: =SUM(D73:K73) -> 0.0600646
A74: 60 | B74: Baseline Paytm merchant GMV (FORECAST) | C74: Rs lakh crore | D74: =Baseline!E15 -> 7.9486905 | E74: =Baseline!E16 -> 8.2971429 | F74: =Baseline!E17 -> 8.6455952 | G74: =Baseline!E18 -> 8.9940476 | H74: =Baseline!E19 -> 9.3425 | I74: =Baseline!E20 -> 9.6909524 | J74: =Baseline!E21 -> 10.039405 | K74: =Baseline!E22 -> 10.387857 | L74: =SUM(D74:K74) -> 73.34619
A75: 61 | B75: Uplift vs baseline GMV | C75: % | D75: =IF(D74>0,D73/D74,0) -> 3.4866989e-05 | E75: =IF(E74>0,E73/E74,0) -> 0.00012310288 | F75: =IF(F74>0,F73/F74,0) -> 0.000282279 | G75: =IF(G74>0,G73/G74,0) -> 0.00050774057 | H75: =IF(H74>0,H73/H74,0) -> 0.00079710348 | I75: =IF(I74>0,I73/I74,0) -> 0.0011144106 | J75: =IF(J74>0,J73/J74,0) -> 0.0014607391 | K75: =IF(K74>0,K73/K74,0) -> 0.0018143634 | L75: =IF(L74>0,L73/L74,0) -> 0.00081891915
A76: 62 | B76: Revenue | C76: Rs crore | D76: =D35+D56+D67*Assumptions!$D$66 -> 0.05864698 | E76: =E35+E56+E67*Assumptions!$D$66 -> 0.21429218 | F76: =F35+F56+F67*Assumptions!$D$66 -> 0.50883542 | G76: =G35+G56+G67*Assumptions!$D$66 -> 0.95171317 | H76: =H35+H56+H67*Assumptions!$D$66 -> 1.552951 | I76: =I35+I56+I67*Assumptions!$D$66 -> 2.2530229 | J76: =J35+J56+J67*Assumptions!$D$66 -> 3.0573152 | K76: =K35+K56+K67*Assumptions!$D$66 -> 3.9297282 | L76: =SUM(D76:K76) -> 12.526505
A77: 63 | B77: Variable cost | C77: Rs crore | D77: =D41+D60+D69*Assumptions!$D$66 -> 0.9649478 | E77: =E41+E60+E69*Assumptions!$D$66 -> 2.7904361 | F77: =F41+F60+F69*Assumptions!$D$66 -> 5.5604574 | G77: =G41+G60+G69*Assumptions!$D$66 -> 8.6223974 | H77: =H41+H60+H69*Assumptions!$D$66 -> 11.98632 | I77: =I41+I60+I69*Assumptions!$D$66 -> 14.517925 | J77: =J41+J60+J69*Assumptions!$D$66 -> 17.181649 | K77: =K41+K60+K69*Assumptions!$D$66 -> 19.142313 | L77: =SUM(D77:K77) -> 80.766446
A78: 64 | B78: Avoided costs | C78: Rs crore | D78: =D59+D68*Assumptions!$D$66 -> 0.44399464 | E78: =E59+E68*Assumptions!$D$66 -> 1.3815161 | F78: =F59+F68*Assumptions!$D$66 -> 2.8620964 | G78: =G59+G68*Assumptions!$D$66 -> 4.4417411 | H78: =H59+H68*Assumptions!$D$66 -> 6.12045 | I78: =I59+I68*Assumptions!$D$66 -> 7.371675 | J78: =J59+J68*Assumptions!$D$66 -> 8.6889429 | K78: =K59+K68*Assumptions!$D$66 -> 9.5126839 | L78: =SUM(D78:K78) -> 40.8231
A79: 65 | B79: Contribution to Paytm | C79: Rs crore | D79: =D76-D77+D78 -> -0.46230618 | E79: =E76-E77+E78 -> -1.1946278 | F79: =F76-F77+F78 -> -2.1895256 | G79: =G76-G77+G78 -> -3.2289432 | H79: =H76-H77+H78 -> -4.3129192 | I79: =I76-I77+I78 -> -4.8932276 | J79: =J76-J77+J78 -> -5.4353912 | K79: =K76-K77+K78 -> -5.6999005 | L79: =SUM(D79:K79) -> -27.416841
A80: 66 | B80: Contribution margin on revenue (before avoided costs) | C80: % | D80: =IF(D76>0,(D76-D77)/D76,0) -> -15.453495 | E80: =IF(E76>0,(E76-E77)/E76,0) -> -12.021642 | F80: =IF(F76>0,(F76-F77)/F76,0) -> -9.9278113 | G80: =IF(G76>0,(G76-G77)/G76,0) -> -8.0598698 | H80: =IF(H76>0,(H76-H77)/H76,0) -> -6.7184151 | I80: =IF(I76>0,(I76-I77)/I76,0) -> -5.4437541 | J80: =IF(J76>0,(J76-J77)/J76,0) -> -4.6198489 | K80: =IF(K76>0,(K76-K77)/K76,0) -> -3.8711543 | L80: =IF(L76>0,(L76-L77)/L76,0) -> -5.4476441
A81: 67 | B81: Contribution as % of revenue plus avoided costs | C81: % | D81: =IF((D76+D78)>0,D79/(D76+D78),0) -> -0.91975308 | E81: =IF((E76+E78)>0,E79/(E76+E78),0) -> -0.74860361 | F81: =IF((F76+F78)>0,F79/(F76+F78),0) -> -0.64953126 | G81: =IF((G76+G78)>0,G79/(G76+G78),0) -> -0.59867815 | H81: =IF((H76+H78)>0,H79/(H76+H78),0) -> -0.56206097 | I81: =IF((I76+I78)>0,I79/(I76+I78),0) -> -0.50840324 | J81: =IF((J76+J78)>0,J79/(J76+J78),0) -> -0.46273385 | K81: =IF((K76+K78)>0,K79/(K76+K78),0) -> -0.42402364 | L81: =IF((L76+L78)>0,L79/(L76+L78),0) -> -0.51390898
A82: 68 | B82: Restock margin on Restock revenue | C82: % | D82: =IF(D35>0,D42/D35,0) -> -10.515299 | E82: =IF(E35>0,E42/E35,0) -> -7.9189923 | F82: =IF(F35>0,F42/F35,0) -> -6.6158264 | G82: =IF(G35>0,G42/G35,0) -> -5.8303192 | H82: =IF(H35>0,H42/H35,0) -> -5.3039333 | I82: =IF(I35>0,I42/I35,0) -> -4.6463624 | J82: =IF(J35>0,J42/J35,0) -> -4.2489387 | K82: =IF(K35>0,K42/K35,0) -> -3.9818011 | L82: =IF(L35>0,L42/L35,0) -> -4.7681826
A83: 69 | B83: Care: avoided costs plus revenue per Rs 1 of Care cost | C83: x | D83: =IF(D60>0,(D59+D56)/D60,0) -> 0.71888889 | E83: =IF(E60>0,(E59+E56)/E60,0) -> 0.73431523 | F83: =IF(F60>0,(F59+F56)/F60,0) -> 0.74950439 | G83: =IF(G60>0,(G59+G56)/G60,0) -> 0.76954586 | H83: =IF(H60>0,(H59+H56)/H60,0) -> 0.79048636 | I83: =IF(I60>0,(I59+I56)/I60,0) -> 0.81818658 | J83: =IF(J60>0,(J59+J56)/J60,0) -> 0.84385584 | K83: =IF(K60>0,(K59+K56)/K60,0) -> 0.87687795 | L83: =IF(L60>0,(L59+L56)/L60,0) -> 0.81914759
A84: 70 | B84: Share of incremental GMV from supplier payments | C84: % | D84: =IF(D72>0,D18/D72,0) -> 0.34431456 | E84: =IF(E72>0,E18/E72,0) -> 0.29070123 | F84: =IF(F72>0,F18/F72,0) -> 0.25205683 | G84: =IF(G72>0,G18/G72,0) -> 0.23227441 | H84: =IF(H72>0,H18/H72,0) -> 0.22080212 | I84: =IF(I72>0,I18/I72,0) -> 0.20957725 | J84: =IF(J72>0,J18/J72,0) -> 0.19897295 | K84: =IF(K72>0,K18/K72,0) -> 0.19143126 | L84: =IF(L72>0,L18/L72,0) -> 0.20813876
A85: 71 | B85: Contribution per device merchant per month | C85: Rs / month | D85: =IF(D10>0,D79*100/D10/3,0) -> -0.087204076 | E85: =IF(E10>0,E79*100/E10/3,0) -> -0.21726149 | F85: =IF(F10>0,F79*100/F10/3,0) -> -0.38441633 | G85: =IF(G10>0,G79*100/G10/3,0) -> -0.54794188 | H85: =IF(H10>0,H79*100/H10/3,0) -> -0.70819691 | I85: =IF(I10>0,I79*100/I10/3,0) -> -0.77829114 | J85: =IF(J10>0,J79*100/J10/3,0) -> -0.83824054 | K85: =IF(K10>0,K79*100/K10/3,0) -> -0.85309608 | L85: =K85 -> -0.85309608
A86: 72 | B86: Quarterly contribution vs Q1 FY27 EBITDA | C86: % | D86: =D79/Baseline!$F$29 -> -0.0022773704 | E86: =E79/Baseline!$F$29 -> -0.0058848661 | F86: =F79/Baseline!$F$29 -> -0.01078584 | G86: =G79/Baseline!$F$29 -> -0.015906124 | H86: =H79/Baseline!$F$29 -> -0.021245907 | I86: =I79/Baseline!$F$29 -> -0.024104569 | J86: =J79/Baseline!$F$29 -> -0.026775326 | K86: =K79/Baseline!$F$29 -> -0.028078328 | L86: =K86 -> -0.028078328
A87: 73 | B87: Quarterly contribution vs Q1 FY27 contribution profit | C87: % | D87: =D79/Baseline!$F$27 -> -0.00034244902 | E87: =E79/Baseline!$F$27 -> -0.00088490949 | F87: =F79/Baseline!$F$27 -> -0.0016218708 | G87: =G79/Baseline!$F$27 -> -0.0023918098 | H87: =H79/Baseline!$F$27 -> -0.0031947549 | I87: =I79/Baseline!$F$27 -> -0.003624613 | J87: =J79/Baseline!$F$27 -> -0.0040262157 | K87: =K79/Baseline!$F$27 -> -0.0042221485 | L87: =K87 -> -0.0042221485
A88: 74 | B88: Restock credit revenue vs Q1 FY27 financial services revenue | C88: % | D88: =(D30+D31)/Baseline!$F$31 -> 2.228277e-05 | E88: =(E30+E31)/Baseline!$F$31 -> 6.9334182e-05 | F88: =(F30+F31)/Baseline!$F$31 -> 0.00014364011 | G88: =(G30+G31)/Baseline!$F$31 -> 0.00024768641 | H88: =(H30+H31)/Baseline!$F$31 -> 0.00038395898 | I88: =(I30+I31)/Baseline!$F$31 -> 0.00052851777 | J88: =(J30+J31)/Baseline!$F$31 -> 0.00068136281 | K88: =(K30+K31)/Baseline!$F$31 -> 0.00084249408 | L88: =K88 -> 0.00084249408
B89: North Star and unit economics
A90: 75 | B90: Paytm sales per active Restock merchant per month, before | C90: Rs / month | D90: =Assumptions!$D$38 -> 50000 | E90: =Assumptions!$D$38 -> 50000 | F90: =Assumptions!$D$38 -> 50000 | G90: =Assumptions!$D$38 -> 50000 | H90: =Assumptions!$D$38 -> 50000 | I90: =Assumptions!$D$38 -> 50000 | J90: =Assumptions!$D$38 -> 50000 | K90: =Assumptions!$D$38 -> 50000 | L90: =K90 -> 50000
A91: 76 | B91: New Paytm GMV per active Restock merchant per month (supplier payments + extra sales) | C91: Rs / month | D91: =IF(D13>0,(D18+D19)*100/D13/3,0) -> 6500 | E91: =IF(E13>0,(E18+E19)*100/E13/3,0) -> 6500 | F91: =IF(F13>0,(F18+F19)*100/F13/3,0) -> 6500 | G91: =IF(G13>0,(G18+G19)*100/G13/3,0) -> 6500 | H91: =IF(H13>0,(H18+H19)*100/H13/3,0) -> 6500 | I91: =IF(I13>0,(I18+I19)*100/I13/3,0) -> 6500 | J91: =IF(J13>0,(J18+J19)*100/J13/3,0) -> 6500 | K91: =IF(K13>0,(K18+K19)*100/K13/3,0) -> 6500 | L91: =K91 -> 6500
A92: 77 | B92: North Star uplift per active Restock merchant | C92: % | D92: =IF(D90>0,D91/D90,0) -> 0.13 | E92: =IF(E90>0,E91/E90,0) -> 0.13 | F92: =IF(F90>0,F91/F90,0) -> 0.13 | G92: =IF(G90>0,G91/G90,0) -> 0.13 | H92: =IF(H90>0,H91/H90,0) -> 0.13 | I92: =IF(I90>0,I91/I90,0) -> 0.13 | J92: =IF(J90>0,J91/J90,0) -> 0.13 | K92: =IF(K90>0,K91/K90,0) -> 0.13 | L92: =K92 -> 0.13
A93: 78 | B93: Restock contribution per active merchant per month, before onboarding | C93: Rs / month | D93: =IF(D13>0,(D35-(D41-D37))*100/D13/3,0) -> -40.217292 | E93: =IF(E13>0,(E35-(E41-E37))*100/E13/3,0) -> -40.217292 | F93: =IF(F13>0,(F35-(F41-F37))*100/F13/3,0) -> -40.217292 | G93: =IF(G13>0,(G35-(G41-G37))*100/G13/3,0) -> -40.217292 | H93: =IF(H13>0,(H35-(H41-H37))*100/H13/3,0) -> -40.217292 | I93: =IF(I13>0,(I35-(I41-I37))*100/I13/3,0) -> -40.217292 | J93: =IF(J13>0,(J35-(J41-J37))*100/J13/3,0) -> -40.217292 | K93: =IF(K13>0,(K35-(K41-K37))*100/K13/3,0) -> -40.217292 | L93: =K93 -> -40.217292
A94: 79 | B94: Months to recover onboarding cost | C94: months | D94: =IF(D93>0,Assumptions!$D$43/D93,"never") -> never | E94: =IF(E93>0,Assumptions!$D$43/E93,"never") -> never | F94: =IF(F93>0,Assumptions!$D$43/F93,"never") -> never | G94: =IF(G93>0,Assumptions!$D$43/G93,"never") -> never | H94: =IF(H93>0,Assumptions!$D$43/H93,"never") -> never | I94: =IF(I93>0,Assumptions!$D$43/I93,"never") -> never | J94: =IF(J93>0,Assumptions!$D$43/J93,"never") -> never | K94: =IF(K93>0,Assumptions!$D$43/K93,"never") -> never | L94: =K94 -> never
A95: 80 | B95: Care contribution per covered device per year | C95: Rs / year | D95: =IF(D46>0,D61*100/D46*4,0) -> -8.4333333 | E95: =IF(E46>0,E61*100/E46*4,0) -> -7.970543 | F95: =IF(F46>0,F61*100/F46*4,0) -> -7.5148683 | G95: =IF(G46>0,G61*100/G46*4,0) -> -6.9136242 | H95: =IF(H46>0,H61*100/H46*4,0) -> -6.2854093 | I95: =IF(I46>0,I61*100/I46*4,0) -> -5.4544026 | J95: =IF(J46>0,J61*100/J46*4,0) -> -4.6843247 | K95: =IF(K46>0,K61*100/K46*4,0) -> -3.6936616 | L95: =K95 -> -3.6936616
B96: Merchant view: a merchant on the paid plan who uses pay-later (Rs per month)
A97: 81 | B97: Merchant sales | C97: Rs / month | D97: =Assumptions!$D$12/(1-Assumptions!$D$47) -> 161290.32 | E97: =Assumptions!$D$12/(1-Assumptions!$D$47) -> 161290.32 | F97: =Assumptions!$D$12/(1-Assumptions!$D$47) -> 161290.32 | G97: =Assumptions!$D$12/(1-Assumptions!$D$47) -> 161290.32 | H97: =Assumptions!$D$12/(1-Assumptions!$D$47) -> 161290.32 | I97: =Assumptions!$D$12/(1-Assumptions!$D$47) -> 161290.32 | J97: =Assumptions!$D$12/(1-Assumptions!$D$47) -> 161290.32 | K97: =Assumptions!$D$12/(1-Assumptions!$D$47) -> 161290.32 | L97: =K97 -> 161290.32
A98: 82 | B98: Extra gross margin from the sales increase | C98: Rs / month | D98: =D97*Assumptions!$D$39*Assumptions!$D$47 -> 112.90323 | E98: =E97*Assumptions!$D$39*Assumptions!$D$47 -> 112.90323 | F98: =F97*Assumptions!$D$39*Assumptions!$D$47 -> 112.90323 | G98: =G97*Assumptions!$D$39*Assumptions!$D$47 -> 112.90323 | H98: =H97*Assumptions!$D$39*Assumptions!$D$47 -> 112.90323 | I98: =I97*Assumptions!$D$39*Assumptions!$D$47 -> 112.90323 | J98: =J97*Assumptions!$D$39*Assumptions!$D$47 -> 112.90323 | K98: =K97*Assumptions!$D$39*Assumptions!$D$47 -> 112.90323 | L98: =K98 -> 112.90323
A99: 83 | B99: Interest on pay-later used | C99: Rs / month | D99: =Assumptions!$D$12*Assumptions!$D$13*Assumptions!$D$17*Assumptions!$D$18*Assumptions!$D$48 -> 31.5 | E99: =Assumptions!$D$12*Assumptions!$D$13*Assumptions!$D$17*Assumptions!$D$18*Assumptions!$D$48 -> 31.5 | F99: =Assumptions!$D$12*Assumptions!$D$13*Assumptions!$D$17*Assumptions!$D$18*Assumptions!$D$48 -> 31.5 | G99: =Assumptions!$D$12*Assumptions!$D$13*Assumptions!$D$17*Assumptions!$D$18*Assumptions!$D$48 -> 31.5 | H99: =Assumptions!$D$12*Assumptions!$D$13*Assumptions!$D$17*Assumptions!$D$18*Assumptions!$D$48 -> 31.5 | I99: =Assumptions!$D$12*Assumptions!$D$13*Assumptions!$D$17*Assumptions!$D$18*Assumptions!$D$48 -> 31.5 | J99: =Assumptions!$D$12*Assumptions!$D$13*Assumptions!$D$17*Assumptions!$D$18*Assumptions!$D$48 -> 31.5 | K99: =Assumptions!$D$12*Assumptions!$D$13*Assumptions!$D$17*Assumptions!$D$18*Assumptions!$D$48 -> 31.5 | L99: =K99 -> 31.5
A100: 84 | B100: Paid plan fee | C100: Rs / month | D100: =Assumptions!$D$37 -> 49 | E100: =Assumptions!$D$37 -> 49 | F100: =Assumptions!$D$37 -> 49 | G100: =Assumptions!$D$37 -> 49 | H100: =Assumptions!$D$37 -> 49 | I100: =Assumptions!$D$37 -> 49 | J100: =Assumptions!$D$37 -> 49 | K100: =Assumptions!$D$37 -> 49 | L100: =K100 -> 49
A101: 85 | B101: Net gain per month | C101: Rs / month | D101: =D98-D99-D100 -> 32.403226 | E101: =E98-E99-E100 -> 32.403226 | F101: =F98-F99-F100 -> 32.403226 | G101: =G98-G99-G100 -> 32.403226 | H101: =H98-H99-H100 -> 32.403226 | I101: =I98-I99-I100 -> 32.403226 | J101: =J98-J99-J100 -> 32.403226 | K101: =K98-K99-K100 -> 32.403226 | L101: =K101 -> 32.403226
A102: 86 | B102: Plus: supplier money protected by Intent Guard | C102: Rs / month | D102: =Assumptions!$D$12*Assumptions!$D$13*Assumptions!$D$49 -> 30 | E102: =Assumptions!$D$12*Assumptions!$D$13*Assumptions!$D$49 -> 30 | F102: =Assumptions!$D$12*Assumptions!$D$13*Assumptions!$D$49 -> 30 | G102: =Assumptions!$D$12*Assumptions!$D$13*Assumptions!$D$49 -> 30 | H102: =Assumptions!$D$12*Assumptions!$D$13*Assumptions!$D$49 -> 30 | I102: =Assumptions!$D$12*Assumptions!$D$13*Assumptions!$D$49 -> 30 | J102: =Assumptions!$D$12*Assumptions!$D$13*Assumptions!$D$49 -> 30 | K102: =Assumptions!$D$12*Assumptions!$D$13*Assumptions!$D$49 -> 30 | L102: =K102 -> 30
...

Sheet Summary
B1: Summary: numbers for the projection slide
B2: All cells link to the Model and Baseline sheets.
B4: A. Base case, quarter by quarter
B5: Metric | C5: Unit | D5: Q4 FY27 | E5: Q1 FY28 | F5: Q2 FY28 | G5: Q3 FY28 | H5: Q4 FY28 | I5: Q1 FY29 | J5: Q2 FY29 | K5: Q3 FY29 | L5: 8-qtr total
B6: Baseline Paytm merchant GMV (FORECAST) | C6: Rs lakh crore | D6: =Model!D172 -> 7.9486905 | E6: =Model!E172 -> 8.2971429 | F6: =Model!F172 -> 8.6455952 | G6: =Model!G172 -> 8.9940476 | H6: =Model!H172 -> 9.3425 | I6: =Model!I172 -> 9.6909524 | J6: =Model!J172 -> 10.039405 | K6: =Model!K172 -> 10.387857 | L6: =Model!L172 -> 73.34619
B7: Incremental GMV from the bundle | C7: Rs crore | D7: =Model!D170 -> 207.88669 | E7: =Model!E170 -> 685.02223 | F7: =Model!F170 -> 1497.0271 | G7: =Model!G170 -> 2663.4943 | H7: =Model!H170 -> 4211.0854 | I7: =Model!I170 -> 5919.9223 | J7: =Model!J170 -> 7803.5397 | K7: =Model!K170 -> 9810.6006 | L7: =Model!L170 -> 32798.578
B8: of which supplier payments new to Paytm (Restock) | C8: Rs crore | D8: =Model!D116 -> 155.862 | E8: =Model!E116 -> 484.974 | F8: =Model!F116 -> 1004.724 | G8: =Model!G116 -> 1732.5 | H8: =Model!H116 -> 2685.69 | I8: =Model!I116 -> 3696.84 | J8: =Model!J116 -> 4765.95 | K8: =Model!K116 -> 5893.02 | L8: =Model!L116 -> 20419.56
B9: of which extra merchant sales (Restock) | C9: Rs crore | D9: =Model!D117 -> 6.7858286 | E9: =Model!E117 -> 21.114514 | F9: =Model!F117 -> 43.743086 | G9: =Model!G117 -> 75.428571 | H9: =Model!H117 -> 116.928 | I9: =Model!I117 -> 160.95086 | J9: =Model!J117 -> 207.49714 | K9: =Model!K117 -> 256.56686 | L9: =Model!L117 -> 889.01486
B10: of which kept during downtime (Care) | C10: Rs crore | D10: =Model!D149 -> 7.0685714 | E10: =Model!E149 -> 21.994286 | F10: =Model!F149 -> 45.565714 | G10: =Model!G149 -> 70.714286 | H10: =Model!H149 -> 97.44 | I10: =Model!I149 -> 117.36 | J10: =Model!J149 -> 138.33143 | K10: =Model!K149 -> 151.44571 | L10: =Model!L149 -> 649.92
B11: of which kept by lower device churn (Care) | C11: Rs crore | D11: =Model!D151 -> 38.170286 | E11: =Model!E151 -> 156.93943 | F11: =Model!F151 -> 402.99429 | G11: =Model!G151 -> 784.85143 | H11: =Model!H151 -> 1311.0274 | I11: =Model!I151 -> 1944.7714 | J11: =Model!J151 -> 2691.7611 | K11: =Model!K151 -> 3509.568 | L11: =Model!L151 -> 10840.083
B12: Uplift vs baseline GMV | C12: % | D12: =Model!D173 -> 0.00026153577 | E12: =Model!E173 -> 0.00082561219 | F12: =Model!F173 -> 0.0017315489 | G12: =Model!G173 -> 0.0029613967 | H12: =Model!H173 -> 0.0045074503 | I12: =Model!I173 -> 0.0061087105 | J12: =Model!J173 -> 0.0077729107 | K12: =Model!K173 -> 0.0094442968 | L12: =Model!L173 -> 0.0044717494
B13: Active Restock merchants | C13: lakh | D13: =Model!D111 -> 0.14137143 | E13: =Model!E111 -> 0.43988571 | F13: =Model!F111 -> 0.91131429 | G13: =Model!G111 -> 1.5714286 | H13: =Model!H111 -> 2.436 | I13: =Model!I111 -> 3.3531429 | J13: =Model!J111 -> 4.3228571 | K13: =Model!K111 -> 5.3451429 | L13: =Model!L111 -> 5.3451429
B14: Devices covered by Soundbox Care | C14: lakh | D14: =Model!D144 -> 8.8357143 | E14: =Model!E144 -> 27.492857 | F14: =Model!F144 -> 56.957143 | G14: =Model!G144 -> 88.392857 | H14: =Model!H144 -> 121.8 | I14: =Model!I144 -> 146.7 | J14: =Model!J144 -> 172.91429 | K14: =Model!K144 -> 189.30714 | L14: =Model!L144 -> 189.30714
B15: Credit routed (pay-later + working capital) | C15: Rs crore | D15: =Model!D126 -> 51.688929 | E15: =Model!E126 -> 160.83321 | F15: =Model!F126 -> 333.19929 | G15: =Model!G126 -> 574.55357 | H15: =Model!H126 -> 890.6625 | I15: =Model!I126 -> 1225.9929 | J15: =Model!J126 -> 1580.5446 | K15: =Model!K126 -> 1954.3179 | L15: =Model!L126 -> 6771.7929
B16: Revenue | C16: Rs crore | D16: =Model!D174 -> 0.56767874 | E16: =Model!E174 -> 1.8388901 | F16: =Model!F174 -> 3.9575788 | G16: =Model!G174 -> 6.9920231 | H16: =Model!H174 -> 11.013329 | I16: =Model!I174 -> 15.419372 | J16: =Model!J174 -> 20.224083 | K16: =Model!K174 -> 25.343284 | L16: =Model!L174 -> 85.356238
B17: of which credit (pay-later take + working-capital loans) | C17: Rs crore | D17: =Model!D128+Model!D129 -> 0.31212161 | E17: =Model!E128+Model!E129 -> 0.97118518 | F17: =Model!F128+Model!F129 -> 2.0120111 | G17: =Model!G128+Model!G129 -> 3.4694196 | H17: =Model!H128+Model!H129 -> 5.3782312 | I17: =Model!I128+Model!I129 -> 7.4031107 | J17: =Model!J128+Model!J129 -> 9.544058 | K17: =Model!K128+Model!K129 -> 11.801073 | L17: =Model!L128+Model!L129 -> 40.891211
B18: of which MDR on supplier payments | C18: Rs crore | D18: =Model!D130 -> 0.0935172 | E18: =Model!E130 -> 0.2909844 | F18: =Model!F130 -> 0.6028344 | G18: =Model!G130 -> 1.0395 | H18: =Model!H130 -> 1.611414 | I18: =Model!I130 -> 2.218104 | J18: =Model!J130 -> 2.85957 | K18: =Model!K130 -> 3.535812 | L18: =Model!L130 -> 12.251736
B19: of which paid plan | C19: Rs crore | D19: =Model!D131 -> 0.083974629 | E19: =Model!E131 -> 0.26129211 | F19: =Model!F131 -> 0.54132069 | G19: =Model!G131 -> 0.93342857 | H19: =Model!H131 -> 1.446984 | I19: =Model!I131 -> 1.9917669 | J19: =Model!J131 -> 2.5677771 | K19: =Model!K131 -> 3.1750149 | L19: =Model!L131 -> 11.001559
B20: of which device subscriptions kept (Care) | C20: Rs crore | D20: =Model!D152 -> 0.057255429 | E20: =Model!E152 -> 0.23540914 | F20: =Model!F152 -> 0.60449143 | G20: =Model!G152 -> 1.1772771 | H20: =Model!H152 -> 1.9665411 | I20: =Model!I152 -> 2.9171571 | J20: =Model!J152 -> 4.0376417 | K20: =Model!K152 -> 5.264352 | L20: =Model!L152 -> 16.260125
B21: Variable cost | C21: Rs crore | D21: =Model!D175 -> 0.89705915 | E21: =Model!E175 -> 2.437825 | F21: =Model!F175 -> 4.6829451 | G21: =Model!G175 -> 7.3002098 | H21: =Model!H175 -> 10.310838 | I21: =Model!I175 -> 12.672197 | J21: =Model!J175 -> 15.156856 | K21: =Model!K175 -> 17.319389 | L21: =Model!L175 -> 70.777319
B22: Avoided costs (Care: field visits, replacements) | C22: Rs crore | D22: =Model!D176 -> 0.88798929 | E22: =Model!E176 -> 2.7630321 | F22: =Model!F176 -> 5.7241929 | G22: =Model!G176 -> 8.8834821 | H22: =Model!H176 -> 12.2409 | I22: =Model!I176 -> 14.74335 | J22: =Model!J176 -> 17.377886 | K22: =Model!K176 -> 19.025368 | L22: =Model!L176 -> 81.6462
B23: Contribution to Paytm | C23: Rs crore | D23: =Model!D177 -> 0.55860888 | E23: =Model!E177 -> 2.1640973 | F23: =Model!F177 -> 4.9988266 | G23: =Model!G177 -> 8.5752954 | H23: =Model!H177 -> 12.94339 | I23: =Model!I177 -> 17.490525 | J23: =Model!J177 -> 22.445112 | K23: =Model!K177 -> 27.049264 | L23: =Model!L177 -> 96.22512
B24: of which Restock Agent | C24: Rs crore | D24: =Model!D140 -> -0.051302808 | E24: =Model!E140 -> 0.19379679 | F24: =Model!F140 -> 0.76900403 | G24: =Model!G140 -> 1.7080241 | H24: =Model!H140 -> 3.0445623 | I24: =Model!I140 -> 4.8731654 | J24: =Model!J140 -> 6.8141193 | K24: =Model!K140 -> 8.8674239 | L24: =Model!L140 -> 26.218793
B25: of which Soundbox Care | C25: Rs crore | D25: =Model!D159 -> 0.60991169 | E25: =Model!E159 -> 1.9703005 | F25: =Model!F159 -> 4.2298226 | G25: =Model!G159 -> 6.8672713 | H25: =Model!H159 -> 9.8988281 | I25: =Model!I159 -> 12.61736 | J25: =Model!J159 -> 15.630993 | K25: =Model!K159 -> 18.18184 | L25: =Model!L159 -> 70.006327
B26: Contribution as % of revenue plus avoided costs | C26: % | D26: =Model!D179 -> 0.38374744 | E26: =Model!E179 -> 0.47025942 | F26: =Model!F179 -> 0.51631321 | G26: =Model!G179 -> 0.5401589 | H26: =Model!H179 -> 0.55660373 | I26: =Model!I179 -> 0.57987225 | J26: =Model!J179 -> 0.59691323 | K26: =Model!K179 -> 0.60964808 | L26: =Model!L179 -> 0.57618991
B27: Restock margin on Restock revenue | C27: % | D27: =Model!D180 -> -0.10420458 | E27: =Model!E180 -> 0.12650685 | F27: =Model!F180 -> 0.242308 | G27: =Model!G180 -> 0.31210927 | H27: =Model!H180 -> 0.35888466 | I27: =Model!I180 -> 0.41731732 | J27: =Model!J180 -> 0.45263295 | K27: =Model!K180 -> 0.47637117 | L27: =Model!L180 -> 0.40649221
B28: Care: avoided costs plus revenue per Rs 1 of Care cost | C28: x | D28: =Model!D181 -> 2.7257 | E28: =Model!E181 -> 2.7916476 | F28: =Model!F181 -> 2.8565813 | G28: =Model!G181 -> 2.9422585 | H28: =Model!H181 -> 3.0317792 | I28: =Model!I181 -> 3.1501976 | J28: =Model!J181 -> 3.2599337 | K28: =Model!K181 -> 3.4011032 | L28: =Model!L181 -> 3.154306
B29: Quarterly contribution vs Q1 FY27 EBITDA (Rs 203 crore) | C29: % | D29: =Model!D184 -> 0.0027517679 | E29: =Model!E184 -> 0.010660578 | F29: =Model!F184 -> 0.024624762 | G29: =Model!G184 -> 0.042242834 | H29: =Model!H184 -> 0.063760544 | I29: =Model!I184 -> 0.086160222 | J29: =Model!J184 -> 0.11056706 | K29: =Model!K184 -> 0.1332476
B30: Merchant money protected by Intent Guard | C30: Rs crore | D30: =Model!D141 -> 0.7422 | E30: =Model!E141 -> 2.3094 | F30: =Model!F141 -> 4.7844 | G30: =Model!G141 -> 8.25 | H30: =Model!H141 -> 12.789 | I30: =Model!I141 -> 17.604 | J30: =Model!J141 -> 22.695 | K30: =Model!K141 -> 28.062 | L30: =Model!L141 -> 97.236
B32: B. Scenarios side by side
B33: Metric | C33: Unit | D33: Bear | E33: Base | F33: Bull
B34: Incremental GMV, 8 quarters | C34: Rs crore | D34: =Model!L72 -> 6006.46 | E34: =Model!L170 -> 32798.578 | F34: =Model!L268 -> 143347.9
B35: Incremental GMV in Q3 FY29 | C35: Rs crore | D35: =Model!K72 -> 1884.7348 | E35: =Model!K170 -> 9810.6006 | F35: =Model!K268 -> 42038.146
B36: Uplift vs baseline GMV at Q3 FY29 | C36: % | D36: =Model!K75 -> 0.0018143634 | E36: =Model!K173 -> 0.0094442968 | F36: =Model!K271 -> 0.040468544
B37: Contribution to Paytm, 8 quarters | C37: Rs crore | D37: =Model!L79 -> -27.416841 | E37: =Model!L177 -> 96.22512 | F37: =Model!L275 -> 601.42431
B38: of which Restock Agent | C38: Rs crore | D38: =Model!L42 -> -16.397504 | E38: =Model!L140 -> 26.218793 | F38: =Model!L238 -> 443.52232
B39: of which Soundbox Care | C39: Rs crore | D39: =Model!L61 -> -11.019337 | E39: =Model!L159 -> 70.006327 | F39: =Model!L257 -> 157.90199
B40: Contribution in Q3 FY29 | C40: Rs crore | D40: =Model!K79 -> -5.6999005 | E40: =Model!K177 -> 27.049264 | F40: =Model!K275 -> 169.50298
B41: Q3 FY29 contribution vs Q1 FY27 EBITDA | C41: % | D41: =Model!K86 -> -0.028078328 | E41: =Model!K184 -> 0.1332476 | F41: =Model!K282 -> 0.83499007
B42: Contribution as % of revenue plus avoided costs, 8 quarters | C42: % | D42: =Model!L81 -> -0.51390898 | E42: =Model!L179 -> 0.57618991 | F42: =Model!L277 -> 0.91070392
B43: Restock margin on Restock revenue, 8 quarters | C43: % | D43: =Model!L82 -> -4.7681826 | E43: =Model!L180 -> 0.40649221 | F43: =Model!L278 -> 0.91213754
B44: Care: avoided costs plus revenue per Rs 1 of Care cost, 8 quarters | C44: x | D44: =Model!L83 -> 0.81914759 | E44: =Model!L181 -> 3.154306 | F44: =Model!L279 -> 10.718242
B45: Share of incremental GMV from supplier payments, 8 quarters | C45: % | D45: =Model!L84 -> 0.20813876 | E45: =Model!L182 -> 0.62257455 | F45: =Model!L280 -> 0.8108065
B46: Revenue, 8 quarters | C46: Rs crore | D46: =Model!L76 -> 12.526505 | E46: =Model!L174 -> 85.356238 | F46: =Model!L272 -> 522.6932
B47: MDR on supplier payments, 8 quarters | C47: Rs crore | D47: =Model!L32 -> 0 | E47: =Model!L130 -> 12.251736 | F47: =Model!L228 -> 130.75583
B48: Active Restock merchants at Q3 FY29 | C48: lakh | D48: =Model!K13 -> 2.0044286 | E48: =Model!K111 -> 5.3451429 | F48: =Model!K209 -> 10.022143
B49: Credit routed, 8 quarters | C49: Rs crore | D49: =Model!L28 -> 414.98936 | E49: =Model!L126 -> 6771.7929 | F49: =Model!L224 -> 44081.767
B50: New Paytm GMV per active Restock merchant per month | C50: Rs / month | D50: =Model!K91 -> 6500 | E50: =Model!K189 -> 38350 | F50: =Model!K287 -> 115162.5
B51: North Star uplift per active Restock merchant | C51: % | D51: =Model!K92 -> 0.13 | E51: =Model!K190 -> 0.479375 | F51: =Model!K288 -> 0.9596875
B52: Restock contribution per active merchant per month | C52: Rs / month | D52: =Model!K93 -> -40.217292 | E52: =Model!K191 -> 71.236875 | F52: =Model!K289 -> 440.15094
B53: Months to recover onboarding cost | C53: months | D53: =Model!K94 -> never | E53: =Model!K192 -> 3.5094184 | F53: =Model!K290 -> 0.34079219
B54: Care contribution per covered device per year | C54: Rs / year | D54: =Model!K95 -> -3.6936616 | E54: =Model!K193 -> 38.417652 | F54: =Model!K291 -> 84.6043
B55: Merchant net gain per month (paid plan + pay-later) | C55: Rs / month | D55: =Model!K101 -> 32.403226 | E55: =Model!K199 -> 204.09924 | F55: =Model!K297 -> 551.56531
B56: Merchant money protected by Intent Guard, 8 quarters | C56: Rs crore | D56: =Model!L43 -> 6.2508857 | E56: =Model!L141 -> 97.236 | F56: =Model!L239 -> 546.9525
B57: Nearby contribution if switched on, 8 quarters | C57: Rs crore | D57: =Model!L70 -> 1.8256945 | E57: =Model!L168 -> 35.53292 | F57: =Model!L266 -> 157.67097
B58: Nearby GMV new to Paytm if switched on, 8 quarters | C58: Rs crore | D58: =Model!L66 -> 22.707643 | E58: =Model!L164 -> 272.49171 | F58: =Model!L262 -> 1335.2094
B60: C. Context
B61: Baseline GMV, Q1 FY27 actual | C61: Rs lakh crore | D61: =Baseline!E12 -> 7.1
B62: Baseline GMV, Q3 FY29 FORECAST (linear) | C62: Rs lakh crore | D62: =Baseline!E22 -> 10.387857
B63: Baseline GMV, Q3 FY29 GROWTH cross-check | C63: Rs lakh crore | D63: =Baseline!G22 -> 12.851426
B64: Device merchants, Q3 FY29 FORECAST | C64: crore | D64: =Baseline!H22 -> 2.2271429
B65: Q1 FY27 contribution profit | C65: Rs crore | D65: =Baseline!F27 -> 1350
B66: Q1 FY27 EBITDA | C66: Rs crore | D66: =Baseline!F29 -> 203
B67: Q1 FY27 financial services revenue | C67: Rs crore | D67: =Baseline!F31 -> 814
B68: Mohalla Network (dropped): base contribution over the same 8 quarters | C68: Rs crore | D68: =Baseline!F41 -> 29.52
B69: This bundle's base contribution as a multiple of Mohalla's | C69: x | D69: =IF(Baseline!F41>0,Model!L177/Baseline!F41,0) -> 3.2596585
B70: Restock credit revenue at Q3 FY29 vs Q1 FY27 financial services revenue | C70: % | D70: =Model!K186 -> 0.014497633
B71: Net payment revenue from a 1% GMV lift, blended rate (Q1 FY27 base) | C71: Rs crore / quarter | D71: =Baseline!F35 -> 6.01
B73: D. Checks
B74: Rail mix adds up to 100% (Bear, Base, Bull) | D74: =Assumptions!D84 -> OK | E74: =Assumptions!E84 -> OK | F74: =Assumptions!F84 -> OK
B75: Pay-later stays within orders paid through Paytm (Bear, Base, Bull) | D75: =Assumptions!D85 -> OK | E75: =Assumptions!E85 -> OK | F75: =Assumptions!F85 -> OK

Sheet Sources
A1: Sources
A3: ID | B3: What it supports | C3: Link
A4: S1 | B4: Paytm Q1 FY27 earnings release (agent datapack): GMV Jun-25 / Mar-26 / Jun-26, subscription merchants, net payment revenue 8.4 bps, processing margin >4 bps, Marketing Services Rs 239 crore, cashback Rs 90 crore, registered merchants | C4: https://paytm.com/document/ir/financial-results/fy2026-27/Paytm_Q1_FY27_Agent_Datapack.md
A5: S2 | B5: Q2 FY26 (Sep-25): GMV Rs 5.67 lakh crore, subscriptions 1.37 crore | C5: https://ianslive.in/paytms-profitability-improves-to-rs-211-crore-in-q2-revenue-up-24-pc--20251104222037
A6: S3 | B6: Q3 FY26 (Dec-25): GMV Rs 6.2 lakh crore | C6: https://www.businesstoday.in/amp/latest/corporate/story/paytms-q3-net-profit-jumps-to-rs225-crore-on-upi-surge-and-merchant-services-boost-513573-2026-01-29
A7: S4 | B7: Q4 FY25 (Mar-25): GMV Rs 5.1 lakh crore, subscriptions 1.24 crore | C7: https://www.business-standard.com/companies/quarterly-results/one-97-communication-paytm-q4-fy25-result-loss-profit-revenue-stock-option-125050601030_1.html
A8: S5 | B8: Q3 FY25 (Dec-24): GMV Rs 5.0 lakh crore, up 13% QoQ from Rs 4.5 lakh crore; subscriptions 1.17 crore after 5 lakh QoQ additions | C8: https://inc42.com/?p=495669
A9: S6 | B9: Q3 FY26 (Dec-25): subscription merchants 1.44 crore | C9: https://alphastreet.com/india/symbol/PAYTM
A10: S7 | B10: Soundbox rental Rs 125-150 a month (BofA merchant checks in Mumbai) | C10: https://www.outlookbusiness.com/amp/story/enterprise/bofa-research-paytm-soundbox-first-to-bring-audio-based-payments-confirmations-dominates-the-market-6795
A11: S8 | B11: Paytm subscription revenue ~Rs 90 per device a month (Q4 FY24) | C11: https://www.medianama.com/2024/10/223-paytm-to-monetize-soundbox-ads-in-partnership-with-meesho-a-shift-away-from-core-payments-business/
A12: S9 | B12: Merchants often keep separate soundboxes for PhonePe, Paytm and Google Pay | C12: https://inc42.com/buzz/upi-transactions-jump-3-8-mom-in-may-cross-23-bn-mark/
A13: S10 | B13: Paytm Q1 FY27 results: revenue Rs 2,448 crore, contribution profit Rs 1,350 crore at 55%, EBITDA Rs 203 crore, PAT Rs 220 crore, financial services Rs 814 crore (+45%), 1.57 crore device merchants, online payment aggregator licence and online merchant momentum | C13: https://paytm.com/blog/investor-relations/paytm-q1-fy27-results-revenue-grows-28-to-2448-crore-highest-ever-quarterly-ebitda-at-203-crore/
A14: S11 | B14: Paytm merchant loans: up to Rs 10 lakh, 6-24 months, daily instalments; over 50% of merchant-loan value to repeat borrowers (Paytm-Piramal release, Aug 2022) | C14: https://bseindia.com/xml-data/corpfiling/AttachHis/01144943-65d3-465d-a4cc-f0556ff55ec5.pdf
... A31: S28 | B31: NPCI agentic payments on UPI (reported Unified Agent Protocol), Sep 2026 | C31: https://inc42.com/buzz/npci-to-launch-agentic-payments-on-upi-report/
